Workbook

Sheet Ações InCompany
A1: ID | B1: Ano | C1: Status Evento | D1: Processo | E1: Curso | F1: Público-Alvo | G1: Programa | H1: Data TXT | I1: Início | J1: Término | K1: Modalidade | L1: Valor instrutoria | M1: Nota Av. Reação | N1: Qtd Vagas | O1: P. Servidores | P1: P. Jurisdicionados | Q1: P. Sociedade | R1: Total Part. | S1: C.H. | T1: Instrutor
A2: 2014-001 | B2: 2014 | C2: Realizado | E2: CURSO DE ELABORAÇÃO DE PARECERES E RELATÓRIOS | F2: Servidores do TCDF | G2: Metodologias de Auditoria e Fiscalização | H2: 17 a 21/03/2014 | I2: 41715 | J2: 41719 | K2: Instrutoria Externa | L2: 19500 | O2: 20 | R2: =SUM(O2:Q2) -> 20 | S2: 20
A3: 2014-002 | B3: 2014 | C3: Realizado | D3: procu | E3: ELABORAÇÃO DE PLANO DE AUDITORIA E MATRIZ DE PLANEJAMENTO | F3: Servidores do TCDF | G3: Metodologias de Auditoria e Fiscalização | H3: 14 e 14/04/2014 | I3: 41743 | J3: 41744 | K3: Instrutoria Externa | L3: 28000 | O3: 16 | R3: =SUM(O3:Q3) -> 16 | S3: 16
A4: 2014-003 | B4: 2014 | C4: Realizado | E4: CURSO DE EXCEL AVANÇADO | F4: Servidores do TCDF | G4: Mineração e Análise de Dados | H4: 02 a 09/06/2014 | I4: 41792 | J4: 41799 | K4: Instrutoria Interna | L4: 2991 | O4: 24 | R4: =SUM(O4:Q4) -> 24 | S4: 24
A5: 2014-004 | B5: 2014 | C5: Realizado | E5: REGIME DIFERENCIADO DE CONTRATAÇÕES PÚBLICAS - RDC | F5: Servidores do TCDF | G5: Administração, Estratégia e Inovação | H5: 24 e 25/06/2014 | I5: 41814 | J5: 41815 | K5: Instrutoria Externa | L5: 41341.16 | O5: 16 | R5: =SUM(O5:Q5) -> 16 | S5: 16
A6: 2014-005 | B6: 2014 | C6: Realizado | E6: ENGENHARIA ECONÔMICA I E II - CAPACITAÇÃO EM PARCERIAS PÚBLICO PRIVADAS E CONCESSÕES DE | F6: Servidores do TCDF | G6: Metodologias de Auditoria e Fiscalização | H6: 04 a 08/08/2014 | I6: 41855 | J6: 41859 | K6: Instrutoria Externa | L6: 54900 | O6: 40 | R6: =SUM(O6:Q6) -> 40 | S6: 40
A7: 2014-006 | B7: 2014 | C7: Realizado | E7: CURSO TÉCNICAS DE AUDITORIA OPERACIONAL | F7: Servidores do TCDF | G7: Metodologias de Auditoria e Fiscalização | H7: 10/09/2014 | I7: 41892 | J7: 41892 | K7: Instrutoria Externa | L7: 15000 | O7: 30 | R7: =SUM(O7:Q7) -> 30 | S7: 30
A8: 2014-007 | B8: 2014 | C8: Realizado | F8: Servidores do TCDF | G8: Metodologias de Auditoria e Fiscalização | H8: 31/10/2014 | I8: 41943 | J8: 41943 | K8: Instrutoria Externa | L8: 33260 | O8: 24 | R8: =SUM(O8:Q8) -> 24 | S8: 24
A9: 2014-008 | B9: 2014 | C9: Realizado | E9: PROCESSO DE CONTRATAÇÃO PÚBLICA | F9: Servidores do TCDF | G9: Administração, Estratégia e Inovação | H9: 10 a 14/11/2014 | I9: 41953 | J9: 41957 | K9: Instrutoria Interna | L9: 4353.54 | P9: 37 | R9: =SUM(O9:Q9) -> 37 | S9: 8
A10: 2014-009 | B10: 2014 | C10: Realizado | E10: TERMO DE REFERÊNCIA DE SERVIÇOS CONTINUADOS COM DEDICAÇÃO EXCLUSIVA DE MÃO DE OBRA | F10: Servidores do TCDF | G10: Metodologias de Auditoria e Fiscalização | H10: 24 a 28/11/2014 | I10: 41967 | J10: 41971 | K10: Instrutoria Interna | L10: 4353.54 | P10: 58 | R10: =SUM(O10:Q10) -> 58 | S10: 20
A11: 2015-001 | B11: 2015 | C11: Realizado | D11: 1683/2015 | E11: ELABORAÇÃO DE PARECERES E RELATÓRIOS | F11: Servidores do TCDF | G11: Metodologias de Auditoria e Fiscalização | H11: 23 a 27/03/2015 | I11: 42086 | J11: 42090 | K11: Instrutoria Externa | L11: 23500 | O11: 25 | R11: =SUM(O11:Q11) -> 25 | S11: 20 | T11: José Paulo Moreira de Oliveira
A12: 2015-002 | B12: 2015 | C12: Realizado | D12: 3716/2015 | E12: O PROCESSO DE CONTRATAÇÃO PÚBLICA | F12: Jurisdicionados | G12: Administração, Estratégia e Inovação | H12: 06 a 10/04/2015 | I12: 42100 | J12: 42104 | K12: Instrutoria Interna | L12: 4992.74 | P12: 85 | R12: =SUM(O12:Q12) -> 85 | S12: 20 | T12: Amauri Alves Nery
A13: 2015-003 | B13: 2015 | C13: Realizado | D13: 5891/2015 | E13: AUDITORIA EM OBRAS RODOVIÁRIAS | F13: Servidores do TCDF | G13: Áreas Temáticas de Fiscalização do Setor Público | H13: 06 a 10/04/2015 | I13: 42100 | J13: 42104 | K13: Instrutoria Externa | L13: 29000 | O13: 19 | R13: =SUM(O13:Q13) -> 19 | S13: 40 | T13: Elci Pessoa Júnior
A14: 2015-004 | B14: 2015 | C14: Realizado | D14: 2515/2015 | E14: TERMO DE REFERÊNCIA DE SERVIÇOS CONTINUADOS COM DEDICAÇÃO EXCLUSIVA DE MÃO DE OBRA | F14: Jurisdicionados | G14: Treinamento de Jurisdicionados | H14: 13 a 17/04/2015 | I14: 42107 | J14: 42111 | K14: Instrutoria Interna | L14: 4447.52 | P14: 89 | R14: =SUM(O14:Q14) -> 89 | S14: 20 | T14: Leonardo José Alves Leal Neri
A15: 2015-005 | B15: 2015 | C15: Realizado | D15: 7690/2015 | E15: FISCALIZAÇÃO DE CONTRATOS ADMINISTRATIVOS | F15: Servidores do TCDF | G15: Administração, Estratégia e Inovação | H15: 16, 17, 22, 23 e 24/04/2020 | I15: 42110 | J15: 42118 | K15: Instrutoria Interna | L15: 4447.52 | O15: 37 | R15: =SUM(O15:Q15) -> 37 | S15: 30 | T15: Leonardo José Alves Leal Neri
A16: 2015-006 | B16: 2015 | C16: Realizado | E16: PALESTRA CONSELHOS REGIONAIS DE SAÚDE | F16: Sociedade | G16: N/A | I16: 42122 | J16: 42122 | K16: Instrutoria Interna | L16: 0 | O16: 0 | P16: 0 | Q16: 0 | R16: =SUM(O16:Q16) -> 0 | S16: 5
A17: 2015-007 | B17: 2015 | C17: Realizado | D17: 3481/2015 | E17: PROCESSO NOS TRIBUNAIS DE CONTAS | F17: Servidores do TCDF | G17: Metodologias de Auditoria e Fiscalização | H17: 26 a 29/05/2015 | I17: 42129 | J17: 42132 | K17: Instrutoria Externa | L17: 35500 | O17: 30 | R17: =SUM(O17:Q17) -> 30 | S17: 16 | T17: Odilon Cavallari de Oliveira
A18: 2015-008 | B18: 2015 | C18: Realizado | D18: 5654/2015 | E18: A NOVA CONTABILIDADE APLICADA AO SETOR PÚBLICO | F18: Servidores do TCDF | G18: Administração, Estratégia e Inovação | H18: 11 a 15/05/2015 | I18: 42135 | J18: 42139 | K18: Instrutoria Interna | L18: 4992.74 | O18: 30 | R18: =SUM(O18:Q18) -> 30 | S18: 20 | T18: Romildo Araújo da Silva
A19: 2015-009 | B19: 2015 | C19: Realizado | D19: 14060/2015 | E19: TREINAMENTO DO SISTEMA TERRAGEO | F19: Servidores do TCDF | G19: Administração, Estratégia e Inovação | H19: 22/05/2015 | I19: 42146 | J19: 42146 | K19: Instrutoria Externa | L19: 0 | O19: 15 | R19: =SUM(O19:Q19) -> 15 | S19: 8 | T19: INSTRUTOR EXTERNO TERRACAP
A20: 2015-010 | B20: 2015 | C20: Realizado | D20: 1098/2015 | E20: EXCEL AVANÇADO | F20: Servidores do TCDF | G20: Mineração e Análise de Dados | H20: 25/05 a 01/06/2015 | I20: 42149 | J20: 42156 | K20: Instrutoria Externa | L20: 2630 | O20: 14 | R20: =SUM(O20:Q20) -> 14 | S20: 24 | T20: Logus TI
A21: 2015-011 | B21: 2015 | C21: Realizado | D21: 12742/2015 | E21: TREINAMENTO SIGGO (Sistema Integrado de Contabilidade Governamental) | F21: Servidores do TCDF | G21: Administração, Estratégia e Inovação | H21: 08 a 12/06/2015 | I21: 42163 | J21: 42167 | K21: Instrutoria Interna | L21: 0 | O21: 14 | R21: =SUM(O21:Q21) -> 14 | S21: 20 | T21: Rômulo Miranda Alvim
A22: 2015-012 | B22: 2015 | C22: Realizado | D22: 13480/2015 | E22: GESTÃO E FISCALIZAÇÃO DE CONTRATOS ADMINISTRATIVOS - MÓDULO I | F22: Jurisdicionados | G22: Treinamento de Jurisdicionados | H22: 15 a 19/06/2015 | I22: 42170 | J22: 42174 | K22: Instrutoria Interna | L22: 4447.52 | P22: 49 | R22: =SUM(O22:Q22) -> 49 | S22: 20 | T22: Roberto Dias Santiago
A23: 2015-013 | B23: 2015 | C23: Realizado | D23: 19283/2015 | E23: SEMINÁRIO ATUALIZAÇÃO EM LEGISLAÇÃO DE PESSOAL | F23: Servidores do TCDF | G23: Administração, Estratégia e Inovação | H23: 05 e 07/08/2015 | I23: 42221 | J23: 42223 | K23: Instrutoria Interna | L23: 0 | O23: 43 | R23: =SUM(O23:Q23) -> 43 | S23: 8 | T23: Inácio Magalhães Filho
A24: 2015-014 | B24: 2015 | C24: Realizado | D24: 22314/2015 | E24: METODOLOGIA DE CONSTRUÇÃO E ATUALIZAÇÃO DO TESAURO DE CONTAS DO DF | F24: Servidores do TCDF | G24: Mineração e Análise de Dados | H24: 24 a 28/08/2015 | I24: 42240 | J24: 42244 | K24: Instrutoria Interna | L24: 2702.38 | O24: 25 | R24: =SUM(O24:Q24) -> 25 | S24: 20 | T24: ANDREA FORTALEZA BRANDES DE SOUZA
A25: 2015-015 | B25: 2015 | C25: Realizado | D25: 17949/2015 | E25: RESPONSABILIDADE DE AGENTES PÚBLICOS E PRIVADOS PERANTE OS TRIBUNAIS DE CONTAS | F25: Servidores do TCDF | G25: Treinamento de Jurisdicionados | H25: 31/08/2015 a 04/09/2015 | I25: 42247 | J25: 42251 | K25: Instrutoria Externa | L25: 33600 | O25: 35 | R25: =SUM(O25:Q25) -> 35 | S25: 20 | T25: Aprimora Treinamentos
A26: 2015-016 | B26: 2015 | C26: Realizado | D26: 23973/2015 | E26: TÉCNICAS DE AUDITORIA OPERACIONAL | F26: Servidores do TCDF | G26: Metodologias de Auditoria e Fiscalização | H26: 14 a 18/09/2015 | I26: 42261 | J26: 42265 | K26: Instrutoria Externa | L26: 15000 | O26: 35 | R26: =SUM(O26:Q26) -> 35 | S26: 25 | T26: Dagomar Henrique Limas
A27: 2015-017 | B27: 2015 | C27: Realizado | E27: LEGISLAÇÃO DE PESSOAL NO SETOR PÚBLICO COM ENFOQUE NA LC nº 840/2011 | F27: Jurisdicionados | G27: N/A | I27: 42268 | J27: 42272 | K27: Instrutoria Interna | L27: 4447.52 | O27: 87 | R27: =SUM(O27:Q27) -> 87
A28: 2015-018 | B28: 2015 | C28: Realizado | D28: 29327/2015 | E28: CAPACITAÇÃO PARA CONSELHEIROS DE SAÚDE - Turma I | F28: Sociedade | G28: Treinamento de Jurisdicionados | H28: 29/09/2015 a 02/10/2015 | I28: 42276 | J28: 42279 | K28: Instrutoria Interna | L28: 4076.52 | Q28: 46 | R28: =SUM(O28:Q28) -> 46 | S28: 20 | T28: Romildo Araújo da Silva; Tarsila Firmino Ely
A29: 2015-019 | B29: 2015 | C29: Realizado | D29: 30040/2015 | E29: OFICINA DE ACCESS AVANÇADO | F29: Servidores do TCDF | G29: Mineração e Análise de Dados | H29: 05 a 09/10/2015 | I29: 42282 | J29: 42286 | K29: Instrutoria Interna | L29: 4447.52 | O29: 15 | R29: =SUM(O29:Q29) -> 15 | S29: 20 | T29: JOSDEYVI MAGALHAES RUSSI
A30: 2015-020 | B30: 2015 | C30: Realizado | D30: 13480/2015 | E30: GESTÃO E FISCALIZAÇÃO DE CONTRATOS ADMINISTRATIVOS - MÓDULO II | F30: Jurisdicionados | G30: Treinamento de Jurisdicionados | H30: 19 a 23/10/2015 | I30: 42296 | J30: 42300 | K30: Instrutoria Interna | L30: 4447.52 | P30: 54 | R30: =SUM(O30:Q30) -> 54 | S30: 20 | T30: Roberto Dias Santiago
A31: 2015-021 | B31: 2015 | C31: Realizado | E31: CONTRATAÇÃO DE SOLUÇÕES DE TECNOLOGIA DA INFORMAÇÃO E COMUNICAÇÃO - IN nº 04/2014 | F31: Jurisdicionados | G31: N/A | I31: 42303 | J31: 42305 | K31: Instrutoria Interna | L31: 4447.52 | O31: 52 | R31: =SUM(O31:Q31) -> 52 | S31: 0
A32: 2015-022 | B32: 2015 | C32: Realizado | D32: 29327/2015 | E32: CAPACITAÇÃO PARA CONSELHEIROS DE SAÚDE - Turma II | F32: Sociedade | G32: Treinamento de Jurisdicionados | H32: 17 a 20/11/2015 | I32: 42325 | J32: 42328 | K32: Instrutoria Interna | L32: 4076.52 | Q32: 46 | R32: =SUM(O32:Q32) -> 46 | S32: 20 | T32: Romildo Araújo da Silva; Tarsila Firmino Ely
A33: 2016-001 | B33: 2016 | C33: Realizado | D33: 13946/2016 | E33: Sistema Channel - Turma 1 | F33: Servidores do TCDF | G33: N/A | I33: 42495 | K33: Instrutoria Externa | L33: 0 | O33: 14 | R33: =SUM(O33:Q33) -> 14 | S33: 8 | T33: Breno
A34: 2016-002 | B34: 2016 | C34: Realizado | E34: Instrutoria | F34: Servidores do TCDF | G34: N/A | I34: 42495 | K34: Instrutoria Externa | L34: 22500 | O34: 25 | R34: =SUM(O34:Q34) -> 25 | S34: 20
A35: 2016-003 | B35: 2016 | C35: Realizado | D35: 30532/2016; 28880/2016 | E35: Trilhas de Aprendizagem | F35: Servidores do TCDF | G35: N/A | I35: 42495 | K35: Instrutoria Externa | L35: 25200 | O35: 17 | R35: =SUM(O35:Q35) -> 17 | S35: 20 | T35: Pedro Paulo Carbone; Sylvio Maestrelli; Anelise Pereira Sihler
A36: 2016-004 | B36: 2016 | C36: Realizado | D36: 8721/2016 | E36: Termo de Referência de Serviços Continuados com dedicação exclusiva de mão de obra | F36: Jurisdicionados | G36: Treinamento de Jurisdicionados | H36: 16 a 20/05/2016 | I36: 42506 | J36: 42510 | K36: Instrutoria Interna | L36: 6671.48 | P36: 75 | R36: =SUM(O36:Q36) -> 75 | S36: 20 | T36: Leonardo José Alves Leal Neri
A37: 2016-005 | B37: 2016 | C37: Realizado | D37: 16866/2016 | E37: Workshop para prefeitos comunitários | F37: Sociedade | G37: Treinamento de Jurisdicionados | H37: 13/06/2016 | I37: 42534 | J37: 42534 | K37: Instrutoria Interna | L37: 2668.6 | P37: 18 | R37: =SUM(O37:Q37) -> 18 | S37: 3 | T37: LUIZ GENEDIO MENDES JORGE
A38: 2016-006 | B38: 2016 | C38: Realizado | D38: 8195/2016 | E38: Workshop sobre Parcerias Público-Privadas | F38: Sociedade | G38: Treinamento de Jurisdicionados | H38: 13 e 14/06/2016 | I38: 42534 | J38: 42535 | K38: Instrutoria Externa | L38: 0 | O38: 33 | R38: =SUM(O38:Q38) -> 33 | S38: 10 | T38: Maria Aparecida Aiko Ikemura
A39: 2016-007 | B39: 2016 | C39: Realizado | D39: 12356/2016 | E39: Contratação Direta - Dispensa e Inexigibilidade de Licitação | F39: Jurisdicionados | G39: Treinamento de Jurisdicionados | H39: 13 a 17/06/2016 | I39: 42534 | J39: 42538 | K39: Instrutoria Interna | L39: 6671.48 | P39: 55 | R39: =SUM(O39:Q39) -> 55 | S39: 20 | T39: Roberto Dias Santiago
A40: 2016-008 | B40: 2016 | C40: Realizado | D40: 16351/2016 | E40: Capacitação para Conselheiros de Saúde | F40: Sociedade | G40: Metodologias de Auditoria e Fiscalização | H40: 27/06/2016 a 01/07/2016 | I40: 42548 | J40: 42552 | K40: Instrutoria Interna | L40: 7080.23 | Q40: 45 | R40: =SUM(O40:Q40) -> 45 | S40: 20 | T40: ROMILDO ARAUJO DA SILVA; TARSILA FIRMINO ELY
A41: 2016-009 | B41: 2016 | C41: Realizado | D41: 13816/2016 | E41: Access básico aplicado ao SIGGO | F41: Servidores do TCDF | G41: Mineração e Análise de Dados | H41: 27/06/2016 a 01/07/2016 | I41: 42548 | J41: 42552 | K41: Instrutoria Interna | L41: 6671.48 | O41: 15 | R41: =SUM(O41:Q41) -> 15 | S41: 20 | T41: ROMULO MIRANDA ALVIM
A42: 2016-010 | B42: 2016 | C42: Realizado | D42: 15487/2016 | E42: Acompanhamento do Orçamento Público – Jornalistas | F42: Sociedade | G42: Treinamento de Jurisdicionados | H42: 28/06/2016 a 30/06/2016 | I42: 42549 | J42: 42551 | K42: Instrutoria Interna | L42: 1334.3 | Q42: 21 | R42: =SUM(O42:Q42) -> 21 | S42: 8 | T42: Luiz Genédio Mendes Jorge
A43: 2016-011 | B43: 2016 | C43: Realizado | D43: 14910/2016 | E43: Curso de Educação Financeira | F43: Servidores do TCDF | G43: Desenvolvimento Individual e Promoção da Cultura Organizacional | H43: 20 e 21/07/2016 | I43: 42571 | J43: 42572 | K43: Instrutoria Externa | L43: 0 | O43: 40 | R43: =SUM(O43:Q43) -> 40 | S43: 9 | T43: BRB
A44: 2016-012 | B44: 2016 | C44: Realizado | D44: 20995/2016 | E44: Governança e gestão de TIC - Melhores práticas de mercado | F44: Jurisdicionados | G44: Treinamento de Jurisdicionados | H44: 01 e 02/08/2016 | I44: 42583 | J44: 42584 | K44: Instrutoria Interna | L44: 2668.6 | P44: 45 | R44: =SUM(O44:Q44) -> 45 | S44: 8 | T44: Everton Peixoto Correia de Assumpção
A45: 2016-013 | B45: 2016 | C45: Realizado | D45: 13794/2016 | E45: Oficina de Access Intermediário | F45: Servidores do TCDF | G45: Mineração e Análise de Dados | H45: 08 a 12/08/2016 | I45: 42590 | J45: 42594 | K45: Instrutoria Interna | L45: 7488.98 | O45: 13 | R45: =SUM(O45:Q45) -> 13 | S45: 20 | T45: Josdeyvi Magalhães Russi
A46: 2016-014 | B46: 2016 | C46: Realizado | D46: 13832/2016 | E46: Elaboração de Relatórios e Pareceres com base no manual de redação do Tribunal de Contas do Distrito Federal - Turma 1 | F46: Servidores do TCDF | G46: Desenvolvimento Individual e Promoção da Cultura Organizacional | H46: 15 a 19/08/2016 | I46: 42597 | J46: 42601 | K46: Instrutoria Externa | L46: 7880 | O46: 35 | R46: =SUM(O46:Q46) -> 35 | S46: 20 | T46: Profª Paula Cobucci
A47: 2016-015 | B47: 2016 | C47: Realizado | D47: 23447/2016 | E47: Processo de Contratação Pública na área de Saúde – Termos de Referência | F47: Jurisdicionados | G47: Treinamento de Jurisdicionados | H47: 15 a 19/08/2016 | I47: 42597 | J47: 42601 | K47: Híbrida | L47: 9556.7 | O47: 8 | P47: 63 | R47: =SUM(O47:Q47) -> 71 | S47: 20 | T47: Tarsila Firmino Ely; Romildo Araújo da Silva; Luiz Eduardo Costa
A48: 2016-016 | B48: 2016 | C48: Realizado | D48: 2251/2016 | E48: XXII SEMAT | F48: Híbrido | G48: Treinamento de Jurisdicionados | H48: 31/08 a 01/09/2016 | I48: 42613 | J48: 42614 | K48: Instrutoria Externa | L48: 44423.6 | O48: 87 | P48: 242 | Q48: 0 | R48: =SUM(O48:Q48) -> 329 | S48: 8 | T48: Ives Gandra da Silva Martins Filho; Pedro Jorge Simon; Antonio Renato Alves Rainha; Luiz Genédio Mendes Jorge; Henrique Moraes Ziller; Maria Rosynete de Oliveira; Eliana Calmon
A49: 2016-017 | B49: 2016 | C49: Realizado | D49: 24427/2016 | E49: Gestão de Processos | F49: Servidores do TCDF | G49: Administração, Estratégia e Inovação | H49: 12 a 16/09/2016 | I49: 42625 | J49: 42629 | K49: Instrutoria Externa | L49: 9200 | O49: 26 | R49: =SUM(O49:Q49) -> 26 | S49: 20 | T49: Annibal
A50: 2016-018 | B50: 2016 | C50: Realizado | D50: 26365/2016 | E50: Orçamento Público | F50: Servidores do TCDF | G50: Administração, Estratégia e Inovação | H50: 19 a 23/09/2016 | I50: 42632 | J50: 42636 | K50: Instrutoria Externa | L50: 5900 | O50: 35 | R50: =SUM(O50:Q50) -> 35 | S50: 20 | T50: Profº Rita (SENADO)
A51: 2016-019 | B51: 2016 | C51: Realizado | D51: 3169/2016 | E51: Gestão e fiscalização de contratos adm. - M1, Turma 1 | F51: Jurisdicionados | G51: Treinamento de Jurisdicionados | H51: 19 a 23/09/2016 | I51: 42632 | J51: 42636 | K51: Instrutoria Interna | L51: 6671.48 | P51: 46 | R51: =SUM(O51:Q51) -> 46 | S51: 20 | T51: Roberto Dias Santiago
A52: 2016-020 | B52: 2016 | C52: Realizado | D52: 3169/2016 | E52: Gestão e fiscalização de contratos adm. - M2, Turma 1 | F52: Jurisdicionados | G52: Treinamento de Jurisdicionados | H52: 19 a 23/09/2016 | I52: 42632 | J52: 42636 | K52: Instrutoria Interna | L52: 6671.48 | P52: 52 | R52: =SUM(O52:Q52) -> 52 | S52: 20 | T52: Roberto Dias Santiago
A53: 2016-021 | B53: 2016 | C53: Realizado | D53: 26373/2016 | E53: Regime Próprio de Previdência Social | F53: Servidores do TCDF | G53: Desenvolvimento Individual e Promoção da Cultura Organizacional | H53: 03 a 07/10/2016 | I53: 42646 | J53: 42650 | K53: Instrutoria Interna | L53: 8088.22 | O53: 34 | R53: =SUM(O53:Q53) -> 34 | S53: 20 | T53: Michel Martins de Morais
A54: 2016-022 | B54: 2016 | C54: Realizado | D54: 18508/2016 | E54: Como elaborar a planilha de formação de preços da IN nº 02/08 e como julgar a licitação para a contratação dos serviços contínuos | F54: Servidores do TCDF | G54: Metodologias de Auditoria e Fiscalização | H54: 17 a 19/10/2016 | I54: 42660 | J54: 42662 | K54: Instrutoria Externa | L54: 54183.63 | O54: 27 | R54: =SUM(O54:Q54) -> 27 | S54: 15 | T54: Zênite Informação e Consultoria
A55: 2016-023 | B55: 2016 | C55: Realizado | D55: 30532/2016 | E55: Aprendizagem Organizacional | F55: Servidores do TCDF | G55: Administração, Estratégia e Inovação | H55: 20, 21, 24, 27 e 28/10/2016 | I55: 42663 | J55: 42671 | K55: Instrutoria Externa | L55: 22500 | O55: 16 | R55: =SUM(O55:Q55) -> 16 | S55: 20 | T55: Pedro Paulo Carbone; Sylvio Maestrelli; Anelise Pereira Sihler
A56: 2016-024 | B56: 2016 | C56: Realizado | D56: 28597/2016 | E56: Contratação de TI com base na jurisprudência do TCDF | F56: Jurisdicionados | G56: Treinamento de Jurisdicionados | H56: 24 a 26/10/2016 | I56: 42667 | J56: 42669 | K56: Instrutoria Interna | L56: 4002.88 | P56: 55 | R56: =SUM(O56:Q56) -> 55 | S56: 12 | T56: Marcelo Oliveira Vasconcelos
A57: 2016-025 | B57: 2016 | C57: Realizado | D57: 29925/2016 | E57: Excel Avançado | F57: Servidores do TCDF | G57: Mineração e Análise de Dados | H57: 07 a 11/11/2016 | I57: 42681 | J57: 42685 | K57: Instrutoria Interna | L57: 8088.22 | O57: 14 | R57: =SUM(O57:Q57) -> 14 | S57: 20 | T57: Josdeyvi Magalhães Russi
A58: 2016-026 | B58: 2016 | C58: Realizado | D58: 30869/2016 | E58: Legislação de Pessoal no Setor Público com enfoque na LC 840/2011 | F58: Jurisdicionados | G58: Treinamento de Jurisdicionados | H58: 07 a 11/11/2016 | I58: 42681 | J58: 42685 | K58: Instrutoria Interna | L58: 6671.48 | P58: 47 | R58: =SUM(O58:Q58) -> 47 | S58: 20 | T58: Sebastião Cal de Miranda
A59: 2016-027 | B59: 2016 | C59: Realizado | D59: 30354/2016 | E59: Elaboração de Relatórios e Pareceres com base no Manual de Redação Oficial do TCDF - Turma 2 | F59: Servidores do TCDF | G59: Desenvolvimento Individual e Promoção da Cultura Organizacional | H59: 21, 22, 23, 24 e 28/11/2016 | I59: 42695 | J59: 42702 | K59: Instrutoria Externa | L59: 7880 | O59: 31 | R59: =SUM(O59:Q59) -> 31 | S59: 20 | T59: Paula Cobucci
A60: 2016-028 | B60: 2016 | C60: Realizado | D60: 9272/2016 | E60: Gestão e fiscalização de contratos adm. - M2, Turma 2 | F60: Jurisdicionados | G60: Treinamento de Jurisdicionados | H60: 21 a 25/11/2016 | I60: 42695 | J60: 42699 | K60: Instrutoria Interna | L60: 5612 | P60: 28 | R60: =SUM(O60:Q60) -> 28 | S60: 20 | T60: Roberto Dias Santiago
A61: 2016-029 | B61: 2016 | C61: Realizado | D61: 9272/2016 | E61: Gestão e fiscalização de contratos adm. - M1, Turma 2 | F61: Jurisdicionados | G61: Treinamento de Jurisdicionados | H61: 21 a 25/11/2016 | I61: 42695 | J61: 42699 | K61: Instrutoria Interna | L61: 5612 | P61: 34 | R61: =SUM(O61:Q61) -> 34 | S61: 20 | T61: Roberto Dias Santiago
A62: 2016-030 | B62: 2016 | C62: Realizado | D62: 32080/2016 | E62: Contratação e Fiscalização de Obras Públicas - Aspectos Polêmicos | F62: Jurisdicionados | G62: Treinamento de Jurisdicionados | H62: 05 a 07/12/2016 | I62: 42709 | J62: 42711 | K62: Instrutoria Interna | L62: 8000 | P62: 60 | R62: =SUM(O62:Q62) -> 60 | S62: 20 | T62: ADRIANA CUOCO PORTUGAL; MARCOS GARCIA DA SILVA PINTO
A63: 2017-001 | B63: 2017 | C63: Realizado | D63: 30532/2016 | E63: Instrutoria - Turma 2 | F63: Servidores do TCDF | G63: Administração, Estratégia e Inovação | H63: 06, 07, 08, 20 e 21/02/2017 | I63: 42773 | J63: 42788 | K63: Instrutoria Externa | L63: 27300 | O63: 29 | R63: =SUM(O63:Q63) -> 29 | S63: 26 | T63: Carbone, Sylvio - Inteletto
A64: 2017-002 | B64: 2017 | C64: Realizado | D64: 30532/2016 | E64: Tutoria em EAD | F64: Servidores do TCDF | G64: Administração, Estratégia e Inovação | H64: 06 e 31/03/2017 | I64: 42800 | J64: 42825 | K64: Instrutoria Externa | L64: 54300 | O64: 26 | R64: =SUM(O64:Q64) -> 26 | S64: 30 | T64: Pedro Paulo Carbone; Sylvio Maestrelli; Anelise Pereira Sihler
A65: 2017-003 | B65: 2017 | C65: Realizado | D65: 3164/2017 | E65: Gestão e Fiscalização de Contratos Adm. - M1 | F65: Jurisdicionados | G65: Treinamento de Jurisdicionados | H65: 13 a 17/03/2017 | I65: 42807 | J65: 42811 | K65: Instrutoria Interna | L65: 6962.15 | P65: 47 | R65: =SUM(O65:Q65) -> 47 | S65: 20 | T65: Roberto Dias Santiago
A66: 2017-004 | B66: 2017 | C66: Realizado | D66: 2265/2017 | E66: Excel Avançado - I | F66: Servidores do TCDF | G66: Mineração e Análise de Dados | H66: 20 a 24/03/2017 | I66: 42814 | J66: 42818 | K66: Instrutoria Interna | L66: 7466.41 | O66: 20 | R66: =SUM(O66:Q66) -> 20 | S66: 20 | T66: Josdeyvi Magalhães Russi
A67: 2017-005 | B67: 2017 | C67: Realizado | D67: 4730/2017 | E67: Gestão e Fiscalização de Contratos - Serviços | F67: Jurisdicionados | G67: Treinamento de Jurisdicionados | H67: 27 a 31/03/2017 | I67: 42821 | J67: 42825 | K67: Instrutoria Interna | L67: 6962.15 | P67: 43 | R67: =SUM(O67:Q67) -> 43 | S67: 20 | T67: Leonardo José Alves Leal Neri
A68: 2017-006 | B68: 2017 | C68: Realizado | D68: 3784/2017 | E68: Regime Próprio da Previdência | F68: Servidores do TCDF | G68: Desenvolvimento Individual e Promoção da Cultura Organizacional | H68: 27 a 31/03/2017 | I68: 42821 | J68: 42825 | K68: Instrutoria Interna | L68: 7241.74 | O68: 15 | R68: =SUM(O68:Q68) -> 15 | S68: 20 | T68: Michel Martins de Morais
A69: 2017-007 | B69: 2017 | C69: Realizado | D69: 997/2017 | E69: Formulação e Avaliação de Políticas Públicas com foco no Controle Externo | F69: Servidores do TCDF | G69: Áreas Temáticas de Fiscalização do Setor Público | H69: 03 a 07/04/2017 | I69: 42828 | J69: 42832 | K69: Instrutoria Externa | L69: 7950 | O69: 29 | R69: =SUM(O69:Q69) -> 29 | S69: 20 | T69: Pedro Luiz Costa Cavalcante
A70: 2017-008 | B70: 2017 | C70: Realizado | D70: 3164/2017 | E70: Gestão e Fiscalização de Contratos Adm. - M2 | F70: Jurisdicionados | G70: Treinamento de Jurisdicionados | H70: 24 a 28/04/2017 | I70: 42849 | J70: 42853 | K70: Instrutoria Interna | L70: 6962.15 | P70: 46 | R70: =SUM(O70:Q70) -> 46 | S70: 20 | T70: Roberto Dias Santiago
A71: 2017-009 | B71: 2017 | C71: Realizado | D71: 30532/2017 | E71: Instrutoria - Turma 3 | F71: Servidores do TCDF | G71: N/A | I71: 42860 | J71: 42860 | K71: Instrutoria Externa | L71: 27300 | O71: 14 | R71: =SUM(O71:Q71) -> 14 | S71: 26 | T71: Pedro Paulo Carbone; Sylvio Maestrelli
A72: 2017-010 | B72: 2017 | C72: Realizado | D72: 13946/2017 | E72: Sistema Channel - Turma 2 | F72: Servidores do TCDF | G72: N/A | I72: 42860 | J72: 42860 | K72: Instrutoria Externa | L72: 0 | O72: 12 | R72: =SUM(O72:Q72) -> 12 | S72: 8 | T72: Breno
A73: 2017-011 | B73: 2017 | C73: Realizado | D73: 8964/2017 | E73: Excel Avançado - II | F73: Servidores do TCDF | G73: Mineração e Análise de Dados | H73: 08 a 12/05/2017 | I73: 42863 | J73: 42867 | K73: Instrutoria Interna | L73: 7241.74 | O73: 18 | R73: =SUM(O73:Q73) -> 18 | S73: 20 | T73: Josdeyvi Magalhães Russi
A74: 2017-012 | B74: 2017 | C74: Realizado | D74: 2001/2017 | E74: Processo nos Tribunais de Contas: Acusação, Contraditório, Julgamento e Recursos | F74: Servidores do TCDF | G74: Metodologias de Auditoria e Fiscalização | H74: 15 a 19/05/2017 | I74: 42870 | J74: 42874 | K74: Instrutoria Externa | L74: 33600 | O74: 30 | R74: =SUM(O74:Q74) -> 30 | S74: 20 | T74: Odilon Cavallari de Oliveira
A75: 2017-013 | B75: 2017 | C75: Realizado | D75: 6120/2017 | E75: Capacitação para Conselheiros de Cultura | F75: Sociedade | G75: Treinamento de Jurisdicionados | H75: 22 a 26/05/2017 | I75: 42877 | J75: 42881 | K75: Instrutoria Interna | L75: 0 | Q75: 37 | R75: =SUM(O75:Q75) -> 37 | S75: 20 | T75: Carlos Augusto Pereira da Silva
A76: 2017-014 | B76: 2017 | C76: Realizado | D76: 11354/2017 | E76: Legislação de Pessoal no Setor Público, com enfoque na LC 840/2011 | F76: Jurisdicionados | G76: Treinamento de Jurisdicionados | H76: 22 a 26/05/2017 | I76: 42877 | J76: 42881 | K76: Instrutoria Interna | L76: 6962.15 | P76: 47 | R76: =SUM(O76:Q76) -> 47 | S76: 20 | T76: Sebastião Cal de Miranda
A77: 2017-015 | B77: 2017 | C77: Realizado | D77: 11460/2017 | E77: Tomada de Contas Especial | F77: Servidores do TCDF | G77: Metodologias de Auditoria e Fiscalização | H77: 25 e 26/05/2017 | I77: 42880 | J77: 42881 | K77: Instrutoria Externa | L77: 8000 | O77: 30 | R77: =SUM(O77:Q77) -> 30 | S77: 16 | T77: Guilherme Henrique De La Rocque Almeida
A78: 2017-016 | B78: 2017 | C78: Realizado | D78: 4675/2017 | E78: Oratória - Turma 1 | F78: Servidores do TCDF | G78: Desenvolvimento Individual e Promoção da Cultura Organizacional | H78: 25 a 26/05/2017 | I78: 42880 | J78: 42881 | K78: Instrutoria Externa | L78: 7880 | O78: 19 | R78: =SUM(O78:Q78) -> 19 | S78: 20 | T78: Paula Cobucci
A79: 2017-017 | B79: 2017 | C79: Realizado | D79: 14086/2017 | E79: Contratação de Soluções de Tecnologia da Informação e Comunicação - TIC - T.1 | F79: Jurisdicionados | G79: Treinamento de Jurisdicionados | H79: 26 a 29/05/2017 | I79: 42881 | J79: 42884 | K79: Instrutoria Interna | L79: 5569.72 | P79: 37 | R79: =SUM(O79:Q79) -> 37 | S79: 16 | T79: ADINOR BEDRITICHUK JUNIOR; EVERTON PEIXOTO CORREIA DE ASSUMPCAO; FLAVIO JOSE FONSECA DE SOUZA
A80: 2017-018 | B80: 2017 | C80: Realizado | D80: 4675/2017 | E80: Oratória - Turma 2 | F80: Servidores do TCDF | G80: Desenvolvimento Individual e Promoção da Cultura Organizacional | H80: 05 a 09/06/2017 | I80: 42891 | J80: 42895 | K80: Instrutoria Externa | L80: 7880 | O80: 19 | R80: =SUM(O80:Q80) -> 19 | S80: 20 | T80: Paula Cobucci
A81: 2017-019 | B81: 2017 | C81: Realizado | D81: 7690/2017 | E81: PPP - Análise Econômica e Financeira no Excel | F81: Servidores do TCDF | G81: Mineração e Análise de Dados | H81: 19 a 23/06/2017 | I81: 42905 | J81: 42909 | K81: Instrutoria Interna | L81: 8547.4 | O81: 20 | R81: =SUM(O81:Q81) -> 20 | S81: 20 | T81: Orivam Ibiapina da Silva
A82: 2017-020 | B82: 2017 | C82: Realizado | D82: 13128/2017 | E82: Capacitação Especial para Promoção Funcional | F82: Servidores do TCDF | G82: Ambientação e Desenvolvimento na Carreira | H82: 23/06 a 16/08/2017 | I82: 42909 | J82: 42963 | K82: Instrutoria Interna | L82: 11567.86 | O82: 50 | R82: =SUM(O82:Q82) -> 50 | S82: 20 | T82: Agnaldo Moreira Marques; DELSO FERREIRA DA SILVA JUNIOR; EMILIO VINHADELLI PAPADOPOLIS; Henrique Mattei ;LUCIENE DE FATIMA CARVALHO TEODORO; Paulo Alves Honorato; ROMULO MIRANDA ALVIM; SERGIO ARAUJO DE AMORIM LOPES
A83: 2017-021 | B83: 2017 | C83: Realizado | D83: 4764/2017 | E83: Gestão de Processos | F83: Servidores do TCDF | G83: Administração, Estratégia e Inovação | H83: 26 a 30/06/2017 | I83: 42912 | J83: 42916 | K83: Instrutoria Externa | L83: 9780 | O83: 17 | R83: =SUM(O83:Q83) -> 17 | S83: 20 | T83: Annibal
A84: 2017-022 | B84: 2017 | C84: Realizado | D84: 12741/2017 | E84: Planilha de Terceirização de Mão de Obra - T.1 | F84: Jurisdicionados | G84: Treinamento de Jurisdicionados | H84: 26 a 30/06/2017 | I84: 42912 | J84: 42916 | K84: Instrutoria Interna | L84: 6962.15 | P84: 25 | R84: =SUM(O84:Q84) -> 25 | S84: 20 | T84: Leonardo José Alves Leal Neri
A85: 2017-023 | B85: 2017 | C85: Realizado | D85: 14060/2017 | E85: Capacitação para Conselheiros de Saúde | F85: Sociedade | G85: Treinamento de Jurisdicionados | H85: 03 a 07/07/2017 | I85: 42919 | J85: 42923 | K85: Instrutoria Interna | L85: 7231.26 | Q85: 49 | R85: =SUM(O85:Q85) -> 49 | S85: 20 | T85: Romildo Araújo da Silva; Tarsila Firmino Ely
A86: 2017-024 | B86: 2017 | C86: Realizado | D86: 20884/2017 | E86: Planilha de Terceirização de Mão de Obra - T.2 | F86: Jurisdicionados | G86: Treinamento de Jurisdicionados | H86: 24 a 28/07/2017 | I86: 42940 | J86: 42944 | K86: Instrutoria Interna | L86: 6008.6 | P86: 34 | R86: =SUM(O86:Q86) -> 34 | S86: 20 | T86: Leonardo José Alves Leal Neri
A87: 2017-025 | B87: 2017 | C87: Realizado | D87: 13098/2017 | E87: Excel Avançado - III | F87: Servidores do TCDF | G87: Mineração e Análise de Dados | H87: 21 a 25/08/2017 | I87: 42968 | J87: 42972 | K87: Instrutoria Interna | L87: 7603.8 | O87: 19 | R87: =SUM(O87:Q87) -> 19 | S87: 20 | T87: Josdeyvi Magalhães Russi
A88: 2017-026 | B88: 2017 | C88: Realizado | D88: 3199/2017 | E88: XXIII SEMAT | F88: Jurisdicionados | G88: Treinamento de Jurisdicionados | H88: 29 e 30/08/2017 | I88: 42976 | J88: 42977 | K88: Instrutoria Externa | L88: 40881.51 | O88: 100 | P88: 212 | Q88: 0 | R88: =SUM(O88:Q88) -> 312 | S88: 8 | T88: Roberto Ellery; Marcos Mendes; Maria Lúcia Fattorelli; Fábio Henrique Granja e Barros; Adler Anaximandro de Cruz e Alves; Daniel Soares Godoi Gomes de Oliveira; Samy Dana
A89: 2017-027 | B89: 2017 | C89: Realizado | D89: 24014/2017 | E89: Contratação Direta - Dispensa e Inexigibilidade de Licitação sob o enfoque da Lei n° 8666/1993 | F89: Jurisdicionados | G89: Treinamento de Jurisdicionados | H89: 11 a 15/09/2017 | I89: 42989 | J89: 42993 | K89: Instrutoria Interna | L89: 7452.02 | P89: 57 | R89: =SUM(O89:Q89) -> 57 | S89: 20 | T89: Roberto Dias Santiago
A90: 2017-028 | B90: 2017 | C90: Realizado | D90: 26440/2017 | E90: Lei das Estatais | F90: Jurisdicionados | G90: Treinamento de Jurisdicionados | H90: 25 a 29/09/2017 | I90: 43003 | J90: 43007 | K90: Instrutoria Interna | L90: 7510.44 | P90: 50 | R90: =SUM(O90:Q90) -> 50 | S90: 20 | T90: Roberto Dias Santiago
A91: 2017-029 | B91: 2017 | C91: Realizado | D91: 25185/2017 | E91: Impactos do Novo Sicro no Orçamento de Obras Rodoviárias | F91: Servidores do TCDF | G91: Áreas Temáticas de Fiscalização do Setor Público | H91: 17 a 18/10/2017 | I91: 43025 | J91: 43026 | K91: Instrutoria Externa | L91: 19780 | O91: 18 | R91: =SUM(O91:Q91) -> 18 | S91: 20 | T91: Elci Pessoa Júnior
A92: 2017-030 | B92: 2017 | C92: Realizado | D92: 29563/2017 | E92: Boas Práticas para uma Atuação Eficiente dos Executores de Contratos Administrativos | F92: Servidores do TCDF | G92: Administração, Estratégia e Inovação | H92: 23 a 27/10/2017 | I92: 43031 | J92: 43035 | K92: Instrutoria Interna | L92: 7452.02 | O92: 18 | R92: =SUM(O92:Q92) -> 18 | S92: 20 | T92: CLEUSA MARTINS PITANGA;PAOLA KARINA DE BARRON SALES
A93: 2017-031 | B93: 2017 | C93: Realizado | D93: 17964/2017 | E93: Regularidade nos Processo de Aquisição / Manutenção de Equipamentos médico-hospitalares – Termos de Referência | F93: Jurisdicionados | G93: Treinamento de Jurisdicionados | H93: 23 a 27/10/2017 | I93: 43031 | J93: 43035 | K93: Híbrida | L93: 10272.4 | P93: 40 | R93: =SUM(O93:Q93) -> 40 | S93: 20 | T93: Tarsila Firmino Ely; Luiz Eduardo Costa
A94: 2017-032 | B94: 2017 | C94: Realizado | D94: 31223/2017 | E94: Contratação de Soluções de Tecnologia da Informação e Comunicação - TIC - T.2 | F94: Jurisdicionados | G94: Treinamento de Jurisdicionados | H94: 06 a 09/11/2017 | I94: 43045 | J94: 43048 | K94: Instrutoria Interna | L94: 5961.61 | P94: 37 | R94: =SUM(O94:Q94) -> 37 | S94: 16 | T94: Adinor Bedritichuk Junior; Everton Peixoto Correia de Assumpção; Flávio José Fonseca de Souza
A95: 2018-001 | B95: 2018 | C95: Realizado | D95: 5529/2018 | E95: Capacitação para Conselheiros de Saúde | F95: Sociedade | G95: Treinamento de Jurisdicionados | H95: 20 e 21/03/2018 | I95: 43179 | J95: 43180 | K95: Instrutoria Interna | L95: 5647.92 | Q95: 96 | R95: =SUM(O95:Q95) -> 96 | S95: 20 | T95: Tarsila Firmino Ely
A96: 2018-002 | B96: 2018 | C96: Realizado | D96: 13475/2018 | E96: SAS aplicado ao Controle Externo (Turma 2) | F96: Servidores do TCDF | G96: Mineração e Análise de Dados | H96: 02 a 06/04/2018 | I96: 43192 | J96: 43196 | K96: Instrutoria Interna | L96: 13018.48 | O96: 19 | R96: =SUM(O96:Q96) -> 19 | S96: 20 | T96: Rômulo Miranda Alvim
A97: 2018-003 | B97: 2018 | C97: Realizado | D97: 6835/2018 | E97: Gestão e Fiscalização de Contratos Adm. - M1, Turma 1 | F97: Jurisdicionados | G97: Treinamento de Jurisdicionados | H97: 09 a 13/04/2018 | I97: 43199 | J97: 43203 | K97: Instrutoria Interna | L97: 7310.2 | P97: 65 | R97: =SUM(O97:Q97) -> 65 | S97: 20 | T97: Roberto Dias Santiago
A98: 2018-004 | B98: 2018 | C98: Realizado | D98: 25059/2016 | E98: Oficina de SAS | F98: Servidores do TCDF | G98: N/A | I98: 43225 | J98: 43225 | K98: Instrutoria Externa | L98: 0 | O98: 19 | R98: =SUM(O98:Q98) -> 19 | S98: 8 | T98: Rômulo Miranda Alvim
A99: 2018-005 | B99: 2018 | C99: Realizado | D99: 6797/2018 | E99: Oratória e Técnicas de Apresentação Corporativa (Turma 1) | F99: Servidores do TCDF | G99: Desenvolvimento Individual e Promoção da Cultura Organizacional | H99: 07, 08, 09 e 11/05/2018 | I99: 43227 | J99: 43231 | K99: Instrutoria Externa | L99: 7690 | O99: 19 | R99: =SUM(O99:Q99) -> 19 | S99: 16 | T99: Paula Cobucci
A100: 2018-006 | B100: 2018 | C100: Realizado | D100: 8374/2018 | E100: SAS aplicado ao Controle Externo (Turma 1) | F100: Servidores do TCDF | G100: Mineração e Análise de Dados | H100: 14 a 18/05/2018 | I100: 43234 | J100: 43238 | K100: Instrutoria Interna | L100: 7510.44 | O100: 20 | R100: =SUM(O100:Q100) -> 20 | S100: 20 | T100: Rômulo Miranda Alvim
...

Sheet Cad. Instrutores
A1: Cadastro Mestre de Instrutores
A3: ID | B3: Instrutor | C3: Tipo | D3: Ativo
A4: 1 | B4: Abdiel Andrade | D4: Sim
A5: 2 | B5: Academia Simulamed | D5: Sim
A6: 3 | B6: Adriana Cuoco Portugal | D6: Sim
A7: 4 | B7: Adriana Magalhães | D7: Sim
A8: 5 | B8: Adriana Salles | D8: Sim
A9: 6 | B9: Alexandre Aquiles | D9: Sim
A10: 7 | B10: Antonio França | D10: Sim
A11: 8 | B11: Antonio Isidro | D11: Sim
A12: 9 | B12: Arthur Nogueira | D12: Sim
A13: 10 | B13: Arthur Wú | D13: Sim
A14: 11 | B14: Atricon | D14: Sim
A15: 12 | B15: Bruno Coelho | D15: Sim
... A88: 85 | B88: Willian Wistuba | D88: Sim

Sheet GECC 2026
A1: Ano | B1: ID Ação | C1: Status | D1: Curso | E1: Carga Horária | F1: Instrutor | G1: Qtd Instrutores | H1: GECC Aula (h) | I1: GECC Material (h) | J1: Total GECC (h) | L1: Ano Filtro: | M1: 2026 | U1: (não usar - overrides movidos para col. X:AA) | X1: Tabela de Overrides | AC1: GECC – Examinador
A2: {=_xlfn.LET(_xlpm.totalRows,MAX(S4:S200),_xlpm.seq,_xlfn.SEQUENCE(_xlpm.totalRows),_xlpm.srcRow,_xlfn.MAP(_xlpm.seq,_xlfn.LAMBDA(_xlpm.s,MATCH(_xlpm.s-1,T4:T200,1))),_xlpm.instrIdx,_xlfn.MAP(_xlpm.seq,_xlpm.srcRow,_xlfn.LAMBDA(_xlpm.s,_xlpm.sr,_xlpm.s-INDEX(T4:T200,_xlpm.sr))),_xlpm.ano,_xlfn.MAP(_xlpm.srcRow,_xlfn.LAMBDA(_xlpm.sr,INDEX(L4:L200,_xlpm.sr))),_xlpm.id,_xlfn.MAP(_xlpm.srcRow,_xlfn.LAMBDA(_xlpm.sr,INDEX(M4:M200,_xlpm.sr))),_xlpm.status,_xlfn.MAP(_xlpm.srcRow,_xlfn.LAMBDA(_xlpm.sr,INDEX(N4:N200,_xlpm.sr))),_xlpm.curso,_xlfn.MAP(_xlpm.srcRow,_xlfn.LAMBDA(_xlpm.sr,INDEX(O4:O200,_xlpm.sr))),_xlpm.ch,_xlfn.MAP(_xlpm.srcRow,_xlfn.LAMBDA(_xlpm.sr,INDEX(P4:P200,_xlpm.sr)+0)),_xlpm.instrStr,_xlfn.MAP(_xlpm.srcRow,_xlfn.LAMBDA(_xlpm.sr,INDEX(Q4:Q200,_xlpm.sr))),_xlpm.nInstr,_xlfn.MAP(_xlpm.srcRow,_xlfn.LAMBDA(_xlpm.sr,INDEX(R4:R200,_xlpm.sr)+0)),_xlpm.instrName,_xlfn.MAP(_xlpm.instrStr,_xlpm.instrIdx,_xlfn.LAMBDA(_xlpm.s,_xlpm.idx,TRIM(INDEX(_xlfn.TEXTSPLIT(_xlpm.s,"; "),,_xlpm.idx)))),_xlpm.ovKey,X3:X200&"|"&Y3:Y200,_xlpm.lookupKey,_xlpm.id&"|"&_xlpm.instrName,_xlpm.ovAula,_xlfn.MAP(_xlpm.lookupKey,_xlfn.LAMBDA(_xlpm.k,IFERROR(_xlfn.XLOOKUP(_xlpm.k,_xlpm.ovKey,Z3:Z200),""))),_xlpm.ovMat,_xlfn.MAP(_xlpm.lookupKey,_xlfn.LAMBDA(_xlpm.k,IFERROR(_xlfn.XLOOKUP(_xlpm.k,_xlpm.ovKey,AA3:AA200),""))),_xlpm.geccAula,_xlfn.MAP(_xlpm.ovAula,_xlpm.ch,_xlfn.LAMBDA(_xlpm.ov,_xlpm.c,IF(_xlpm.ov<>"",_xlpm.ov+0,_xlpm.c))),_xlpm.geccMat,_xlfn.MAP(_xlpm.ovMat,_xlpm.ch,_xlpm.nInstr,_xlfn.LAMBDA(_xlpm.ov,_xlpm.c,_xlpm.n,IF(_xlpm.ov<>"",_xlpm.ov+0,_xlpm.c*0.3/_xlpm.n))),_xlpm.geccTotal,_xlpm.geccAula+_xlpm.geccMat,_xlfn.HSTACK(_xlpm.ano,_xlpm.id,_xlpm.status,_xlpm.curso,_xlpm.ch,_xlpm.instrName,_xlpm.nInstr,_xlpm.geccAula,_xlpm.geccMat,_xlpm.geccTotal))} -> 2026 | B2: 2026-001 | C2: Realizado | D2: Contratação de TIC | E2: 8 | F2: Flávio José Fonseca de Souza | G2: 1 | H2: 8 | I2: 2.4 | J2: 10.4 | X2: ID Ação | Y2: Instrutor | Z2: Override Aula (h) | AA2: Override Material (h) | AC2: Ano | AD2: Examinador | AE2: Horas GECC
A3: 2026 | B3: 2026-002 | C3: Realizado | D3: Tcendo o Futuro - Edição Especial Filhos | E3: 4 | F3: Cinthia Thais de Carvalho Luz Thomazi | G3: 5 | H3: 4 | I3: 1.2 | J3: 5.2 | L3: fAno | M3: fID | N3: fStatus | O3: fCurso | P3: fCH | Q3: fInstr | R3: fNInstr | S3: fCumSum | T3: preCum | X3: 2026-021 | Y3: Paulo José Góes Daltro | Z3: 0 | AA3: 0 | AC3: 2026 | AD3: Cássio Murilo Alves Costa Filho | AE3: 16
A4: 2026 | B4: 2026-002 | C4: Realizado | D4: Tcendo o Futuro - Edição Especial Filhos | E4: 4 | F4: Adriana Cuoco Portugal | G4: 5 | H4: 4 | I4: 1.2 | J4: 5.2 | L4: {=_xlfn.LET(_xlpm.src,'Ações InCompany'!A2:T997,_xlpm.sAno,INDEX(_xlpm.src,,2),_xlpm.sMod,INDEX(_xlpm.src,,11),_xlfn._xlws.FILTER(_xlfn.HSTACK(INDEX(_xlpm.src,,2),INDEX(_xlpm.src,,1),INDEX(_xlpm.src,,3),INDEX(_xlpm.src,,5),INDEX(_xlpm.src,,19),INDEX(_xlpm.src,,20)),(_xlpm.sAno=M1)*(_xlpm.sMod="Instrutoria Interna"),""))} -> 2026 | M4: 2026-001 | N4: Realizado | O4: Contratação de TIC | P4: 8 | Q4: Flávio José Fonseca de Souza | R4: {=IF(L4:L200="","",IF(ISERROR(FIND("; ",Q4:Q200)),1,(LEN(Q4:Q200)-LEN(SUBSTITUTE(Q4:Q200,"; ","")))/2+1))} -> 1 | S4: {=IF(R4:R200="","",_xlfn.SCAN(0,R4:R200,_xlfn.LAMBDA(_xlpm.a,_xlpm.b,IF(_xlpm.b="","",_xlpm.a+_xlpm.b))))} -> 1 | T4: {=_xlfn.VSTACK(0,_xlfn._xlws.FILTER(S4:S200,S4:S200<>""))} -> 0 | X4: 2026-024 | Y4: Paulo José Góes Daltro | Z4: 0 | AA4: 0 | AC4: 2026 | AD4: Michel Martins de Morais | AE4: 16
A5: 2026 | B5: 2026-002 | C5: Realizado | D5: Tcendo o Futuro - Edição Especial Filhos | E5: 4 | F5: Fernanda Viana de Souza | G5: 5 | H5: 4 | I5: 1.2 | J5: 5.2 | L5: 2026 | M5: 2026-002 | N5: Realizado | O5: Tcendo o Futuro - Edição Especial Filhos | P5: 4 | Q5: Cinthia Thais de Carvalho Luz Thomazi; Adriana Cuoco Portugal; Fernanda Viana de Souza; Denise Duarte Guirra Kuhlmann; Priscila Nolasco de Oliveira | R5: 5 | S5: 6 | T5: 1 | X5: 2026-016 | Y5: Arthur Wú | Z5: 1 | AA5: 0.6 | AC5: 2026 | AD5: Marcelo Bálbio Moraes | AE5: 16
A6: 2026 | B6: 2026-002 | C6: Realizado | D6: Tcendo o Futuro - Edição Especial Filhos | E6: 4 | F6: Denise Duarte Guirra Kuhlmann | G6: 5 | H6: 4 | I6: 1.2 | J6: 5.2 | L6: 2026 | M6: 2026-004 | N6: Realizado | O6: Gestão e Fiscalização de Contratos de Equipamentos Médico Hospitalares e Serviços de Manutenção | P6: 12 | Q6: Tarsila Firmino Ely; Luciana Alvim | R6: 2 | S6: 8 | T6: 6 | X6: 2026-016 | Y6: Gustavo Takahashi | Z6: 1 | AA6: 0 | AC6: 2026 | AD6: Mauri Siqueira Montessi | AE6: 16
A7: 2026 | B7: 2026-002 | C7: Realizado | D7: Tcendo o Futuro - Edição Especial Filhos | E7: 4 | F7: Priscila Nolasco de Oliveira | G7: 5 | H7: 4 | I7: 0.24 | J7: 4.24 | L7: 2026 | M7: 2026-005 | N7: Realizado | O7: FIT1: Treinamento e Desenvolvimento (T&D) | P7: 16 | Q7: Paulo José Góes Daltro | R7: 1 | S7: 9 | T7: 8 | X7: 2026-005 | Y7: Paulo José Góes Daltro | Z7: 0 | AA7: 0 | AC7: 2026 | AD7: Rômulo Miranda Alvim | AE7: 16
A8: 2026 | B8: 2026-004 | C8: Realizado | D8: Gestão e Fiscalização de Contratos de Equipamentos Médico Hospitalares e Serviços de Manutenção | E8: 12 | F8: Tarsila Firmino Ely | G8: 2 | H8: 12 | I8: 1.8 | J8: 13.8 | L8: 2026 | M8: 2026-006 | N8: Realizado | O8: Curso para gestores e fiscais de contratos de serviços assistenciais complementares – SES/DF | P8: 12 | Q8: Adriana Magalhães; Luciana Alvim | R8: 2 | S8: 11 | T8: 9 | X8: 2026-002 | Y8: Cinthia Thais de Carvalho Luz Thomazi | AA8: 1.2 | AC8: 2026
A9: 2026 | B9: 2026-004 | C9: Realizado | D9: Gestão e Fiscalização de Contratos de Equipamentos Médico Hospitalares e Serviços de Manutenção | E9: 12 | F9: Luciana Alvim | G9: 2 | H9: 12 | I9: 1.8 | J9: 13.8 | L9: 2026 | M9: 2026-007 | N9: Realizado | O9: Planilhas de Terceirização de Mão de Obra, de acordo com a Lei nº 14.133/2021 - T1 | P9: 20 | Q9: Leonardo José Alves Leal Neri | R9: 1 | S9: 12 | T9: 11 | X9: 2026-002 | Y9: Adriana Cuoco Portugal | AA9: 1.2 | AC9: 2026
A10: 2026 | B10: 2026-005 | C10: Realizado | D10: FIT1: Treinamento e Desenvolvimento (T&D) | E10: 16 | F10: Paulo José Góes Daltro | G10: 1 | H10: 0 | I10: 0 | J10: 0 | L10: 2026 | M10: 2026-008 | N10: Realizado | O10: Curso de Promoção Funcional 2026/2027 | P10: 20 | Q10: Rômulo Miranda Alvim; Cinthia Thais de Carvalho Luz Thomazi | R10: 2 | S10: 14 | T10: 12 | X10: 2026-002 | Y10: Fernanda Viana de Souza | AA10: 1.2 | AC10: 2026
A11: 2026 | B11: 2026-006 | C11: Realizado | D11: Curso para gestores e fiscais de contratos de serviços assistenciais complementares – SES/DF | E11: 12 | F11: Adriana Magalhães | G11: 2 | H11: 12 | I11: 1.8 | J11: 13.8 | L11: 2026 | M11: 2026-009 | N11: Realizado | O11: Introdução à Engenharia de Prompt - t1 | P11: 8 | Q11: Arthur Wú | R11: 1 | S11: 15 | T11: 14 | X11: 2026-002 | Y11: Denise Duarte Guirra Kuhlmann | AA11: 1.2 | AC11: 2026
A12: 2026 | B12: 2026-006 | C12: Realizado | D12: Curso para gestores e fiscais de contratos de serviços assistenciais complementares – SES/DF | E12: 12 | F12: Luciana Alvim | G12: 2 | H12: 12 | I12: 1.8 | J12: 13.8 | L12: 2026 | M12: 2026-010 | N12: Realizado | O12: Planilhas de Terceirização de Mão de Obra, de acordo com a Lei nº 14.133/2021 - T2 | P12: 20 | Q12: Leonardo José Alves Leal Neri | R12: 1 | S12: 16 | T12: 15 | X12: 2026-002 | Y12: Priscila Nolasco | AA12: 1.2 | AC12: 2026
A13: 2026 | B13: 2026-007 | C13: Realizado | D13: Planilhas de Terceirização de Mão de Obra, de acordo com a Lei nº 14.133/2021 - T1 | E13: 20 | F13: Leonardo José Alves Leal Neri | G13: 1 | H13: 20 | I13: 6 | J13: 26 | L13: 2026 | M13: 2026-013 | N13: Realizado | O13: Curso para gestores e fiscais de contratos de serviços assistenciais complementares – SES/DF - T2 | P13: 12 | Q13: Adriana Magalhães; Luciana Alvim | R13: 2 | S13: 18 | T13: 16 | X13: 2026-020 | Y13: Cinthia Thais de Carvalho Luz Thomazi | AA13: 1.2 | AC13: 2026
A14: 2026 | B14: 2026-008 | C14: Realizado | D14: Curso de Promoção Funcional 2026/2027 | E14: 20 | F14: Rômulo Miranda Alvim | G14: 2 | H14: 20 | I14: 3 | J14: 23 | L14: 2026 | M14: 2026-015 | N14: Realizado | O14: Introdução à Engenharia de Prompt - t2 | P14: 8 | Q14: Arthur Wú; Gustavo Takahashi | R14: 2 | S14: 20 | T14: 18 | X14: 2026-020 | Y14: Adriana Cuoco Portugal | AA14: 1.2 | AC14: 2026
A15: 2026 | B15: 2026-008 | C15: Realizado | D15: Curso de Promoção Funcional 2026/2027 | E15: 20 | F15: Cinthia Thais de Carvalho Luz Thomazi | G15: 2 | H15: 20 | I15: 3 | J15: 23 | L15: 2026 | M15: 2026-016 | N15: Realizado | O15: Mentoria de introdução à Engenharia de Prompt | P15: 2 | Q15: Arthur Wú; Gustavo Takahashi | R15: 2 | S15: 22 | T15: 20 | X15: 2026-020 | Y15: Fernanda Viana de Souza | AA15: 1.2 | AC15: 2026
A16: 2026 | B16: 2026-009 | C16: Realizado | D16: Introdução à Engenharia de Prompt - t1 | E16: 8 | F16: Arthur Wú | G16: 1 | H16: 8 | I16: 2.4 | J16: 10.4 | L16: 2026 | M16: 2026-017 | N16: Realizado | O16: Mostra Fotográfica “Meu Olhar sobre Brasília” | P16: 0 | Q16: Servidores, colaboradores e estagiários do TCDF | R16: 1 | S16: 23 | T16: 22 | X16: 2026-020 | Y16: Denise Duarte Guirra Kuhlmann | AA16: 1.2 | AC16: 2026
A17: 2026 | B17: 2026-010 | C17: Realizado | D17: Planilhas de Terceirização de Mão de Obra, de acordo com a Lei nº 14.133/2021 - T2 | E17: 20 | F17: Leonardo José Alves Leal Neri | G17: 1 | H17: 20 | I17: 6 | J17: 26 | L17: 2026 | M17: 2026-018 | N17: Realizado | O17: Tcendo o Futuro | P17: 4 | Q17: Cinthia Thais de Carvalho Luz Thomazi; Adriana Cuoco Portugal; Fernanda Viana de Souza; Denise Duarte Guirra Kuhlmann; Priscila Nolasco de Oliveira | R17: 5 | S17: 28 | T17: 23 | X17: 2026-020 | Y17: Priscila Nolasco | AA17: 1.2 | AC17: 2026
A18: 2026 | B18: 2026-013 | C18: Realizado | D18: Curso para gestores e fiscais de contratos de serviços assistenciais complementares – SES/DF - T2 | E18: 12 | F18: Adriana Magalhães | G18: 2 | H18: 12 | I18: 1.8 | J18: 13.8 | L18: 2026 | M18: 2026-019 | N18: Realizado | O18: Tcendo o Futuro | P18: 4 | Q18: Cinthia Thais de Carvalho Luz Thomazi; Adriana Cuoco Portugal; Fernanda Viana de Souza; Denise Duarte Guirra Kuhlmann; Priscila Nolasco de Oliveira | R18: 5 | S18: 33 | T18: 28 | X18: 2026-018 | Y18: Cinthia Thais de Carvalho Luz Thomazi | AA18: 1.2 | AC18: 2026
A19: 2026 | B19: 2026-013 | C19: Realizado | D19: Curso para gestores e fiscais de contratos de serviços assistenciais complementares – SES/DF - T2 | E19: 12 | F19: Luciana Alvim | G19: 2 | H19: 12 | I19: 1.8 | J19: 13.8 | L19: 2026 | M19: 2026-020 | N19: Cancelado | O19: Escola de Instrutores - Curso "Fundamentos em TD&E" | P19: 16 | Q19: Paulo José Góes Daltro | R19: 1 | S19: 34 | T19: 33 | X19: 2026-018 | Y19: Adriana Cuoco Portugal | AA19: 1.2 | AC19: 2026
... A25: 2026 | B25: 2026-018 | C25: Realizado | D25: Tcendo o Futuro | E25: 4 | F25: Cinthia Thais de Carvalho Luz Thomazi | G25: 5 | H25: 4 | I25: 1.2 | J25: 5.2 | L25: 2026 | M25: 2026-032 | N25: Em andamento | O25: MROSC para os gestores das Organizações da Sociedade Civil – OSCs | P25: 12 | Q25: Indio Artiaga do Brasil Rabelo; Leonardo de Melo | R25: 2 | S25: 45 | T25: 43 | X25: 2026-032 | Y25: Indio Artiaga do Brasil Rabelo | AA25: 3.6 | AC25: 2026
A26: 2026 | B26: 2026-018 | C26: Realizado | D26: Tcendo o Futuro | E26: 4 | F26: Adriana Cuoco Portugal | G26: 5 | H26: 4 | I26: 1.2 | J26: 5.2 | L26: 2026 | M26: 2026-033 | N26: Realizado | O26: Introdução à Engenharia de Prompt - T3 | P26: 8 | Q26: Arthur Wú; Gustavo Takahashi | R26: 2 | S26: 47 | T26: 45 | X26: 2026-032 | Y26: Leonardo de Melo | Z26: 0 | AA26: 0 | AC26: 2026
A27: 2026 | B27: 2026-018 | C27: Realizado | D27: Tcendo o Futuro | E27: 4 | F27: Fernanda Viana de Souza | G27: 5 | H27: 4 | I27: 1.2 | J27: 5.2 | L27: 2026 | M27: 2026-034 | N27: Realizado | O27: Introdução à Engenharia de Prompt - T4 | P27: 8 | Q27: Arthur Wú; Gustavo Takahashi | R27: 2 | S27: 49 | T27: 47 | X27: 2026-033 | Y27: Arthur Wú | AA27: 2.4 | AC27: 2026
A28: 2026 | B28: 2026-018 | C28: Realizado | D28: Tcendo o Futuro | E28: 4 | F28: Denise Duarte Guirra Kuhlmann | G28: 5 | H28: 4 | I28: 1.2 | J28: 5.2 | L28: 2026 | M28: 2026-035 | N28: Realizado | O28: Curso básico de e-TCDF | P28: 16 | Q28: Cássio Murilo Alves Costa Filho | R28: 1 | S28: 50 | T28: 49 | X28: 2026-033 | Y28: Gustavo Takahashi | AA28: 0 | AC28: 2026
A29: 2026 | B29: 2026-018 | C29: Realizado | D29: Tcendo o Futuro | E29: 4 | F29: Priscila Nolasco de Oliveira | G29: 5 | H29: 4 | I29: 0.24 | J29: 4.24 | L29: 2026 | M29: 2026-036 | N29: Realizado | O29: Curso de Ambientação para os novos Auditores de Controle Externo - Área Auditoria | P29: 20 | Q29: Diversos | R29: 1 | S29: 51 | T29: 50 | X29: 2026-034 | Y29: Arthur Wú | AA29: 2.4 | AC29: 2026
A30: 2026 | B30: 2026-019 | C30: Realizado | D30: Tcendo o Futuro | E30: 4 | F30: Cinthia Thais de Carvalho Luz Thomazi | G30: 5 | H30: 4 | I30: 0.24 | J30: 4.24 | L30: 2026 | M30: 2026-037 | N30: Realizado | O30: Curso de Formação Inicial para Novos Auditores do TCDF | P30: 12 | Q30: Cinthia Thais de Carvalho Luz Thomazi; Reinaldo Alencar; Rogério Ribeiro; Rômulo Miranda Alvim; Gabriel Heller | R30: 5 | S30: 56 | T30: 51 | X30: 2026-034 | Y30: Gustavo Takahashi | AA30: 0 | AC30: 2026
A31: 2026 | B31: 2026-019 | C31: Realizado | D31: Tcendo o Futuro | E31: 4 | F31: Adriana Cuoco Portugal | G31: 5 | H31: 4 | I31: 0.24 | J31: 4.24 | L31: 2026 | M31: 2026-038 | N31: A realizar | O31: Elaboração da Cartilha "Gestão e Fiscalização de Contratos em Saúde" | P31: 85 | Q31: Tarsila Firmino Ely; Luciana Alvim | R31: 2 | S31: 58 | T31: 56 | X31: 2026-036 | Y31: Diversos | Z31: 0 | AA31: 0 | AC31: 2026
A32: 2026 | B32: 2026-019 | C32: Realizado | D32: Tcendo o Futuro | E32: 4 | F32: Fernanda Viana de Souza | G32: 5 | H32: 4 | I32: 0.24 | J32: 4.24 | L32: 2026 | M32: 2026-039 | N32: A realizar | O32: Curso de Formação para Conselheiros de Saúde do DF | P32: 20 | Q32: Tarsila Firmino Ely | R32: 1 | S32: 59 | T32: 58 | X32: 2026-037 | Y32: Cinthia Thais de Carvalho Luz Thomazi | Z32: 4 | AA32: 0.6 | AC32: 2026
A33: 2026 | B33: 2026-019 | C33: Realizado | D33: Tcendo o Futuro | E33: 4 | F33: Denise Duarte Guirra Kuhlmann | G33: 5 | H33: 4 | I33: 0.24 | J33: 4.24 | L33: 2026 | M33: 2026-040 | N33: Realizado | O33: UniTCDF: TCDF e a Fiscalização de Obras | P33: 4 | Q33: Adriana Cuoco Portugal | R33: 1 | S33: 60 | T33: 59 | X33: 2026-037 | Y33: Reinaldo Alencar | Z33: 4 | AA33: 0.6 | AD33: Total: | AE33: =SUM(AE3:AE32) -> 80
A34: 2026 | B34: 2026-019 | C34: Realizado | D34: Tcendo o Futuro | E34: 4 | F34: Priscila Nolasco de Oliveira | G34: 5 | H34: 4 | I34: 0.24 | J34: 4.24 | L34: 2026 | M34: 2026-041 | N34: Realizado | O34: UniTCDF: Ciências Contábeis | P34: 3 | Q34: Fernanda Viana de Souza; Túllio Herbeth Teixeira Moraes | R34: 2 | S34: 62 | T34: 60 | X34: 2026-037 | Y34: Rogério Ribeiro | Z34: 4 | AA34: 0.6
A35: 2026 | B35: 2026-020 | C35: Cancelado | D35: Escola de Instrutores - Curso "Fundamentos em TD&E" | E35: 16 | F35: Paulo José Góes Daltro | G35: 1 | H35: 16 | I35: 4.8 | J35: 20.8 | L35: 2026 | M35: 2026-042 | N35: A realizar | O35: Introdução ao processo de controle externo - EAD | P35: 16 | Q35: Gabriel Heller | R35: 1 | S35: 63 | T35: 62 | X35: 2026-037 | Y35: Rômulo Miranda Alvim | Z35: 4 | AA35: 0.6
A36: 2026 | B36: 2026-022 | C36: Realizado | D36: Fiscalizações Baseadas em Risco | E36: 20 | F36: Reinaldo Alencar | G36: 2 | H36: 20 | I36: 3 | J36: 23 | L36: 2026 | M36: 2026-044 | N36: A realizar | O36: Painel MROSC | P36: 4 | Q36: Diversos | R36: 1 | S36: 64 | T36: 63 | X36: 2026-037 | Y36: Gabriel Heller | Z36: 4 | AA36: 1.2
A37: 2026 | B37: 2026-022 | C37: Realizado | D37: Fiscalizações Baseadas em Risco | E37: 20 | F37: Rogério Ribeiro | G37: 2 | H37: 20 | I37: 3 | J37: 23 | L37: 2026 | M37: 2026-045 | N37: A realizar | O37: 31º SEMAT | P37: 8 | Q37: José Roberto Alcuri Júnior; Felipe Ramos Barbosa; Carolina Pereira de Oliveira; Eustáquio Rabelo de Souza; Alinne Patrícia de Andrade Carvalho; Silvia Lima Damasceno Carvalho; Marcelo Santana; Cinthia Thais de Carvalho Luz Thomazi; Igor Queiroz; Guilherme Bride Fernandes | R37: 10 | S37: 74 | T37: 64 | X37: 2026-038 | Y37: Tarsila Firmino Ely | Z37: 0 | AA37: 85
A38: 2026 | B38: 2026-023 | C38: Realizado | D38: Curso de formação para gestores e fiscais de Contrato em equipamentos nas unidades hospitalares - T2 | E38: 12 | F38: Tarsila Firmino Ely | G38: 2 | H38: 12 | I38: 1.8 | J38: 13.8 | L38: 2026 | M38: 2026-046 | N38: Realizado | O38: Curso “Sisaudit na Prática” | P38: 12 | Q38: Davi Assunção Salvador Nery de Castro; David da Silva de Araújo; Hamilton de Jesus Lopes Neto | R38: 3 | S38: 77 | T38: 74 | X38: 2026-038 | Y38: Luciana Alvim | Z38: 0 | AA38: 85
A39: 2026 | B39: 2026-023 | C39: Realizado | D39: Curso de formação para gestores e fiscais de Contrato em equipamentos nas unidades hospitalares - T2 | E39: 12 | F39: Luciana Alvim | G39: 2 | H39: 12 | I39: 1.8 | J39: 13.8 | L39: 2026 | M39: 2026-047 | N39: A realizar | O39: Contratações de TIC com base na jurisprudência do TCDF - EAD | P39: 17.45 | Q39: Flávio José Fonseca de Souza; Felipe da Costa Malaquias | R39: 2 | S39: 79 | T39: 77 | X39: 2026-042 | Y39: Gabriel Heller | Z39: 0 | AA39: 32
A40: 2026 | B40: 2026-024 | C40: A realizar | D40: Escola de Instrutores - Design Instrucional | E40: 12 | F40: Paulo José Góes Daltro | G40: 1 | H40: 0 | I40: 0 | J40: 0 | L40: 2026 | M40: 2026-048 | N40: Em andamento | O40: Introdução à Engenharia de Prompt - SEE | P40: 8 | Q40: Arthur Wú; Gustavo Takahashi | R40: 2 | S40: 81 | T40: 79 | X40: 2026-044 | Y40: Diversos | Z40: 0 | AA40: 0
A41: 2026 | B41: 2026-025 | C41: Realizado | D41: Curso de formação para gestores e fiscais de Contrato em equipamentos nas unidades hospitalares - T3 | E41: 12 | F41: Tarsila Firmino Ely | G41: 2 | H41: 12 | I41: 1.8 | J41: 13.8 | L41: 2026 | M41: 2026-049 | N41: A realizar | O41: TCendo o Futuro | P41: 4 | Q41: Adriana Cuoco Portugal; Cinthia Thais de Carvalho Luz Thomazi; Fernanda Viana de Souza; Luiz Felipe Tenório de Lima Gondim; Priscila Nolasco de Oliveira | R41: 5 | S41: 86 | T41: 81 | X41: 2026-047 | Y41: Flávio José Fonseca de Souza | Z41: 0 | AA41: 34.9
A42: 2026 | B42: 2026-025 | C42: Realizado | D42: Curso de formação para gestores e fiscais de Contrato em equipamentos nas unidades hospitalares - T3 | E42: 12 | F42: Luciana Alvim | G42: 2 | H42: 12 | I42: 1.8 | J42: 13.8 | L42: 2026 | M42: 2026-050 | N42: A realizar | O42: TCendo o Futuro | P42: 4 | Q42: Adriana Cuoco Portugal; Cinthia Thais de Carvalho Luz Thomazi; Fernanda Viana de Souza; Luiz Felipe Tenório de Lima Gondim; Priscila Nolasco de Oliveira | R42: 5 | S42: 91 | T42: 86 | X42: 2026-047 | Y42: Felipe da Costa Malaquias | Z42: 0 | AA42: 34.9
A43: 2026 | B43: 2026-030 | C43: A realizar | D43: O novo olhar sobre as políticas públicas para o Controle Externo | E43: 24 | F43: Reinaldo Alencar | G43: 2 | H43: 24 | I43: 3.6 | J43: 27.6 | L43: 2026 | M43: 2026-051 | N43: A realizar | O43: TCendo o Futuro | P43: 4 | Q43: Adriana Cuoco Portugal; Cinthia Thais de Carvalho Luz Thomazi; Fernanda Viana de Souza; Luiz Felipe Tenório de Lima Gondim; Priscila Nolasco de Oliveira | R43: 5 | S43: 96 | T43: 91 | X43: 2026-048 | Y43: Arthur Wú | AA43: 2.4
A44: 2026 | B44: 2026-030 | C44: A realizar | D44: O novo olhar sobre as políticas públicas para o Controle Externo | E44: 24 | F44: Rogério Ribeiro | G44: 2 | H44: 24 | I44: 3.6 | J44: 27.6 | L44: 2026 | M44: 2026-052 | N44: A realizar | O44: TCendo o Futuro | P44: 4 | Q44: Adriana Cuoco Portugal; Cinthia Thais de Carvalho Luz Thomazi; Fernanda Viana de Souza; Luiz Felipe Tenório de Lima Gondim; Priscila Nolasco de Oliveira | R44: 5 | S44: 101 | T44: 96 | X44: 2026-048 | Y44: Gustavo Takahashi | AA44: 0
A45: 2026 | B45: 2026-032 | C45: Em andamento | D45: MROSC para os gestores das Organizações da Sociedade Civil – OSCs | E45: 12 | F45: Indio Artiaga do Brasil Rabelo | G45: 2 | H45: 12 | I45: 3.6 | J45: 15.6 | L45: 2026 | M45: 2026-054 | N45: A realizar | O45: Oficina Temática – SEMAT: Falhas recorrentes em contratações de TI | P45: 8 | Q45: Felipe da Costa Malaquias | R45: 1 | S45: 102 | T45: 101 | X45: 2026-045 | Y45: José Roberto Alcuri Júnior | Z45: 1 | AA45: 0.3
A46: 2026 | B46: 2026-032 | C46: Em andamento | D46: MROSC para os gestores das Organizações da Sociedade Civil – OSCs | E46: 12 | F46: Leonardo de Melo | G46: 2 | H46: 0 | I46: 0 | J46: 0 | L46: 2026 | M46: 2026-055 | N46: A realizar | O46: TCendo o Futuro | P46: 4 | Q46: Adriana Cuoco Portugal; Cinthia Thais de Carvalho Luz Thomazi; Fernanda Viana de Souza; Luiz Felipe Tenório de Lima Gondim; Priscila Nolasco de Oliveira | R46: 5 | S46: 107 | T46: 102 | X46: 2026-045 | Y46: Felipe Ramos Barbosa | Z46: 1 | AA46: 0.3
A47: 2026 | B47: 2026-033 | C47: Realizado | D47: Introdução à Engenharia de Prompt - T3 | E47: 8 | F47: Arthur Wú | G47: 2 | H47: 8 | I47: 2.4 | J47: 10.4 | L47: 2026 | M47: 2026-056 | N47: A realizar | O47: TCendo o Futuro | P47: 4 | Q47: Adriana Cuoco Portugal; Cinthia Thais de Carvalho Luz Thomazi; Fernanda Viana de Souza; Luiz Felipe Tenório de Lima Gondim; Priscila Nolasco de Oliveira | R47: 5 | S47: 112 | T47: 107 | X47: 2026-045 | Y47: Carolina Pereira de Oliveira | Z47: 1 | AA47: 0.3
A48: 2026 | B48: 2026-033 | C48: Realizado | D48: Introdução à Engenharia de Prompt - T3 | E48: 8 | F48: Gustavo Takahashi | G48: 2 | H48: 8 | I48: 0 | J48: 8 | T48: 112 | X48: 2026-045 | Y48: Eustáquio Rabelo de Souza | Z48: 1 | AA48: 0.3
A49: 2026 | B49: 2026-034 | C49: Realizado | D49: Introdução à Engenharia de Prompt - T4 | E49: 8 | F49: Arthur Wú | G49: 2 | H49: 8 | I49: 2.4 | J49: 10.4 | X49: 2026-045 | Y49: Alinne Patrícia de Andrade Carvalho | Z49: 0 | AA49: 0
A50: 2026 | B50: 2026-034 | C50: Realizado | D50: Introdução à Engenharia de Prompt - T4 | E50: 8 | F50: Gustavo Takahashi | G50: 2 | H50: 8 | I50: 0 | J50: 8 | X50: 2026-045 | Y50: Silvia Lima Damasceno Carvalho | Z50: 1 | AA50: 0.3
A51: 2026 | B51: 2026-035 | C51: Realizado | D51: Curso básico de e-TCDF | E51: 16 | F51: Cássio Murilo Alves Costa Filho | G51: 1 | H51: 16 | I51: 4.8 | J51: 20.8 | X51: 2026-045 | Y51: Marcelo Santana | Z51: 1 | AA51: 0.3
A52: 2026 | B52: 2026-036 | C52: Realizado | D52: Curso de Ambientação para os novos Auditores de Controle Externo - Área Auditoria | E52: 20 | F52: Diversos | G52: 1 | H52: 0 | I52: 0 | J52: 0 | X52: 2026-045 | Y52: Cinthia Thais de Carvalho Luz Thomazi | Z52: 1 | AA52: 0.3
A53: 2026 | B53: 2026-037 | C53: Realizado | D53: Curso de Formação Inicial para Novos Auditores do TCDF | E53: 12 | F53: Cinthia Thais de Carvalho Luz Thomazi | G53: 5 | H53: 4 | I53: 0.6 | J53: 4.6 | X53: 2026-045 | Y53: Igor Queiroz | Z53: 1 | AA53: 0.3
A54: 2026 | B54: 2026-037 | C54: Realizado | D54: Curso de Formação Inicial para Novos Auditores do TCDF | E54: 12 | F54: Reinaldo Alencar | G54: 5 | H54: 4 | I54: 0.6 | J54: 4.6 | X54: 2026-045 | Y54: Guilherme Bride Fernandes | Z54: 0 | AA54: 0
A55: 2026 | B55: 2026-037 | C55: Realizado | D55: Curso de Formação Inicial para Novos Auditores do TCDF | E55: 12 | F55: Rogério Ribeiro | G55: 5 | H55: 4 | I55: 0.6 | J55: 4.6
A56: 2026 | B56: 2026-037 | C56: Realizado | D56: Curso de Formação Inicial para Novos Auditores do TCDF | E56: 12 | F56: Rômulo Miranda Alvim | G56: 5 | H56: 4 | I56: 0.6 | J56: 4.6
A57: 2026 | B57: 2026-037 | C57: Realizado | D57: Curso de Formação Inicial para Novos Auditores do TCDF | E57: 12 | F57: Gabriel Heller | G57: 5 | H57: 4 | I57: 1.2 | J57: 5.2
A58: 2026 | B58: 2026-038 | C58: A realizar | D58: Elaboração da Cartilha "Gestão e Fiscalização de Contratos em Saúde" | E58: 85 | F58: Tarsila Firmino Ely | G58: 2 | H58: 0 | I58: 85 | J58: 85
A59: 2026 | B59: 2026-038 | C59: A realizar | D59: Elaboração da Cartilha "Gestão e Fiscalização de Contratos em Saúde" | E59: 85 | F59: Luciana Alvim | G59: 2 | H59: 0 | I59: 85 | J59: 85
A60: 2026 | B60: 2026-039 | C60: A realizar | D60: Curso de Formação para Conselheiros de Saúde do DF | E60: 20 | F60: Tarsila Firmino Ely | G60: 1 | H60: 20 | I60: 6 | J60: 26
A61: 2026 | B61: 2026-040 | C61: Realizado | D61: UniTCDF: TCDF e a Fiscalização de Obras | E61: 4 | F61: Adriana Cuoco Portugal | G61: 1 | H61: 4 | I61: 1.2 | J61: 5.2
A62: 2026 | B62: 2026-041 | C62: Realizado | D62: UniTCDF: Ciências Contábeis | E62: 3 | F62: Fernanda Viana de Souza | G62: 2 | H62: 3 | I62: 0.45 | J62: 3.45
A63: 2026 | B63: 2026-041 | C63: Realizado | D63: UniTCDF: Ciências Contábeis | E63: 3 | F63: Túllio Herbeth Teixeira Moraes | G63: 2 | H63: 3 | I63: 0.45 | J63: 3.45
A64: 2026 | B64: 2026-042 | C64: A realizar | D64: Introdução ao processo de controle externo - EAD | E64: 16 | F64: Gabriel Heller | G64: 1 | H64: 0 | I64: 32 | J64: 32
A65: 2026 | B65: 2026-044 | C65: A realizar | D65: Painel MROSC | E65: 4 | F65: Diversos | G65: 1 | H65: 0 | I65: 0 | J65: 0
A66: 2026 | B66: 2026-045 | C66: A realizar | D66: 31º SEMAT | E66: 8 | F66: José Roberto Alcuri Júnior | G66: 10 | H66: 1 | I66: 0.3 | J66: 1.3
... A113: 2026 | B113: 2026-056 | C113: A realizar | D113: TCendo o Futuro | E113: 4 | F113: Priscila Nolasco de Oliveira | G113: 5 | H113: 4 | I113: 0.24 | J113: 4.24

Sheet Dashboard 2026
A1: DASHBOARD DE CURSOS — 2026
A4: TOTAL DE CURSOS | D4: REALIZADOS | G4: A REALIZAR
A5: =COUNTIF('Ações InCompany'!B:B,2026) -> 56 | B5: cursos | D5: =COUNTIFS('Ações InCompany'!B:B,2026,'Ações InCompany'!C:C,"Realizado") -> 32 | E5: cursos | G5: =COUNTIFS('Ações InCompany'!B:B,2026,'Ações InCompany'!C:C,"A realizar") -> 19
A8: CURSOS REALIZADOS POR PÚBLICO-ALVO | D8: PARTICIPANTES POR PÚBLICO (REALIZADOS)
A10: Público-Alvo | B10: Qtd. Cursos | D10: Público | E10: Qtd. Participantes
A11: Servidores do TCDF | B11: =COUNTIFS('Ações InCompany'!B:B,2026,'Ações InCompany'!C:C,"Realizado",'Ações InCompany'!F:F,"Servidores do TCDF") -> 16 | D11: Servidores (P. Servidores) | E11: =SUMIFS('Ações InCompany'!O:O,'Ações InCompany'!B:B,2026,'Ações InCompany'!C:C,"Realizado") -> 502
A12: Jurisdicionados | B12: =COUNTIFS('Ações InCompany'!B:B,2026,'Ações InCompany'!C:C,"Realizado",'Ações InCompany'!F:F,"Jurisdicionados") -> 11 | D12: Jurisdicionados (P. Jurisdicionados) | E12: =SUMIFS('Ações InCompany'!P:P,'Ações InCompany'!B:B,2026,'Ações InCompany'!C:C,"Realizado") -> 561
A13: Sociedade | B13: =COUNTIFS('Ações InCompany'!B:B,2026,'Ações InCompany'!C:C,"Realizado",'Ações InCompany'!F:F,"Sociedade") -> 5 | D13: Sociedade (P. Sociedade) | E13: =SUMIFS('Ações InCompany'!Q:Q,'Ações InCompany'!B:B,2026,'Ações InCompany'!C:C,"Realizado") -> 411
A14: TOTAL | B14: =SUM(B11:B13) -> 32 | D14: TOTAL GERAL | E14: =SUM(E11:E13) -> 1474
A30: CURSOS POR PROGRAMA (TODOS OS STATUS)
A32: Programa | B32: Realizados | C32: A Realizar | D32: Total | E32: % do Total
A33: Treinamento de Jurisdicionados | B33: =COUNTIFS('Ações InCompany'!B:B,2026,'Ações InCompany'!C:C,"Realizado",'Ações InCompany'!G:G,A33) -> 5 | C33: =COUNTIFS('Ações InCompany'!B:B,2026,'Ações InCompany'!C:C,"A realizar",'Ações InCompany'!G:G,A33) -> 6 | D33: =B33+C33 -> 11 | E33: =D33/$D$45 -> 0.21568627
A34: Administração, Estratégia e Inovação | B34: =COUNTIFS('Ações InCompany'!B:B,2026,'Ações InCompany'!C:C,"Realizado",'Ações InCompany'!G:G,A34) -> 3 | C34: =COUNTIFS('Ações InCompany'!B:B,2026,'Ações InCompany'!C:C,"A realizar",'Ações InCompany'!G:G,A34) -> 0 | D34: =B34+C34 -> 3 | E34: =D34/$D$45 -> 0.058823529
A35: Inteligência Artificial e Análise de Dados | B35: =COUNTIFS('Ações InCompany'!B:B,2026,'Ações InCompany'!C:C,"Realizado",'Ações InCompany'!G:G,A35) -> 5 | C35: =COUNTIFS('Ações InCompany'!B:B,2026,'Ações InCompany'!C:C,"A realizar",'Ações InCompany'!G:G,A35) -> 1 | D35: =B35+C35 -> 6 | E35: =D35/$D$45 -> 0.11764706
A36: Escola de Instrutores | B36: =COUNTIFS('Ações InCompany'!B:B,2026,'Ações InCompany'!C:C,"Realizado",'Ações InCompany'!G:G,A36) -> 1 | C36: =COUNTIFS('Ações InCompany'!B:B,2026,'Ações InCompany'!C:C,"A realizar",'Ações InCompany'!G:G,A36) -> 1 | D36: =B36+C36 -> 2 | E36: =D36/$D$45 -> 0.039215686
A37: Desenvolvimento Individual e Promoção da Cultura Organizacional | B37: =COUNTIFS('Ações InCompany'!B:B,2026,'Ações InCompany'!C:C,"Realizado",'Ações InCompany'!G:G,A37) -> 2 | C37: =COUNTIFS('Ações InCompany'!B:B,2026,'Ações InCompany'!C:C,"A realizar",'Ações InCompany'!G:G,A37) -> 0 | D37: =B37+C37 -> 2 | E37: =D37/$D$45 -> 0.039215686
A38: Formação de Controladores sociais e cidadãos | B38: =COUNTIFS('Ações InCompany'!B:B,2026,'Ações InCompany'!C:C,"Realizado",'Ações InCompany'!G:G,A38) -> 5 | C38: =COUNTIFS('Ações InCompany'!B:B,2026,'Ações InCompany'!C:C,"A realizar",'Ações InCompany'!G:G,A38) -> 7 | D38: =B38+C38 -> 12 | E38: =D38/$D$45 -> 0.23529412
A39: Metodologias de Auditoria e Fiscalização | B39: =COUNTIFS('Ações InCompany'!B:B,2026,'Ações InCompany'!C:C,"Realizado",'Ações InCompany'!G:G,A39) -> 3 | C39: =COUNTIFS('Ações InCompany'!B:B,2026,'Ações InCompany'!C:C,"A realizar",'Ações InCompany'!G:G,A39) -> 1 | D39: =B39+C39 -> 4 | E39: =D39/$D$45 -> 0.078431373
A40: Áreas Temáticas de Fiscalização do Setor Público | B40: =COUNTIFS('Ações InCompany'!B:B,2026,'Ações InCompany'!C:C,"Realizado",'Ações InCompany'!G:G,A40) -> 0 | C40: =COUNTIFS('Ações InCompany'!B:B,2026,'Ações InCompany'!C:C,"A realizar",'Ações InCompany'!G:G,A40) -> 2 | D40: =B40+C40 -> 2 | E40: =D40/$D$45 -> 0.039215686
A41: Treinamento em Saúde Pública | B41: =COUNTIFS('Ações InCompany'!B:B,2026,'Ações InCompany'!C:C,"Realizado",'Ações InCompany'!G:G,A41) -> 6 | C41: =COUNTIFS('Ações InCompany'!B:B,2026,'Ações InCompany'!C:C,"A realizar",'Ações InCompany'!G:G,A41) -> 1 | D41: =B41+C41 -> 7 | E41: =D41/$D$45 -> 0.1372549
A42: Desenvolvimento de Líderes | B42: =COUNTIFS('Ações InCompany'!B:B,2026,'Ações InCompany'!C:C,"Realizado",'Ações InCompany'!G:G,A42) -> 0 | C42: =COUNTIFS('Ações InCompany'!B:B,2026,'Ações InCompany'!C:C,"A realizar",'Ações InCompany'!G:G,A42) -> 0 | D42: =B42+C42 -> 0 | E42: =D42/$D$45 -> 0
A43: Ambientação e Desenvolvimento na Carreira | B43: =COUNTIFS('Ações InCompany'!B:B,2026,'Ações InCompany'!C:C,"Realizado",'Ações InCompany'!G:G,A43) -> 2 | C43: =COUNTIFS('Ações InCompany'!B:B,2026,'Ações InCompany'!C:C,"A realizar",'Ações InCompany'!G:G,A43) -> 0 | D43: =B43+C43 -> 2 | E43: =D43/$D$45 -> 0.039215686
A44: (Sem Programa) | B44: =COUNTIFS('Ações InCompany'!B:B,2026,'Ações InCompany'!C:C,"Realizado",'Ações InCompany'!G:G,"") -> 0 | C44: =COUNTIFS('Ações InCompany'!B:B,2026,'Ações InCompany'!C:C,"A realizar",'Ações InCompany'!G:G,"") -> 0 | D44: =B44+C44 -> 0 | E44: =D44/$D$45 -> 0
A45: TOTAL | B45: =SUM(B33:B44) -> 32 | C45: =SUM(C33:C44) -> 19 | D45: =SUM(D33:D44) -> 51 | E45: =SUM(E33:E44) -> 1

Sheet PlanoCap
A1: ANO - VIGÊNCIA | B1: EIXO TEMÁTICO | C1: Programa | D1: Público-Alvo Preferencial | E1: Descrição
A2: 2024/2025 | B2: Controle Externo | C2: Avaliação de Políticas Públicas | D2: Membros e servidores que atuam no Controle Externo | E2: Destina-se a oferecer ações de aprendizagem de metodologias necessárias à avaliação de políticas públicas governamentais.
A3: 2024/2025 | B3: Controle Externo | C3: Metodologias de Auditoria e Fiscalização | D3: Membros e servidores que atuam no Controle Externo | E3: Destina-se a oferecer ações de aprendizagem de metodologias necessárias à realização de fiscalizações governamentais, alinhadas às Normas Brasileiras de Auditoria do Setor Público.
A4: 2024/2025 | B4: Controle Externo | C4: Áreas Temáticas de Fiscalização do Setor Público | D4: Membros e servidores que atuam no Controle Externo | E4: Destina-se a oferecer ações de aprendizagem voltadas às áreas temáticas fiscalizadas, como saúde, pessoal, previdência, assistência social, obras e serviços de engenharia, tecnologia de informação e comunicação, licitações e contratos, parcerias público-privadas, concessões e desestatização, entre outros
A5: 2024/2025 | B5: Controle Externo | C5: Treinamento de Jurisdicionados | D5: Servidores Públicos dos órgãos jurisdicionados ao TCDF | E5: Destina-se a oferecer ações de aprendizagem para os gestores e servidores públicos dos órgãos jurisdicionados ao TCDF, a fim de promover a correta e eficiente aplicação dos recursos públicos
A6: 2024/2025 | B6: Controle Externo | C6: Formação de Controladores sociais e cidadãos | D6: Representantes de entidades de Controle social e Cidadãos | E6: Destina-se a oferecer ações de aprendizagem para os cidadãos, para fomentar o exercício do controle social.
A7: 2024/2025 | B7: Organizacional | C7: Mineração e Análise de Dados | D7: Servidores que possam utilizar análise de dados no desempenho de suas atividades | E7: Destina-se a oferecer ações de aprendizagem voltadas à análise e mineração de dados, a fim de identificar informações úteis à tomada de decisão em meio a grandes quantidades de dados.
A8: 2024/2025 | B8: Organizacional | C8: Administração, Estratégia e Inovação | D8: Membros e Servidores do TCDF | E8: Destina-se a oferecer ações de aprendizagem para auxiliar na gestão e apoio estratégico do TCDF, assim como promover a inovação na Casa. As ações buscam aprimorar processos como os de planejamento, gestão de pessoas, gestão da informação, gestão de projetos, gestão de processos, gestão administrativa, gestão contratual, relacionamento com o cliente, operacionalização de sistemas, entre outros
A9: 2024/2025 | B9: Programas Transversais | C9: Desenvolvimento Gerencial | D9: Servidores que ocupam função gerencial e potenciais líderes a desenvolver | E9: Destina-se a oferecer ações de aprendizagem para os atuais dirigentes do TCDF, considerando as necessidades de cada nível gerencial (estratégico, tático e operacional), àqueles que assumem funções gerenciais e os servidores com potencial de atuação gerencial no TCDF. As ações devem auxiliar os gestores no exercício da função gerencial, aprimorando competências relacionadas à gestão de desempenho, ao desenvolvimento da equipe, gestão da equipe remota e/ou híbrida, orientação estratégica, feedback, entre outros.
A10: 2024/2025 | B10: Programas Transversais | C10: Desenvolvimento Individual e Promoção da Cultura Organizacional | D10: Servidores do TCDF | E10: Destina-se a oferecer ações de aprendizagem para auxiliar no desenvolvimento de competências funcionais dos servidores, tais quais orientação para resultado, ética e relacionamento interpessoal.
A11: 2024/2025 | B11: Programas Transversais | C11: Ambientação e Desenvolvimento na Carreira | D11: Servidores do TCDF | E11: Destina-se a oferecer ações de aprendizagem para auxiliar na ambientação e promoção de servidores, promovendo a visão sistêmica da sua atuação no âmbito do TCDF

Sheet Validação Dados
A1: Público-alvo | B1: Modalidade | C1: Previsão | D1: Status
A2: Servidores do TCDF | B2: Instrutoria Interna | C2: Previsto | D2: A realizar
A3: Jurisdicionados | B3: Instrutoria Externa | C3: Solicitado | D3: Em andamento
A4: Sociedade | B4: Híbrida | D4: Cancelado
A5: Híbrido | D5: Realizado
D6: Adiado

Sheet PlanoCap2627
A1: ANO - VIGÊNCIA | B1: EIXO TEMÁTICO | C1: Programa | D1: Público-Alvo Preferencial | E1: Descrição
A2: 2026/2027 | B2: Controle Externo | C2: Metodologias de Auditoria e Fiscalização | D2: Membros e servidores que atuam no Controle Externo | E2: Destina-se a oferecer ações de aprendizagem de metodologias necessárias à realização de fiscalizações governamentais, alinhadas às Normas Brasileiras de Auditoria do Setor Público
A3: 2026/2027 | B3: Controle Externo | C3: Áreas Temáticas de Fiscalização do Setor Público | D3: Membros e servidores que atuam no Controle Externo | E3: Destina-se a oferecer ações de aprendizagem voltadas às áreas temáticas fiscalizadas, como saúde, pessoal, previdência, assistência social, obras e serviços de engenharia, tecnologia da informação e comunicação, licitações e contratos, parcerias público-privadas, concessões e desestatização, entre outras
A4: 2026/2027 | B4: Controle Externo | C4: Treinamento de Jurisdicionados | D4: Servidores Públicos dos órgãos jurisdicionados ao TCDF | E4: Destina-se a oferecer ações de aprendiza_x0002_gem para os gestores e servidores públicos dos órgãos jurisdicionados ao TCDF, a fim de promover a correta e eficiente aplicação dos recursos públicos
A5: 2026/2027 | B5: Controle Externo | C5: Treinamento em Saúde Pública | D5: Membros e servidores do TCDF, servidores públicos dos órgãos jurisdicionados ao TCDF da área da saúde e cidadãos interessados na temática de saúde pública | E5: Destina-se a oferecer ações de aprendiza_x0002_gem para os atores responsáveis pela saúde pública distrital e interessados na temática, com vistas à correta e eficiente aplicação dos recursos públicos e à melhoria dos resultados do setor
A6: 2026/2027 | B6: Controle Externo | C6: Formação de Controladores sociais e cidadãos | D6: Representantes de entidades de Controle social e Cidadãos | E6: Destina-se a oferecer ações de aprendizagem para os cidadãos, para fomentar o exercício do controle social.
A7: 2026/2027 | B7: Organizacional | C7: Inteligência Artificial e Análise de Dados | D7: Membros e servidores do TCDF | E7: Destina-se a oferecer ações de aprendizagem voltadas ao uso da inteligência artificial e à análise e mineração de dados, a fim de iden_x0002_tificar informações úteis à tomada de decisão em meio a grandes quantidades de dados.
A8: 2026/2027 | B8: Organizacional | C8: Administração, Estratégia e Inovação | D8: Membros e Servidores do TCDF | E8: Destina-se a oferecer ações de aprendizagem para auxiliar na gestão e apoio estratégico do TCDF, assim como promover a inovação na Casa. As ações buscam aprimorar processos como os de planejamento, gestão de pessoas, gestão da informação, gestão de projetos, gestão de processos, gestão administrativa, gestão contratual, relacionamento com o cliente, operacionalização de sistemas, entre outros
A9: 2026/2027 | B9: Organizacional | C9: Escola de Instrutores | D9: Corpo técnico e docente da Escola de Contas Públicas do TCDF | E9: Destina-se a oferecer ações de aprendizagem para o corpo técnico e docente da Escola de Contas Públicas do TCDF, a fim de aprimorar a qualidade instrucional e os resultados das ações de treinamento oferecidas internamente.
A10: 2026/2027 | B10: Transversal | C10: Desenvolvimento de Líderes | D10: Servidores que ocu_x0002_pam função gerencial e potenciais líderes a desenvolver | E10: Destina-se a oferecer ações de aprendizagem para os atuais dirigentes do TCDF, consideran_x0002_do as necessidades de cada nível gerencial (estratégico, tático e operacional), àqueles que assumem funções gerenciais e aos servido_x0002_res com potencial de atuação gerencial no Tribunal. As ações devem auxiliar os gestores no exercício da função gerencial, aprimoran_x0002_do competências relacionadas à gestão de desempenho, ao desenvolvimento da equipe, à gestão de equipes remotas e/ou híbridas, à orientação estratégica, ao feedback, entre outras
A11: 2026/2027 | B11: Transversal | C11: Desenvolvimento Individual e Promoção da Cultura Organizacional | D11: Servidores do TCDF | E11: Destina-se a oferecer ações de aprendizagem para auxiliar no desenvolvimento de competências funcionais dos servidores, tais quais orientação para resultado, ética e relacionamento interpessoal.
A12: 2026/2027 | B12: Transversal | C12: Ambientação e Desenvolvimento na Carreira | D12: Servidores do TCDF | E12: Destina-se a oferecer ações de aprendizagem para auxiliar na ambientação e promoção de servidores, promovendo a visão sistêmica da sua atuação no âmbito do TCDF

Sheet Dashboard Maratonas
A1: 📊 DASHBOARD — MARATONAS TEMÁTICAS
A2: Atualizado automaticamente a partir da aba Ações InCompany
A4: Total de Maratonas | D4: Total de Participantes | G4: Média Participantes
A5: =COUNTIF('Ações InCompany'!E:E,"*maratona*") -> 13 | D5: =SUM(H8:H100) -> 1762 | G5: =IFERROR(ROUND(D5/A5,0),"-") -> 136
A7: # | B7: Data Início | C7: Ano | D7: Tema da Maratona | E7: Data | F7: Status | G7: Público-Alvo | H7: Participantes
A8: {=IFERROR(_xlfn.SEQUENCE(COUNTIF('Ações InCompany'!E:E,"*maratona*")),"")} -> 1 | B8: {=_xlfn._xlws.SORT(_xlfn._xlws.FILTER(CHOOSE({1,2,3,4,5,6,7},'Ações InCompany'!I2:I999,'Ações InCompany'!B2:B999,'Ações InCompany'!E2:E999,'Ações InCompany'!H2:H999,'Ações InCompany'!C2:C999,'Ações InCompany'!F2:F999,'Ações InCompany'!R2:R999),ISNUMBER(SEARCH("maratona",'Ações InCompany'!E2:E999))),1,1)} -> 45092 | C8: 2023 | D8: Maratona Temática: Auditoria em saúde | E8: 15 e 16/06/2023 | F8: Realizado | G8: Servidores do TCDF | H8: 184
A9: 2 | B9: 45154 | C9: 2023 | D9: Maratona temática: auditoria em mobilidade urbana | E9: 16 a 18/08/2023 | F9: Realizado | G9: Servidores do TCDF | H9: 64
A10: 3 | B10: 45239 | C10: 2023 | D10: Maratona temática: primeira infância | E10: 09 e 10/11/2023 | F10: Realizado | G10: Sociedade | H10: 91
A11: 4 | B11: 45264 | C11: 2023 | D11: Maratona Temática: auditoria em resíduos sólidos | E11: 04 e 05/12/2023 | F11: Realizado | G11: Servidores do TCDF | H11: 85
A12: 5 | B12: 45456 | C12: 2024 | D12: Maratona Temática - educação | E12: 13 e 14/06/2024 | F12: Realizado | G12: Sociedade | H12: 155
A13: 6 | B13: 45624 | C13: 2024 | D13: Maratona temática - Governança em Saúde | E13: 28 e 29/11/2024 | F13: Realizado | G13: Jurisdicionados | H13: 138
A14: 7 | B14: 45750 | C14: 2025 | D14: Maratona Temática: Obras Públicas | E14: 03 e 04/04/2025 | F14: Realizado | G14: Jurisdicionados | H14: 250
A15: 8 | B15: 45925 | C15: 2025 | D15: Maratona Temática “O Olhar dos Tribunais de Contas sobre Políticas Públicas" | E15: 25 e 26/09/2025 | F15: Realizado | G15: Sociedade | H15: 228
A16: 9 | B16: 45950 | C16: 2025 | D16: Maratona Temática: Segurança Pública | E16: 20 e 21/10/2025 | F16: Realizado | G16: Sociedade | H16: 179
A17: 10 | B17: 46111 | C17: 2026 | D17: Maratona Temática: Transparência Pública | E17: 30 a 31/03/2026 | F17: Realizado | G17: Jurisdicionados | H17: 192
A18: 11 | B18: 46195 | C18: 2026 | D18: 3ª Maratona Temática em Saúde Pública - Boas Práticas | E18: 22 e 23/06/2026 | F18: Realizado | G18: Jurisdicionados | H18: 196
A19: 12 | B19: 46321 | C19: 2026 | D19: Maratona Temática - Obras Públicas | E19: 26 e 27/10/2026 | F19: A realizar | G19: Jurisdicionados | H19: 0
A20: 13 | B20: 46335 | C20: 2026 | D20: Maratona Temática - Mobilidade Urbana | E20: 09 e 10/11/2026 | F20: A realizar | G20: Jurisdicionados | H20: 0

Sheet Dashboard GECC 2026
A1: Dashboard GECC 2026 - Horas por Instrutor
A2: Consulta de horas GECC por instrutor em 2026
A4: Instrutor | B4: GECC Aula (h) | C4: GECC Material (h) | D4: GECC Examinador (h) | E4: Total GECC (h) | F4: Qtd Ações
A5: {=IFERROR(_xlfn._xlws.SORT(_xlfn.UNIQUE(_xlfn._xlws.FILTER(_xlfn.VSTACK('GECC 2026'!F2:F200,'GECC 2026'!AD3:AD32),_xlfn.VSTACK('GECC 2026'!F2:F200,'GECC 2026'!AD3:AD32)<>""))),"")} -> Adriana Cuoco Portugal | B5: =IF($A5="","",SUMIFS('GECC 2026'!H$2:H$200,'GECC 2026'!F$2:F$200,$A5)) -> 40 | C5: =IF($A5="","",SUMIFS('GECC 2026'!I$2:I$200,'GECC 2026'!F$2:F$200,$A5)) -> 5.28 | D5: =IF($A5="","",SUMIFS('GECC 2026'!$AE$3:$AE$32,'GECC 2026'!$AD$3:$AD$32,$A5)) -> 0 | E5: =IF($A5="","",SUMIFS('GECC 2026'!J$2:J$200,'GECC 2026'!F$2:F$200,$A5)+SUMIFS('GECC 2026'!$AE$3:$AE$32,'GECC 2026'!$AD$3:$AD$32,$A5)) -> 45.28 | F5: =IF($A5="","",COUNTIFS('GECC 2026'!F$2:F$200,$A5)) -> 10 | G5: =IF($A5="","",COUNTIFS('GECC 2026'!G$2:G$200,$A5)) -> 0
A6: Adriana Magalhães | B6: =IF($A6="","",SUMIFS('GECC 2026'!H$2:H$200,'GECC 2026'!F$2:F$200,$A6)) -> 24 | C6: =IF($A6="","",SUMIFS('GECC 2026'!I$2:I$200,'GECC 2026'!F$2:F$200,$A6)) -> 3.6 | D6: =IF($A6="","",SUMIFS('GECC 2026'!$AE$3:$AE$32,'GECC 2026'!$AD$3:$AD$32,$A6)) -> 0 | E6: =IF($A6="","",SUMIFS('GECC 2026'!J$2:J$200,'GECC 2026'!F$2:F$200,$A6)+SUMIFS('GECC 2026'!$AE$3:$AE$32,'GECC 2026'!$AD$3:$AD$32,$A6)) -> 27.6 | F6: =IF($A6="","",COUNTIFS('GECC 2026'!F$2:F$200,$A6)) -> 2
A7: Alinne Patrícia de Andrade Carvalho | B7: =IF($A7="","",SUMIFS('GECC 2026'!H$2:H$200,'GECC 2026'!F$2:F$200,$A7)) -> 0 | C7: =IF($A7="","",SUMIFS('GECC 2026'!I$2:I$200,'GECC 2026'!F$2:F$200,$A7)) -> 0 | D7: =IF($A7="","",SUMIFS('GECC 2026'!$AE$3:$AE$32,'GECC 2026'!$AD$3:$AD$32,$A7)) -> 0 | E7: =IF($A7="","",SUMIFS('GECC 2026'!J$2:J$200,'GECC 2026'!F$2:F$200,$A7)+SUMIFS('GECC 2026'!$AE$3:$AE$32,'GECC 2026'!$AD$3:$AD$32,$A7)) -> 0 | F7: =IF($A7="","",COUNTIFS('GECC 2026'!F$2:F$200,$A7)) -> 1
A8: Arthur Wú | B8: =IF($A8="","",SUMIFS('GECC 2026'!H$2:H$200,'GECC 2026'!F$2:F$200,$A8)) -> 41 | C8: =IF($A8="","",SUMIFS('GECC 2026'!I$2:I$200,'GECC 2026'!F$2:F$200,$A8)) -> 12.6 | D8: =IF($A8="","",SUMIFS('GECC 2026'!$AE$3:$AE$32,'GECC 2026'!$AD$3:$AD$32,$A8)) -> 0 | E8: =IF($A8="","",SUMIFS('GECC 2026'!J$2:J$200,'GECC 2026'!F$2:F$200,$A8)+SUMIFS('GECC 2026'!$AE$3:$AE$32,'GECC 2026'!$AD$3:$AD$32,$A8)) -> 53.6 | F8: =IF($A8="","",COUNTIFS('GECC 2026'!F$2:F$200,$A8)) -> 6
A9: Carolina Pereira de Oliveira | B9: =IF($A9="","",SUMIFS('GECC 2026'!H$2:H$200,'GECC 2026'!F$2:F$200,$A9)) -> 1 | C9: =IF($A9="","",SUMIFS('GECC 2026'!I$2:I$200,'GECC 2026'!F$2:F$200,$A9)) -> 0.3 | D9: =IF($A9="","",SUMIFS('GECC 2026'!$AE$3:$AE$32,'GECC 2026'!$AD$3:$AD$32,$A9)) -> 0 | E9: =IF($A9="","",SUMIFS('GECC 2026'!J$2:J$200,'GECC 2026'!F$2:F$200,$A9)+SUMIFS('GECC 2026'!$AE$3:$AE$32,'GECC 2026'!$AD$3:$AD$32,$A9)) -> 1.3 | F9: =IF($A9="","",COUNTIFS('GECC 2026'!F$2:F$200,$A9)) -> 1
A10: Cássio Murilo Alves Costa Filho | B10: =IF($A10="","",SUMIFS('GECC 2026'!H$2:H$200,'GECC 2026'!F$2:F$200,$A10)) -> 16 | C10: =IF($A10="","",SUMIFS('GECC 2026'!I$2:I$200,'GECC 2026'!F$2:F$200,$A10)) -> 4.8 | D10: =IF($A10="","",SUMIFS('GECC 2026'!$AE$3:$AE$32,'GECC 2026'!$AD$3:$AD$32,$A10)) -> 16 | E10: =IF($A10="","",SUMIFS('GECC 2026'!J$2:J$200,'GECC 2026'!F$2:F$200,$A10)+SUMIFS('GECC 2026'!$AE$3:$AE$32,'GECC 2026'!$AD$3:$AD$32,$A10)) -> 36.8 | F10: =IF($A10="","",COUNTIFS('GECC 2026'!F$2:F$200,$A10)) -> 1
A11: Cinthia Thais de Carvalho Luz Thomazi | B11: =IF($A11="","",SUMIFS('GECC 2026'!H$2:H$200,'GECC 2026'!F$2:F$200,$A11)) -> 61 | C11: =IF($A11="","",SUMIFS('GECC 2026'!I$2:I$200,'GECC 2026'!F$2:F$200,$A11)) -> 7.98 | D11: =IF($A11="","",SUMIFS('GECC 2026'!$AE$3:$AE$32,'GECC 2026'!$AD$3:$AD$32,$A11)) -> 0 | E11: =IF($A11="","",SUMIFS('GECC 2026'!J$2:J$200,'GECC 2026'!F$2:F$200,$A11)+SUMIFS('GECC 2026'!$AE$3:$AE$32,'GECC 2026'!$AD$3:$AD$32,$A11)) -> 68.98 | F11: =IF($A11="","",COUNTIFS('GECC 2026'!F$2:F$200,$A11)) -> 12
A12: Davi Assunção Salvador Nery de Castro | B12: =IF($A12="","",SUMIFS('GECC 2026'!H$2:H$200,'GECC 2026'!F$2:F$200,$A12)) -> 12 | C12: =IF($A12="","",SUMIFS('GECC 2026'!I$2:I$200,'GECC 2026'!F$2:F$200,$A12)) -> 1.2 | D12: =IF($A12="","",SUMIFS('GECC 2026'!$AE$3:$AE$32,'GECC 2026'!$AD$3:$AD$32,$A12)) -> 0 | E12: =IF($A12="","",SUMIFS('GECC 2026'!J$2:J$200,'GECC 2026'!F$2:F$200,$A12)+SUMIFS('GECC 2026'!$AE$3:$AE$32,'GECC 2026'!$AD$3:$AD$32,$A12)) -> 13.2 | F12: =IF($A12="","",COUNTIFS('GECC 2026'!F$2:F$200,$A12)) -> 1
A13: David da Silva de Araújo | B13: =IF($A13="","",SUMIFS('GECC 2026'!H$2:H$200,'GECC 2026'!F$2:F$200,$A13)) -> 12 | C13: =IF($A13="","",SUMIFS('GECC 2026'!I$2:I$200,'GECC 2026'!F$2:F$200,$A13)) -> 1.2 | D13: =IF($A13="","",SUMIFS('GECC 2026'!$AE$3:$AE$32,'GECC 2026'!$AD$3:$AD$32,$A13)) -> 0 | E13: =IF($A13="","",SUMIFS('GECC 2026'!J$2:J$200,'GECC 2026'!F$2:F$200,$A13)+SUMIFS('GECC 2026'!$AE$3:$AE$32,'GECC 2026'!$AD$3:$AD$32,$A13)) -> 13.2 | F13: =IF($A13="","",COUNTIFS('GECC 2026'!F$2:F$200,$A13)) -> 1
A14: Denise Duarte Guirra Kuhlmann | B14: =IF($A14="","",SUMIFS('GECC 2026'!H$2:H$200,'GECC 2026'!F$2:F$200,$A14)) -> 12 | C14: =IF($A14="","",SUMIFS('GECC 2026'!I$2:I$200,'GECC 2026'!F$2:F$200,$A14)) -> 2.64 | D14: =IF($A14="","",SUMIFS('GECC 2026'!$AE$3:$AE$32,'GECC 2026'!$AD$3:$AD$32,$A14)) -> 0 | E14: =IF($A14="","",SUMIFS('GECC 2026'!J$2:J$200,'GECC 2026'!F$2:F$200,$A14)+SUMIFS('GECC 2026'!$AE$3:$AE$32,'GECC 2026'!$AD$3:$AD$32,$A14)) -> 14.64 | F14: =IF($A14="","",COUNTIFS('GECC 2026'!F$2:F$200,$A14)) -> 3
A15: Diversos | B15: =IF($A15="","",SUMIFS('GECC 2026'!H$2:H$200,'GECC 2026'!F$2:F$200,$A15)) -> 0 | C15: =IF($A15="","",SUMIFS('GECC 2026'!I$2:I$200,'GECC 2026'!F$2:F$200,$A15)) -> 0 | D15: =IF($A15="","",SUMIFS('GECC 2026'!$AE$3:$AE$32,'GECC 2026'!$AD$3:$AD$32,$A15)) -> 0 | E15: =IF($A15="","",SUMIFS('GECC 2026'!J$2:J$200,'GECC 2026'!F$2:F$200,$A15)+SUMIFS('GECC 2026'!$AE$3:$AE$32,'GECC 2026'!$AD$3:$AD$32,$A15)) -> 0 | F15: =IF($A15="","",COUNTIFS('GECC 2026'!F$2:F$200,$A15)) -> 2
A16: Eustáquio Rabelo de Souza | B16: =IF($A16="","",SUMIFS('GECC 2026'!H$2:H$200,'GECC 2026'!F$2:F$200,$A16)) -> 1 | C16: =IF($A16="","",SUMIFS('GECC 2026'!I$2:I$200,'GECC 2026'!F$2:F$200,$A16)) -> 0.3 | D16: =IF($A16="","",SUMIFS('GECC 2026'!$AE$3:$AE$32,'GECC 2026'!$AD$3:$AD$32,$A16)) -> 0 | E16: =IF($A16="","",SUMIFS('GECC 2026'!J$2:J$200,'GECC 2026'!F$2:F$200,$A16)+SUMIFS('GECC 2026'!$AE$3:$AE$32,'GECC 2026'!$AD$3:$AD$32,$A16)) -> 1.3 | F16: =IF($A16="","",COUNTIFS('GECC 2026'!F$2:F$200,$A16)) -> 1
A17: Felipe da Costa Malaquias | B17: =IF($A17="","",SUMIFS('GECC 2026'!H$2:H$200,'GECC 2026'!F$2:F$200,$A17)) -> 8 | C17: =IF($A17="","",SUMIFS('GECC 2026'!I$2:I$200,'GECC 2026'!F$2:F$200,$A17)) -> 37.3 | D17: =IF($A17="","",SUMIFS('GECC 2026'!$AE$3:$AE$32,'GECC 2026'!$AD$3:$AD$32,$A17)) -> 0 | E17: =IF($A17="","",SUMIFS('GECC 2026'!J$2:J$200,'GECC 2026'!F$2:F$200,$A17)+SUMIFS('GECC 2026'!$AE$3:$AE$32,'GECC 2026'!$AD$3:$AD$32,$A17)) -> 45.3 | F17: =IF($A17="","",COUNTIFS('GECC 2026'!F$2:F$200,$A17)) -> 2
... A44: Túllio Herbeth Teixeira Moraes | B44: =IF($A44="","",SUMIFS('GECC 2026'!H$2:H$200,'GECC 2026'!F$2:F$200,$A44)) -> 3 | C44: =IF($A44="","",SUMIFS('GECC 2026'!I$2:I$200,'GECC 2026'!F$2:F$200,$A44)) -> 0.45 | D44: =IF($A44="","",SUMIFS('GECC 2026'!$AE$3:$AE$32,'GECC 2026'!$AD$3:$AD$32,$A44)) -> 0 | E44: =IF($A44="","",SUMIFS('GECC 2026'!J$2:J$200,'GECC 2026'!F$2:F$200,$A44)+SUMIFS('GECC 2026'!$AE$3:$AE$32,'GECC 2026'!$AD$3:$AD$32,$A44)) -> 3.45 | F44: =IF($A44="","",COUNTIFS('GECC 2026'!F$2:F$200,$A44)) -> 1
B45: =IF($A45="","",SUMIFS('GECC 2026'!H$2:H$200,'GECC 2026'!F$2:F$200,$A45)) | C45: =IF($A45="","",SUMIFS('GECC 2026'!I$2:I$200,'GECC 2026'!F$2:F$200,$A45)) | D45: =IF($A45="","",SUMIFS('GECC 2026'!$AE$3:$AE$32,'GECC 2026'!$AD$3:$AD$32,$A45)) | E45: =IF($A45="","",SUMIFS('GECC 2026'!J$2:J$200,'GECC 2026'!F$2:F$200,$A45)+SUMIFS('GECC 2026'!$AE$3:$AE$32,'GECC 2026'!$AD$3:$AD$32,$A45)) | F45: =IF($A45="","",COUNTIFS('GECC 2026'!F$2:F$200,$A45))
B46: =IF($A46="","",SUMIFS('GECC 2026'!H$2:H$200,'GECC 2026'!F$2:F$200,$A46)) | C46: =IF($A46="","",SUMIFS('GECC 2026'!I$2:I$200,'GECC 2026'!F$2:F$200,$A46)) | D46: =IF($A46="","",SUMIFS('GECC 2026'!$AE$3:$AE$32,'GECC 2026'!$AD$3:$AD$32,$A46)) | E46: =IF($A46="","",SUMIFS('GECC 2026'!J$2:J$200,'GECC 2026'!F$2:F$200,$A46)+SUMIFS('GECC 2026'!$AE$3:$AE$32,'GECC 2026'!$AD$3:$AD$32,$A46)) | F46: =IF($A46="","",COUNTIFS('GECC 2026'!F$2:F$200,$A46))
B47: =IF($A47="","",SUMIFS('GECC 2026'!H$2:H$200,'GECC 2026'!F$2:F$200,$A47)) | C47: =IF($A47="","",SUMIFS('GECC 2026'!I$2:I$200,'GECC 2026'!F$2:F$200,$A47)) | D47: =IF($A47="","",SUMIFS('GECC 2026'!$AE$3:$AE$32,'GECC 2026'!$AD$3:$AD$32,$A47)) | E47: =IF($A47="","",SUMIFS('GECC 2026'!J$2:J$200,'GECC 2026'!F$2:F$200,$A47)+SUMIFS('GECC 2026'!$AE$3:$AE$32,'GECC 2026'!$AD$3:$AD$32,$A47)) | F47: =IF($A47="","",COUNTIFS('GECC 2026'!F$2:F$200,$A47))
B48: =IF($A48="","",SUMIFS('GECC 2026'!H$2:H$200,'GECC 2026'!F$2:F$200,$A48)) | C48: =IF($A48="","",SUMIFS('GECC 2026'!I$2:I$200,'GECC 2026'!F$2:F$200,$A48)) | D48: =IF($A48="","",SUMIFS('GECC 2026'!$AE$3:$AE$32,'GECC 2026'!$AD$3:$AD$32,$A48)) | E48: =IF($A48="","",SUMIFS('GECC 2026'!J$2:J$200,'GECC 2026'!F$2:F$200,$A48)+SUMIFS('GECC 2026'!$AE$3:$AE$32,'GECC 2026'!$AD$3:$AD$32,$A48)) | F48: =IF($A48="","",COUNTIFS('GECC 2026'!F$2:F$200,$A48))
B49: =IF($A49="","",SUMIFS('GECC 2026'!H$2:H$200,'GECC 2026'!F$2:F$200,$A49)) | C49: =IF($A49="","",SUMIFS('GECC 2026'!I$2:I$200,'GECC 2026'!F$2:F$200,$A49)) | D49: =IF($A49="","",SUMIFS('GECC 2026'!$AE$3:$AE$32,'GECC 2026'!$AD$3:$AD$32,$A49)) | E49: =IF($A49="","",SUMIFS('GECC 2026'!J$2:J$200,'GECC 2026'!F$2:F$200,$A49)+SUMIFS('GECC 2026'!$AE$3:$AE$32,'GECC 2026'!$AD$3:$AD$32,$A49)) | F49: =IF($A49="","",COUNTIFS('GECC 2026'!F$2:F$200,$A49))
B50: =IF($A50="","",SUMIFS('GECC 2026'!H$2:H$200,'GECC 2026'!F$2:F$200,$A50)) | C50: =IF($A50="","",SUMIFS('GECC 2026'!I$2:I$200,'GECC 2026'!F$2:F$200,$A50)) | D50: =IF($A50="","",SUMIFS('GECC 2026'!$AE$3:$AE$32,'GECC 2026'!$AD$3:$AD$32,$A50)) | E50: =IF($A50="","",SUMIFS('GECC 2026'!J$2:J$200,'GECC 2026'!F$2:F$200,$A50)+SUMIFS('GECC 2026'!$AE$3:$AE$32,'GECC 2026'!$AD$3:$AD$32,$A50)) | F50: =IF($A50="","",COUNTIFS('GECC 2026'!F$2:F$200,$A50))
B51: =IF($A51="","",SUMIFS('GECC 2026'!H$2:H$200,'GECC 2026'!F$2:F$200,$A51)) | C51: =IF($A51="","",SUMIFS('GECC 2026'!I$2:I$200,'GECC 2026'!F$2:F$200,$A51)) | D51: =IF($A51="","",SUMIFS('GECC 2026'!$AE$3:$AE$32,'GECC 2026'!$AD$3:$AD$32,$A51)) | E51: =IF($A51="","",SUMIFS('GECC 2026'!J$2:J$200,'GECC 2026'!F$2:F$200,$A51)+SUMIFS('GECC 2026'!$AE$3:$AE$32,'GECC 2026'!$AD$3:$AD$32,$A51)) | F51: =IF($A51="","",COUNTIFS('GECC 2026'!F$2:F$200,$A51))
B52: =IF($A52="","",SUMIFS('GECC 2026'!H$2:H$200,'GECC 2026'!F$2:F$200,$A52)) | C52: =IF($A52="","",SUMIFS('GECC 2026'!I$2:I$200,'GECC 2026'!F$2:F$200,$A52)) | D52: =IF($A52="","",SUMIFS('GECC 2026'!$AE$3:$AE$32,'GECC 2026'!$AD$3:$AD$32,$A52)) | E52: =IF($A52="","",SUMIFS('GECC 2026'!J$2:J$200,'GECC 2026'!F$2:F$200,$A52)+SUMIFS('GECC 2026'!$AE$3:$AE$32,'GECC 2026'!$AD$3:$AD$32,$A52)) | F52: =IF($A52="","",COUNTIFS('GECC 2026'!F$2:F$200,$A52))
B53: =IF($A53="","",SUMIFS('GECC 2026'!H$2:H$200,'GECC 2026'!F$2:F$200,$A53)) | C53: =IF($A53="","",SUMIFS('GECC 2026'!I$2:I$200,'GECC 2026'!F$2:F$200,$A53)) | D53: =IF($A53="","",SUMIFS('GECC 2026'!$AE$3:$AE$32,'GECC 2026'!$AD$3:$AD$32,$A53)) | E53: =IF($A53="","",SUMIFS('GECC 2026'!J$2:J$200,'GECC 2026'!F$2:F$200,$A53)+SUMIFS('GECC 2026'!$AE$3:$AE$32,'GECC 2026'!$AD$3:$AD$32,$A53)) | F53: =IF($A53="","",COUNTIFS('GECC 2026'!F$2:F$200,$A53))
B54: =IF($A54="","",SUMIFS('GECC 2026'!H$2:H$200,'GECC 2026'!F$2:F$200,$A54)) | C54: =IF($A54="","",SUMIFS('GECC 2026'!I$2:I$200,'GECC 2026'!F$2:F$200,$A54)) | D54: =IF($A54="","",SUMIFS('GECC 2026'!$AE$3:$AE$32,'GECC 2026'!$AD$3:$AD$32,$A54)) | E54: =IF($A54="","",SUMIFS('GECC 2026'!J$2:J$200,'GECC 2026'!F$2:F$200,$A54)+SUMIFS('GECC 2026'!$AE$3:$AE$32,'GECC 2026'!$AD$3:$AD$32,$A54)) | F54: =IF($A54="","",COUNTIFS('GECC 2026'!F$2:F$200,$A54))
B55: =IF($A55="","",SUMIFS('GECC 2026'!H$2:H$200,'GECC 2026'!F$2:F$200,$A55)) | C55: =IF($A55="","",SUMIFS('GECC 2026'!I$2:I$200,'GECC 2026'!F$2:F$200,$A55)) | D55: =IF($A55="","",SUMIFS('GECC 2026'!$AE$3:$AE$32,'GECC 2026'!$AD$3:$AD$32,$A55)) | E55: =IF($A55="","",SUMIFS('GECC 2026'!J$2:J$200,'GECC 2026'!F$2:F$200,$A55)+SUMIFS('GECC 2026'!$AE$3:$AE$32,'GECC 2026'!$AD$3:$AD$32,$A55)) | F55: =IF($A55="","",COUNTIFS('GECC 2026'!F$2:F$200,$A55))
B56: =IF($A56="","",SUMIFS('GECC 2026'!H$2:H$200,'GECC 2026'!F$2:F$200,$A56)) | C56: =IF($A56="","",SUMIFS('GECC 2026'!I$2:I$200,'GECC 2026'!F$2:F$200,$A56)) | D56: =IF($A56="","",SUMIFS('GECC 2026'!$AE$3:$AE$32,'GECC 2026'!$AD$3:$AD$32,$A56)) | E56: =IF($A56="","",SUMIFS('GECC 2026'!J$2:J$200,'GECC 2026'!F$2:F$200,$A56)+SUMIFS('GECC 2026'!$AE$3:$AE$32,'GECC 2026'!$AD$3:$AD$32,$A56)) | F56: =IF($A56="","",COUNTIFS('GECC 2026'!F$2:F$200,$A56))
... B100: =IF($A100="","",SUMIFS('GECC 2026'!H$2:H$200,'GECC 2026'!F$2:F$200,$A100)) | C100: =IF($A100="","",SUMIFS('GECC 2026'!I$2:I$200,'GECC 2026'!F$2:F$200,$A100)) | D100: =IF($A100="","",SUMIFS('GECC 2026'!$AE$3:$AE$32,'GECC 2026'!$AD$3:$AD$32,$A100)) | E100: =IF($A100="","",SUMIFS('GECC 2026'!J$2:J$200,'GECC 2026'!F$2:F$200,$A100)+SUMIFS('GECC 2026'!$AE$3:$AE$32,'GECC 2026'!$AD$3:$AD$32,$A100)) | F100: =IF($A100="","",COUNTIFS('GECC 2026'!F$2:F$200,$A100))
D101: =IF($A101="","",SUMIFS('GECC 2026'!$AE$3:$AE$32,'GECC 2026'!$AD$3:$AD$32,$A101)) | E101: =IF($A101="","",SUMIFS('GECC 2026'!J$2:J$200,'GECC 2026'!F$2:F$200,$A101)+SUMIFS('GECC 2026'!$AE$3:$AE$32,'GECC 2026'!$AD$3:$AD$32,$A101))
D102: =IF($A102="","",SUMIFS('GECC 2026'!$AE$3:$AE$32,'GECC 2026'!$AD$3:$AD$32,$A102)) | E102: =IF($A102="","",SUMIFS('GECC 2026'!J$2:J$200,'GECC 2026'!F$2:F$200,$A102)+SUMIFS('GECC 2026'!$AE$3:$AE$32,'GECC 2026'!$AD$3:$AD$32,$A102))
D103: =IF($A103="","",SUMIFS('GECC 2026'!$AE$3:$AE$32,'GECC 2026'!$AD$3:$AD$32,$A103)) | E103: =IF($A103="","",SUMIFS('GECC 2026'!J$2:J$200,'GECC 2026'!F$2:F$200,$A103)+SUMIFS('GECC 2026'!$AE$3:$AE$32,'GECC 2026'!$AD$3:$AD$32,$A103))
D104: =IF($A104="","",SUMIFS('GECC 2026'!$AE$3:$AE$32,'GECC 2026'!$AD$3:$AD$32,$A104)) | E104: =IF($A104="","",SUMIFS('GECC 2026'!J$2:J$200,'GECC 2026'!F$2:F$200,$A104)+SUMIFS('GECC 2026'!$AE$3:$AE$32,'GECC 2026'!$AD$3:$AD$32,$A104))
A105: TOTAL GERAL | B105: =SUM(B5:B100) -> 696 | C105: =SUM(C5:C100) -> 387.78 | D105: =IF($A105="","",SUMIFS('GECC 2026'!$AE$3:$AE$32,'GECC 2026'!$AD$3:$AD$32,$A105)) -> 0 | E105: =IF($A105="","",SUMIFS('GECC 2026'!J$2:J$200,'GECC 2026'!F$2:F$200,$A105)+SUMIFS('GECC 2026'!$AE$3:$AE$32,'GECC 2026'!$AD$3:$AD$32,$A105)) -> 0 | F105: =SUM(F5:F100) -> 112
