Workbook

Sheet Dashboard 2026
A1: DASHBOARD DE CURSOS — 2026
A4: TOTAL DE CURSOS | D4: REALIZADOS | G4: A REALIZAR
A5: =COUNTIF('Ações InCompany'!B:B,2026) -> 20 | B5: cursos | D5: =COUNTIFS('Ações InCompany'!B:B,2026,'Ações InCompany'!C:C,"Realizado") -> 12 | E5: cursos | G5: =COUNTIFS('Ações InCompany'!B:B,2026,'Ações InCompany'!C:C,"A realizar") -> 8
A8: CURSOS REALIZADOS POR PÚBLICO-ALVO | D8: PARTICIPANTES POR PÚBLICO (REALIZADOS)
A10: Público-Alvo | B10: Qtd. Cursos | D10: Público | E10: Qtd. Participantes
A11: Servidores do TCDF | B11: =COUNTIFS('Ações InCompany'!B:B,2026,'Ações InCompany'!C:C,"Realizado",'Ações InCompany'!F:F,"Servidores do TCDF") -> 5 | D11: Servidores (P. Servidores) | E11: =SUMIFS('Ações InCompany'!O:O,'Ações InCompany'!B:B,2026,'Ações InCompany'!C:C,"Realizado") -> 202
A12: Jurisdicionados | B12: =COUNTIFS('Ações InCompany'!B:B,2026,'Ações InCompany'!C:C,"Realizado",'Ações InCompany'!F:F,"Jurisdicionados") -> 7 | D12: Jurisdicionados (P. Jurisdicionados) | E12: =SUMIFS('Ações InCompany'!P:P,'Ações InCompany'!B:B,2026,'Ações InCompany'!C:C,"Realizado") -> 321
A13: Sociedade | B13: =COUNTIFS('Ações InCompany'!B:B,2026,'Ações InCompany'!C:C,"Realizado",'Ações InCompany'!F:F,"Sociedade") -> 0 | D13: Sociedade (P. Sociedade) | E13: =SUMIFS('Ações InCompany'!Q:Q,'Ações InCompany'!B:B,2026,'Ações InCompany'!C:C,"Realizado") -> 73
A14: TOTAL | B14: =SUM(B11:B13) -> 12 | D14: TOTAL GERAL | E14: =SUM(E11:E13) -> 596
A30: CURSOS POR PROGRAMA (TODOS OS STATUS)
A32: Programa | B32: Realizados | C32: A Realizar | D32: Total | E32: % do Total
A33: Treinamento de Jurisdicionados | B33: =COUNTIFS('Ações InCompany'!B:B,2026,'Ações InCompany'!C:C,"Realizado",'Ações InCompany'!G:G,A33) -> 8 | C33: =COUNTIFS('Ações InCompany'!B:B,2026,'Ações InCompany'!C:C,"A realizar",'Ações InCompany'!G:G,A33) -> 1 | D33: =B33+C33 -> 9 | E33: =D33/$D$41 -> 0.45
A34: Administração, Estratégia e Inovação | B34: =COUNTIFS('Ações InCompany'!B:B,2026,'Ações InCompany'!C:C,"Realizado",'Ações InCompany'!G:G,A34) -> 1 | C34: =COUNTIFS('Ações InCompany'!B:B,2026,'Ações InCompany'!C:C,"A realizar",'Ações InCompany'!G:G,A34) -> 2 | D34: =B34+C34 -> 3 | E34: =D34/$D$41 -> 0.15
A35: Inteligência Artificial e Análise de Dados | B35: =COUNTIFS('Ações InCompany'!B:B,2026,'Ações InCompany'!C:C,"Realizado",'Ações InCompany'!G:G,A35) -> 1 | C35: =COUNTIFS('Ações InCompany'!B:B,2026,'Ações InCompany'!C:C,"A realizar",'Ações InCompany'!G:G,A35) -> 1 | D35: =B35+C35 -> 2 | E35: =D35/$D$41 -> 0.1
A36: Escola de Instrutores | B36: =COUNTIFS('Ações InCompany'!B:B,2026,'Ações InCompany'!C:C,"Realizado",'Ações InCompany'!G:G,A36) -> 1 | C36: =COUNTIFS('Ações InCompany'!B:B,2026,'Ações InCompany'!C:C,"A realizar",'Ações InCompany'!G:G,A36) -> 0 | D36: =B36+C36 -> 1 | E36: =D36/$D$41 -> 0.05
A37: Desenvolvimento Individual e Promoção da Cultura Organizacional | B37: =COUNTIFS('Ações InCompany'!B:B,2026,'Ações InCompany'!C:C,"Realizado",'Ações InCompany'!G:G,A37) -> 1 | C37: =COUNTIFS('Ações InCompany'!B:B,2026,'Ações InCompany'!C:C,"A realizar",'Ações InCompany'!G:G,A37) -> 1 | D37: =B37+C37 -> 2 | E37: =D37/$D$41 -> 0.1
A38: Formação de Controladores sociais e cidadãos | B38: =COUNTIFS('Ações InCompany'!B:B,2026,'Ações InCompany'!C:C,"Realizado",'Ações InCompany'!G:G,A38) -> 0 | C38: =COUNTIFS('Ações InCompany'!B:B,2026,'Ações InCompany'!C:C,"A realizar",'Ações InCompany'!G:G,A38) -> 2 | D38: =B38+C38 -> 2 | E38: =D38/$D$41 -> 0.1
A39: Metodologias de Auditoria e Fiscalização | B39: =COUNTIFS('Ações InCompany'!B:B,2026,'Ações InCompany'!C:C,"Realizado",'Ações InCompany'!G:G,A39) -> 0 | C39: =COUNTIFS('Ações InCompany'!B:B,2026,'Ações InCompany'!C:C,"A realizar",'Ações InCompany'!G:G,A39) -> 1 | D39: =B39+C39 -> 1 | E39: =D39/$D$41 -> 0.05
A40: (Sem Programa) | B40: =COUNTIFS('Ações InCompany'!B:B,2026,'Ações InCompany'!C:C,"Realizado",'Ações InCompany'!G:G,"") -> 0 | C40: =COUNTIFS('Ações InCompany'!B:B,2026,'Ações InCompany'!C:C,"A realizar",'Ações InCompany'!G:G,"") -> 0 | D40: =B40+C40 -> 0 | E40: =D40/$D$41 -> 0
A41: TOTAL | B41: =SUM(B33:B40) -> 12 | C41: =SUM(C33:C40) -> 8 | D41: =SUM(D33:D40) -> 20 | E41: =SUM(E33:E40) -> 1

Sheet Dashboard 2025
A1: DASHBOARD DE CURSOS REALIZADOS — 2025
A4: TOTAL DE CURSOS REALIZADOS | D4: TOTAL DE PARTICIPANTES
A5: =COUNTIFS('Ações InCompany'!B:B,2025,'Ações InCompany'!C:C,"Realizado") -> 120 | B5: cursos | D5: =SUMIFS('Ações InCompany'!R:R,'Ações InCompany'!B:B,2025,'Ações InCompany'!C:C,"Realizado") -> 6029 | E5: participantes
A7: CURSOS POR PÚBLICO-ALVO | D7: PARTICIPANTES POR PÚBLICO
A9: Público-Alvo | B9: Qtd. Cursos | D9: Público | E9: Qtd. Participantes
A10: Servidores do TCDF | B10: =COUNTIFS('Ações InCompany'!B:B,2025,'Ações InCompany'!C:C,"Realizado",'Ações InCompany'!F:F,"Servidores do TCDF") -> 61 | D10: Servidores (P. Servidores) | E10: =SUMIFS('Ações InCompany'!O:O,'Ações InCompany'!B:B,2025,'Ações InCompany'!C:C,"Realizado") -> 2649
A11: Jurisdicionados | B11: =COUNTIFS('Ações InCompany'!B:B,2025,'Ações InCompany'!C:C,"Realizado",'Ações InCompany'!F:F,"Jurisdicionados") -> 31 | D11: Jurisdicionados (P. Jurisdicionados) | E11: =SUMIFS('Ações InCompany'!P:P,'Ações InCompany'!B:B,2025,'Ações InCompany'!C:C,"Realizado") -> 2140
A12: Sociedade | B12: =COUNTIFS('Ações InCompany'!B:B,2025,'Ações InCompany'!C:C,"Realizado",'Ações InCompany'!F:F,"Sociedade") -> 28 | D12: Sociedade (P. Sociedade) | E12: =SUMIFS('Ações InCompany'!Q:Q,'Ações InCompany'!B:B,2025,'Ações InCompany'!C:C,"Realizado") -> 1240
A13: TOTAL | B13: =SUM(B10:B12) -> 120 | D13: TOTAL GERAL | E13: =SUM(E10:E12) -> 6029
A29: CURSOS POR PROGRAMA
A31: Programa | B31: Qtd. Cursos | C31: % do Total
A32: Treinamento de Jurisdicionados | B32: =COUNTIFS('Ações InCompany'!B:B,2025,'Ações InCompany'!C:C,"Realizado",'Ações InCompany'!G:G,A32) -> 57 | C32: =B32/$B$42 -> 0.475
A33: Administração, Estratégia e Inovação | B33: =COUNTIFS('Ações InCompany'!B:B,2025,'Ações InCompany'!C:C,"Realizado",'Ações InCompany'!G:G,A33) -> 16 | C33: =B33/$B$42 -> 0.13333333
A34: Desenvolvimento Individual e Promoção da Cultura Organizacional | B34: =COUNTIFS('Ações InCompany'!B:B,2025,'Ações InCompany'!C:C,"Realizado",'Ações InCompany'!G:G,A34) -> 16 | C34: =B34/$B$42 -> 0.13333333
A35: Áreas Temáticas de Fiscalização do Setor Público | B35: =COUNTIFS('Ações InCompany'!B:B,2025,'Ações InCompany'!C:C,"Realizado",'Ações InCompany'!G:G,A35) -> 8 | C35: =B35/$B$42 -> 0.066666667
A36: Mineração e Análise de Dados | B36: =COUNTIFS('Ações InCompany'!B:B,2025,'Ações InCompany'!C:C,"Realizado",'Ações InCompany'!G:G,A36) -> 9 | C36: =B36/$B$42 -> 0.075
A37: Metodologias de Auditoria e Fiscalização | B37: =COUNTIFS('Ações InCompany'!B:B,2025,'Ações InCompany'!C:C,"Realizado",'Ações InCompany'!G:G,A37) -> 6 | C37: =B37/$B$42 -> 0.05
A38: Ambientação e Desenvolvimento na Carreira | B38: =COUNTIFS('Ações InCompany'!B:B,2025,'Ações InCompany'!C:C,"Realizado",'Ações InCompany'!G:G,A38) -> 4 | C38: =B38/$B$42 -> 0.033333333
A39: Avaliação de Políticas Públicas | B39: =COUNTIFS('Ações InCompany'!B:B,2025,'Ações InCompany'!C:C,"Realizado",'Ações InCompany'!G:G,A39) -> 2 | C39: =B39/$B$42 -> 0.016666667
A40: Desenvolvimento Gerencial | B40: =COUNTIFS('Ações InCompany'!B:B,2025,'Ações InCompany'!C:C,"Realizado",'Ações InCompany'!G:G,A40) -> 2 | C40: =B40/$B$42 -> 0.016666667
A41: (Sem Programa) | B41: =COUNTIFS('Ações InCompany'!B:B,2025,'Ações InCompany'!C:C,"Realizado",'Ações InCompany'!G:G,"") -> 0 | C41: =B41/$B$42 -> 0
A42: TOTAL | B42: =SUM(B32:B41) -> 120 | C42: =SUM(C32:C41) -> 1

Sheet PlanoCap
A1: ANO - VIGÊNCIA | B1: EIXO TEMÁTICO | C1: Programa | D1: Público-Alvo Preferencial | E1: Descrição
A2: 2024/2025 | B2: Controle Externo | C2: Avaliação de Políticas Públicas | D2: Membros e servidores que atuam no Controle Externo | E2: Destina-se a oferecer ações de aprendizagem de metodologias necessárias à avaliação de políticas públicas governamentais.
A3: 2024/2025 | B3: Controle Externo | C3: Metodologias de Auditoria e Fiscalização | D3: Membros e servidores que atuam no Controle Externo | E3: Destina-se a oferecer ações de aprendizagem de metodologias necessárias à realização de fiscalizações governamentais, alinhadas às Normas Brasileiras de Auditoria do Setor Público.
A4: 2024/2025 | B4: Controle Externo | C4: Áreas Temáticas de Fiscalização do Setor Público | D4: Membros e servidores que atuam no Controle Externo | E4: Destina-se a oferecer ações de aprendizagem voltadas às áreas temáticas fiscalizadas, como saúde, pessoal, previdência, assistência social, obras e serviços de engenharia, tecnologia de informação e comunicação, licitações e contratos, parcerias público-privadas, concessões e desestatização, entre outros
A5: 2024/2025 | B5: Controle Externo | C5: Treinamento de Jurisdicionados | D5: Servidores Públicos dos órgãos jurisdicionados ao TCDF | E5: Destina-se a oferecer ações de aprendizagem para os gestores e servidores públicos dos órgãos jurisdicionados ao TCDF, a fim de promover a correta e eficiente aplicação dos recursos públicos
A6: 2024/2025 | B6: Controle Externo | C6: Formação de Controladores sociais e cidadãos | D6: Representantes de entidades de Controle social e Cidadãos | E6: Destina-se a oferecer ações de aprendizagem para os cidadãos, para fomentar o exercício do controle social.
A7: 2024/2025 | B7: Organizacional | C7: Mineração e Análise de Dados | D7: Servidores que possam utilizar análise de dados no desempenho de suas atividades | E7: Destina-se a oferecer ações de aprendizagem voltadas à análise e mineração de dados, a fim de identificar informações úteis à tomada de decisão em meio a grandes quantidades de dados.
A8: 2024/2025 | B8: Organizacional | C8: Administração, Estratégia e Inovação | D8: Membros e Servidores do TCDF | E8: Destina-se a oferecer ações de aprendizagem para auxiliar na gestão e apoio estratégico do TCDF, assim como promover a inovação na Casa. As ações buscam aprimorar processos como os de planejamento, gestão de pessoas, gestão da informação, gestão de projetos, gestão de processos, gestão administrativa, gestão contratual, relacionamento com o cliente, operacionalização de sistemas, entre outros
A9: 2024/2025 | B9: Programas Transversais | C9: Desenvolvimento Gerencial | D9: Servidores que ocupam função gerencial e potenciais líderes a desenvolver | E9: Destina-se a oferecer ações de aprendizagem para os atuais dirigentes do TCDF, considerando as necessidades de cada nível gerencial (estratégico, tático e operacional), àqueles que assumem funções gerenciais e os servidores com potencial de atuação gerencial no TCDF. As ações devem auxiliar os gestores no exercício da função gerencial, aprimorando competências relacionadas à gestão de desempenho, ao desenvolvimento da equipe, gestão da equipe remota e/ou híbrida, orientação estratégica, feedback, entre outros.
A10: 2024/2025 | B10: Programas Transversais | C10: Desenvolvimento Individual e Promoção da Cultura Organizacional | D10: Servidores do TCDF | E10: Destina-se a oferecer ações de aprendizagem para auxiliar no desenvolvimento de competências funcionais dos servidores, tais quais orientação para resultado, ética e relacionamento interpessoal.
A11: 2024/2025 | B11: Programas Transversais | C11: Ambientação e Desenvolvimento na Carreira | D11: Servidores do TCDF | E11: Destina-se a oferecer ações de aprendizagem para auxiliar na ambientação e promoção de servidores, promovendo a visão sistêmica da sua atuação no âmbito do TCDF

Sheet Validação Dados
A1: Público-alvo | B1: Modalidade | C1: Previsão | D1: Status
A2: Servidores do TCDF | B2: Instrutoria Interna | C2: Previsto | D2: A realizar
A3: Jurisdicionados | B3: Instrutoria Externa | C3: Solicitado | D3: Em andamento
A4: Sociedade | B4: Híbrida | D4: Cancelado
A5: Híbrido | D5: Realizado
D6: Adiado

Sheet Ações InCompany
A1: ID | B1: Ano | C1: Status Evento | D1: Processo | E1: Curso | F1: Público-Alvo | G1: Programa | H1: Data TXT | I1: Início | J1: Término | K1: Modalidade | L1: Valor instrutoria | M1: Nota Av. Reação | N1: Qtd Vagas | O1: P. Servidores | P1: P. Jurisdicionados | Q1: P. Sociedade | R1: Total Part. | S1: C.H. | T1: Instrutor
A2: 2014-001 | B2: 2014 | C2: Realizado | E2: CURSO DE ELABORAÇÃO DE PARECERES E RELATÓRIOS | F2: Servidores do TCDF | G2: Metodologias de Auditoria e Fiscalização | H2: 17 a 21/03/2014 | I2: 41715 | J2: 41719 | K2: Instrutoria Externa | L2: 19500 | O2: 20 | R2: =SUM(O2:Q2) -> 20 | S2: 20
A3: 2014-002 | B3: 2014 | C3: Realizado | E3: ELABORAÇÃO DE PLANO DE AUDITORIA E MATRIZ DE PLANEJAMENTO | F3: Servidores do TCDF | G3: Metodologias de Auditoria e Fiscalização | H3: 14 e 14/04/2014 | I3: 41743 | J3: 41744 | K3: Instrutoria Externa | L3: 28000 | O3: 16 | R3: =SUM(O3:Q3) -> 16 | S3: 16
A4: 2014-003 | B4: 2014 | C4: Realizado | E4: CURSO DE EXCEL AVANÇADO | F4: Servidores do TCDF | G4: Mineração e Análise de Dados | H4: 02 a 09/06/2014 | I4: 41792 | J4: 41799 | K4: Instrutoria Interna | L4: 2991 | O4: 24 | R4: =SUM(O4:Q4) -> 24 | S4: 24
A5: 2014-004 | B5: 2014 | C5: Realizado | E5: REGIME DIFERENCIADO DE CONTRATAÇÕES PÚBLICAS - RDC | F5: Servidores do TCDF | G5: Administração, Estratégia e Inovação | H5: 24 e 25/06/2014 | I5: 41814 | J5: 41815 | K5: Instrutoria Externa | L5: 41341.16 | O5: 16 | R5: =SUM(O5:Q5) -> 16 | S5: 16
A6: 2014-005 | B6: 2014 | C6: Realizado | E6: ENGENHARIA ECONÔMICA I E II - CAPACITAÇÃO EM PARCERIAS PÚBLICO PRIVADAS E CONCESSÕES DE | F6: Servidores do TCDF | G6: Metodologias de Auditoria e Fiscalização | H6: 04 a 08/08/2014 | I6: 41855 | J6: 41859 | K6: Instrutoria Externa | L6: 54900 | O6: 40 | R6: =SUM(O6:Q6) -> 40 | S6: 40
A7: 2014-006 | B7: 2014 | C7: Realizado | E7: CURSO TÉCNICAS DE AUDITORIA OPERACIONAL | F7: Servidores do TCDF | G7: Metodologias de Auditoria e Fiscalização | H7: 10/09/2014 | I7: 41892 | J7: 41892 | K7: Instrutoria Externa | L7: 15000 | O7: 30 | R7: =SUM(O7:Q7) -> 30 | S7: 30
A8: 2014-007 | B8: 2014 | C8: Realizado | F8: Servidores do TCDF | G8: Metodologias de Auditoria e Fiscalização | H8: 31/10/2014 | I8: 41943 | J8: 41943 | K8: Instrutoria Externa | L8: 33260 | O8: 24 | R8: =SUM(O8:Q8) -> 24 | S8: 24
A9: 2014-008 | B9: 2014 | C9: Realizado | E9: PROCESSO DE CONTRATAÇÃO PÚBLICA | F9: Servidores do TCDF | G9: Administração, Estratégia e Inovação | H9: 10 a 14/11/2014 | I9: 41953 | J9: 41957 | K9: Instrutoria Interna | L9: 4353.54 | P9: 37 | R9: =SUM(O9:Q9) -> 37 | S9: 8
A10: 2014-009 | B10: 2014 | C10: Realizado | E10: TERMO DE REFERÊNCIA DE SERVIÇOS CONTINUADOS COM DEDICAÇÃO EXCLUSIVA DE MÃO DE OBRA | F10: Servidores do TCDF | G10: Metodologias de Auditoria e Fiscalização | H10: 24 a 28/11/2014 | I10: 41967 | J10: 41971 | K10: Instrutoria Interna | L10: 4353.54 | P10: 58 | R10: =SUM(O10:Q10) -> 58 | S10: 20
A11: 2015-001 | B11: 2015 | C11: Realizado | D11: 1683/2015 | E11: ELABORAÇÃO DE PARECERES E RELATÓRIOS | F11: Servidores do TCDF | G11: Metodologias de Auditoria e Fiscalização | H11: 23 a 27/03/2015 | I11: 42086 | J11: 42090 | K11: Instrutoria Externa | L11: 23500 | O11: 25 | R11: =SUM(O11:Q11) -> 25 | S11: 20 | T11: José Paulo Moreira de Oliveira
A12: 2015-002 | B12: 2015 | C12: Realizado | D12: 3716/2015 | E12: O PROCESSO DE CONTRATAÇÃO PÚBLICA | F12: Jurisdicionados | G12: Administração, Estratégia e Inovação | H12: 06 a 10/04/2015 | I12: 42100 | J12: 42104 | K12: Instrutoria Interna | L12: 4992.74 | P12: 85 | R12: =SUM(O12:Q12) -> 85 | S12: 20 | T12: Amauri Alves Nery
A13: 2015-003 | B13: 2015 | C13: Realizado | D13: 5891/2015 | E13: AUDITORIA EM OBRAS RODOVIÁRIAS | F13: Servidores do TCDF | G13: Áreas Temáticas de Fiscalização do Setor Público | H13: 06 a 10/04/2015 | I13: 42100 | J13: 42104 | K13: Instrutoria Externa | L13: 29000 | O13: 19 | R13: =SUM(O13:Q13) -> 19 | S13: 40 | T13: Elci Pessoa Júnior
A14: 2015-004 | B14: 2015 | C14: Realizado | D14: 2515/2015 | E14: TERMO DE REFERÊNCIA DE SERVIÇOS CONTINUADOS COM DEDICAÇÃO EXCLUSIVA DE MÃO DE OBRA | F14: Jurisdicionados | G14: Treinamento de Jurisdicionados | H14: 13 a 17/04/2015 | I14: 42107 | J14: 42111 | K14: Instrutoria Interna | L14: 4447.52 | P14: 89 | R14: =SUM(O14:Q14) -> 89 | S14: 20 | T14: Leonardo José Alves Leal Neri
A15: 2015-005 | B15: 2015 | C15: Realizado | D15: 7690/2015 | E15: FISCALIZAÇÃO DE CONTRATOS ADMINISTRATIVOS | F15: Servidores do TCDF | G15: Administração, Estratégia e Inovação | H15: 16, 17, 22, 23 e 24/04/2020 | I15: 42110 | J15: 42118 | K15: Instrutoria Interna | L15: 4447.52 | O15: 37 | R15: =SUM(O15:Q15) -> 37 | S15: 30 | T15: Leonardo José Alves Leal Neri
A16: 2015-006 | B16: 2015 | C16: Realizado | E16: PALESTRA CONSELHOS REGIONAIS DE SAÚDE | F16: Sociedade | G16: N/A | I16: 42122 | J16: 42122 | K16: Instrutoria Interna | L16: 0 | O16: 0 | P16: 0 | Q16: 0 | R16: =SUM(O16:Q16) -> 0 | S16: 5
A17: 2015-007 | B17: 2015 | C17: Realizado | D17: 3481/2015 | E17: PROCESSO NOS TRIBUNAIS DE CONTAS | F17: Servidores do TCDF | G17: Metodologias de Auditoria e Fiscalização | H17: 26 a 29/05/2015 | I17: 42129 | J17: 42132 | K17: Instrutoria Externa | L17: 35500 | O17: 30 | R17: =SUM(O17:Q17) -> 30 | S17: 16 | T17: Odilon Cavallari de Oliveira
A18: 2015-008 | B18: 2015 | C18: Realizado | D18: 5654/2015 | E18: A NOVA CONTABILIDADE APLICADA AO SETOR PÚBLICO | F18: Servidores do TCDF | G18: Administração, Estratégia e Inovação | H18: 11 a 15/05/2015 | I18: 42135 | J18: 42139 | K18: Instrutoria Interna | L18: 4992.74 | O18: 30 | R18: =SUM(O18:Q18) -> 30 | S18: 20 | T18: Romildo Araújo da Silva
A19: 2015-009 | B19: 2015 | C19: Realizado | D19: 14060/2015 | E19: TREINAMENTO DO SISTEMA TERRAGEO | F19: Servidores do TCDF | G19: Administração, Estratégia e Inovação | H19: 22/05/2015 | I19: 42146 | J19: 42146 | K19: Instrutoria Externa | L19: 0 | O19: 15 | R19: =SUM(O19:Q19) -> 15 | S19: 8 | T19: INSTRUTOR EXTERNO TERRACAP
A20: 2015-010 | B20: 2015 | C20: Realizado | D20: 1098/2015 | E20: EXCEL AVANÇADO | F20: Servidores do TCDF | G20: Mineração e Análise de Dados | H20: 25/05 a 01/06/2015 | I20: 42149 | J20: 42156 | K20: Instrutoria Externa | L20: 2630 | O20: 14 | R20: =SUM(O20:Q20) -> 14 | S20: 24 | T20: Logus TI
A21: 2015-011 | B21: 2015 | C21: Realizado | D21: 12742/2015 | E21: TREINAMENTO SIGGO (Sistema Integrado de Contabilidade Governamental) | F21: Servidores do TCDF | G21: Administração, Estratégia e Inovação | H21: 08 a 12/06/2015 | I21: 42163 | J21: 42167 | K21: Instrutoria Interna | L21: 0 | O21: 14 | R21: =SUM(O21:Q21) -> 14 | S21: 20 | T21: Rômulo Miranda Alvim
A22: 2015-012 | B22: 2015 | C22: Realizado | D22: 13480/2015 | E22: GESTÃO E FISCALIZAÇÃO DE CONTRATOS ADMINISTRATIVOS - MÓDULO I | F22: Jurisdicionados | G22: Treinamento de Jurisdicionados | H22: 15 a 19/06/2015 | I22: 42170 | J22: 42174 | K22: Instrutoria Interna | L22: 4447.52 | P22: 49 | R22: =SUM(O22:Q22) -> 49 | S22: 20 | T22: Roberto Dias Santiago
A23: 2015-013 | B23: 2015 | C23: Realizado | D23: 19283/2015 | E23: SEMINÁRIO ATUALIZAÇÃO EM LEGISLAÇÃO DE PESSOAL | F23: Servidores do TCDF | G23: Administração, Estratégia e Inovação | H23: 05 e 07/08/2015 | I23: 42221 | J23: 42223 | K23: Instrutoria Interna | L23: 0 | O23: 43 | R23: =SUM(O23:Q23) -> 43 | S23: 8 | T23: Inácio Magalhães Filho
A24: 2015-014 | B24: 2015 | C24: Realizado | D24: 22314/2015 | E24: METODOLOGIA DE CONSTRUÇÃO E ATUALIZAÇÃO DO TESAURO DE CONTAS DO DF | F24: Servidores do TCDF | G24: Mineração e Análise de Dados | H24: 24 a 28/08/2015 | I24: 42240 | J24: 42244 | K24: Instrutoria Interna | L24: 2702.38 | O24: 25 | R24: =SUM(O24:Q24) -> 25 | S24: 20 | T24: ANDREA FORTALEZA BRANDES DE SOUZA
A25: 2015-015 | B25: 2015 | C25: Realizado | D25: 17949/2015 | E25: RESPONSABILIDADE DE AGENTES PÚBLICOS E PRIVADOS PERANTE OS TRIBUNAIS DE CONTAS | F25: Servidores do TCDF | G25: Treinamento de Jurisdicionados | H25: 31/08/2015 a 04/09/2015 | I25: 42247 | J25: 42251 | K25: Instrutoria Externa | L25: 33600 | O25: 35 | R25: =SUM(O25:Q25) -> 35 | S25: 20 | T25: Aprimora Treinamentos
A26: 2015-016 | B26: 2015 | C26: Realizado | D26: 23973/2015 | E26: TÉCNICAS DE AUDITORIA OPERACIONAL | F26: Servidores do TCDF | G26: Metodologias de Auditoria e Fiscalização | H26: 14 a 18/09/2015 | I26: 42261 | J26: 42265 | K26: Instrutoria Externa | L26: 15000 | O26: 35 | R26: =SUM(O26:Q26) -> 35 | S26: 25 | T26: Dagomar Henrique Limas
A27: 2015-017 | B27: 2015 | C27: Realizado | E27: LEGISLAÇÃO DE PESSOAL NO SETOR PÚBLICO COM ENFOQUE NA LC nº 840/2011 | F27: Jurisdicionados | G27: N/A | I27: 42268 | J27: 42272 | K27: Instrutoria Interna | L27: 4447.52 | O27: 87 | R27: =SUM(O27:Q27) -> 87
A28: 2015-018 | B28: 2015 | C28: Realizado | D28: 29327/2015 | E28: CAPACITAÇÃO PARA CONSELHEIROS DE SAÚDE - Turma I | F28: Sociedade | G28: Treinamento de Jurisdicionados | H28: 29/09/2015 a 02/10/2015 | I28: 42276 | J28: 42279 | K28: Instrutoria Interna | L28: 4076.52 | Q28: 46 | R28: =SUM(O28:Q28) -> 46 | S28: 20 | T28: Romildo Araújo da Silva; Tarsila Firmino Ely
A29: 2015-019 | B29: 2015 | C29: Realizado | D29: 30040/2015 | E29: OFICINA DE ACCESS AVANÇADO | F29: Servidores do TCDF | G29: Mineração e Análise de Dados | H29: 05 a 09/10/2015 | I29: 42282 | J29: 42286 | K29: Instrutoria Interna | L29: 4447.52 | O29: 15 | R29: =SUM(O29:Q29) -> 15 | S29: 20 | T29: JOSDEYVI MAGALHAES RUSSI
A30: 2015-020 | B30: 2015 | C30: Realizado | D30: 13480/2015 | E30: GESTÃO E FISCALIZAÇÃO DE CONTRATOS ADMINISTRATIVOS - MÓDULO II | F30: Jurisdicionados | G30: Treinamento de Jurisdicionados | H30: 19 a 23/10/2015 | I30: 42296 | J30: 42300 | K30: Instrutoria Interna | L30: 4447.52 | P30: 54 | R30: =SUM(O30:Q30) -> 54 | S30: 20 | T30: Roberto Dias Santiago
A31: 2015-021 | B31: 2015 | C31: Realizado | E31: CONTRATAÇÃO DE SOLUÇÕES DE TECNOLOGIA DA INFORMAÇÃO E COMUNICAÇÃO - IN nº 04/2014 | F31: Jurisdicionados | G31: N/A | I31: 42303 | J31: 42305 | K31: Instrutoria Interna | L31: 4447.52 | O31: 52 | R31: =SUM(O31:Q31) -> 52 | S31: 0
A32: 2015-022 | B32: 2015 | C32: Realizado | D32: 29327/2015 | E32: CAPACITAÇÃO PARA CONSELHEIROS DE SAÚDE - Turma II | F32: Sociedade | G32: Treinamento de Jurisdicionados | H32: 17 a 20/11/2015 | I32: 42325 | J32: 42328 | K32: Instrutoria Interna | L32: 4076.52 | Q32: 46 | R32: =SUM(O32:Q32) -> 46 | S32: 20 | T32: Romildo Araújo da Silva; Tarsila Firmino Ely
A33: 2016-001 | B33: 2016 | C33: Realizado | D33: 13946/2016 | E33: Sistema Channel - Turma 1 | F33: Servidores do TCDF | G33: N/A | I33: 42495 | K33: Instrutoria Externa | L33: 0 | O33: 14 | R33: =SUM(O33:Q33) -> 14 | S33: 8 | T33: Breno
A34: 2016-002 | B34: 2016 | C34: Realizado | E34: Instrutoria | F34: Servidores do TCDF | G34: N/A | I34: 42495 | K34: Instrutoria Externa | L34: 22500 | O34: 25 | R34: =SUM(O34:Q34) -> 25 | S34: 20
A35: 2016-003 | B35: 2016 | C35: Realizado | D35: 30532/2016; 28880/2016 | E35: Trilhas de Aprendizagem | F35: Servidores do TCDF | G35: N/A | I35: 42495 | K35: Instrutoria Externa | L35: 25200 | O35: 17 | R35: =SUM(O35:Q35) -> 17 | S35: 20 | T35: Pedro Paulo Carbone; Sylvio Maestrelli; Anelise Pereira Sihler
A36: 2016-004 | B36: 2016 | C36: Realizado | D36: 8721/2016 | E36: Termo de Referência de Serviços Continuados com dedicação exclusiva de mão de obra | F36: Jurisdicionados | G36: Treinamento de Jurisdicionados | H36: 16 a 20/05/2016 | I36: 42506 | J36: 42510 | K36: Instrutoria Interna | L36: 6671.48 | P36: 75 | R36: =SUM(O36:Q36) -> 75 | S36: 20 | T36: Leonardo José Alves Leal Neri
A37: 2016-005 | B37: 2016 | C37: Realizado | D37: 16866/2016 | E37: Workshop para prefeitos comunitários | F37: Sociedade | G37: Treinamento de Jurisdicionados | H37: 13/06/2016 | I37: 42534 | J37: 42534 | K37: Instrutoria Interna | L37: 2668.6 | P37: 18 | R37: =SUM(O37:Q37) -> 18 | S37: 3 | T37: LUIZ GENEDIO MENDES JORGE
A38: 2016-006 | B38: 2016 | C38: Realizado | D38: 8195/2016 | E38: Workshop sobre Parcerias Público-Privadas | F38: Sociedade | G38: Treinamento de Jurisdicionados | H38: 13 e 14/06/2016 | I38: 42534 | J38: 42535 | K38: Instrutoria Externa | L38: 0 | O38: 33 | R38: =SUM(O38:Q38) -> 33 | S38: 10 | T38: Maria Aparecida Aiko Ikemura
A39: 2016-007 | B39: 2016 | C39: Realizado | D39: 12356/2016 | E39: Contratação Direta - Dispensa e Inexigibilidade de Licitação | F39: Jurisdicionados | G39: Treinamento de Jurisdicionados | H39: 13 a 17/06/2016 | I39: 42534 | J39: 42538 | K39: Instrutoria Interna | L39: 6671.48 | P39: 55 | R39: =SUM(O39:Q39) -> 55 | S39: 20 | T39: Roberto Dias Santiago
A40: 2016-008 | B40: 2016 | C40: Realizado | D40: 16351/2016 | E40: Capacitação para Conselheiros de Saúde | F40: Sociedade | G40: Metodologias de Auditoria e Fiscalização | H40: 27/06/2016 a 01/07/2016 | I40: 42548 | J40: 42552 | K40: Instrutoria Interna | L40: 7080.23 | Q40: 45 | R40: =SUM(O40:Q40) -> 45 | S40: 20 | T40: ROMILDO ARAUJO DA SILVA; TARSILA FIRMINO ELY
A41: 2016-009 | B41: 2016 | C41: Realizado | D41: 13816/2016 | E41: Access básico aplicado ao SIGGO | F41: Servidores do TCDF | G41: Mineração e Análise de Dados | H41: 27/06/2016 a 01/07/2016 | I41: 42548 | J41: 42552 | K41: Instrutoria Interna | L41: 6671.48 | O41: 15 | R41: =SUM(O41:Q41) -> 15 | S41: 20 | T41: ROMULO MIRANDA ALVIM
A42: 2016-010 | B42: 2016 | C42: Realizado | D42: 15487/2016 | E42: Acompanhamento do Orçamento Público – Jornalistas | F42: Sociedade | G42: Treinamento de Jurisdicionados | H42: 28/06/2016 a 30/06/2016 | I42: 42549 | J42: 42551 | K42: Instrutoria Interna | L42: 1334.3 | Q42: 21 | R42: =SUM(O42:Q42) -> 21 | S42: 8 | T42: Luiz Genédio Mendes Jorge
A43: 2016-011 | B43: 2016 | C43: Realizado | D43: 14910/2016 | E43: Curso de Educação Financeira | F43: Servidores do TCDF | G43: Desenvolvimento Individual e Promoção da Cultura Organizacional | H43: 20 e 21/07/2016 | I43: 42571 | J43: 42572 | K43: Instrutoria Externa | L43: 0 | O43: 40 | R43: =SUM(O43:Q43) -> 40 | S43: 9 | T43: BRB
A44: 2016-012 | B44: 2016 | C44: Realizado | D44: 20995/2016 | E44: Governança e gestão de TIC - Melhores práticas de mercado | F44: Jurisdicionados | G44: Treinamento de Jurisdicionados | H44: 01 e 02/08/2016 | I44: 42583 | J44: 42584 | K44: Instrutoria Interna | L44: 2668.6 | P44: 45 | R44: =SUM(O44:Q44) -> 45 | S44: 8 | T44: Everton Peixoto Correia de Assumpção
A45: 2016-013 | B45: 2016 | C45: Realizado | D45: 13794/2016 | E45: Oficina de Access Intermediário | F45: Servidores do TCDF | G45: Mineração e Análise de Dados | H45: 08 a 12/08/2016 | I45: 42590 | J45: 42594 | K45: Instrutoria Interna | L45: 7488.98 | O45: 13 | R45: =SUM(O45:Q45) -> 13 | S45: 20 | T45: Josdeyvi Magalhães Russi
A46: 2016-014 | B46: 2016 | C46: Realizado | D46: 13832/2016 | E46: Elaboração de Relatórios e Pareceres com base no manual de redação do Tribunal de Contas do Distrito Federal - Turma 1 | F46: Servidores do TCDF | G46: Desenvolvimento Individual e Promoção da Cultura Organizacional | H46: 15 a 19/08/2016 | I46: 42597 | J46: 42601 | K46: Instrutoria Externa | L46: 7880 | O46: 35 | R46: =SUM(O46:Q46) -> 35 | S46: 20 | T46: Profª Paula Cobucci
A47: 2016-015 | B47: 2016 | C47: Realizado | D47: 23447/2016 | E47: Processo de Contratação Pública na área de Saúde – Termos de Referência | F47: Jurisdicionados | G47: Treinamento de Jurisdicionados | H47: 15 a 19/08/2016 | I47: 42597 | J47: 42601 | K47: Híbrida | L47: 9556.7 | O47: 8 | P47: 63 | R47: =SUM(O47:Q47) -> 71 | S47: 20 | T47: Tarsila Firmino Ely; Romildo Araújo da Silva; Luiz Eduardo Costa
A48: 2016-016 | B48: 2016 | C48: Realizado | D48: 2251/2016 | E48: XXII SEMAT | F48: Híbrido | G48: Treinamento de Jurisdicionados | H48: 31/08 a 01/09/2016 | I48: 42613 | J48: 42614 | K48: Instrutoria Externa | L48: 44423.6 | O48: 87 | P48: 242 | Q48: 0 | R48: =SUM(O48:Q48) -> 329 | S48: 8 | T48: Ives Gandra da Silva Martins Filho; Pedro Jorge Simon; Antonio Renato Alves Rainha; Luiz Genédio Mendes Jorge; Henrique Moraes Ziller; Maria Rosynete de Oliveira; Eliana Calmon
A49: 2016-017 | B49: 2016 | C49: Realizado | D49: 24427/2016 | E49: Gestão de Processos | F49: Servidores do TCDF | G49: Administração, Estratégia e Inovação | H49: 12 a 16/09/2016 | I49: 42625 | J49: 42629 | K49: Instrutoria Externa | L49: 9200 | O49: 26 | R49: =SUM(O49:Q49) -> 26 | S49: 20 | T49: Annibal
A50: 2016-018 | B50: 2016 | C50: Realizado | D50: 26365/2016 | E50: Orçamento Público | F50: Servidores do TCDF | G50: Administração, Estratégia e Inovação | H50: 19 a 23/09/2016 | I50: 42632 | J50: 42636 | K50: Instrutoria Externa | L50: 5900 | O50: 35 | R50: =SUM(O50:Q50) -> 35 | S50: 20 | T50: Profº Rita (SENADO)
A51: 2016-019 | B51: 2016 | C51: Realizado | D51: 3169/2016 | E51: Gestão e fiscalização de contratos adm. - M1, Turma 1 | F51: Jurisdicionados | G51: Treinamento de Jurisdicionados | H51: 19 a 23/09/2016 | I51: 42632 | J51: 42636 | K51: Instrutoria Interna | L51: 6671.48 | P51: 46 | R51: =SUM(O51:Q51) -> 46 | S51: 20 | T51: Roberto Dias Santiago
A52: 2016-020 | B52: 2016 | C52: Realizado | D52: 3169/2016 | E52: Gestão e fiscalização de contratos adm. - M2, Turma 1 | F52: Jurisdicionados | G52: Treinamento de Jurisdicionados | H52: 19 a 23/09/2016 | I52: 42632 | J52: 42636 | K52: Instrutoria Interna | L52: 6671.48 | P52: 52 | R52: =SUM(O52:Q52) -> 52 | S52: 20 | T52: Roberto Dias Santiago
A53: 2016-021 | B53: 2016 | C53: Realizado | D53: 26373/2016 | E53: Regime Próprio de Previdência Social | F53: Servidores do TCDF | G53: Desenvolvimento Individual e Promoção da Cultura Organizacional | H53: 03 a 07/10/2016 | I53: 42646 | J53: 42650 | K53: Instrutoria Interna | L53: 8088.22 | O53: 34 | R53: =SUM(O53:Q53) -> 34 | S53: 20 | T53: Michel Martins de Morais
A54: 2016-022 | B54: 2016 | C54: Realizado | D54: 18508/2016 | E54: Como elaborar a planilha de formação de preços da IN nº 02/08 e como julgar a licitação para a contratação dos serviços contínuos | F54: Servidores do TCDF | G54: Metodologias de Auditoria e Fiscalização | H54: 17 a 19/10/2016 | I54: 42660 | J54: 42662 | K54: Instrutoria Externa | L54: 54183.63 | O54: 27 | R54: =SUM(O54:Q54) -> 27 | S54: 15 | T54: Zênite Informação e Consultoria
A55: 2016-023 | B55: 2016 | C55: Realizado | D55: 30532/2016 | E55: Aprendizagem Organizacional | F55: Servidores do TCDF | G55: Administração, Estratégia e Inovação | H55: 20, 21, 24, 27 e 28/10/2016 | I55: 42663 | J55: 42671 | K55: Instrutoria Externa | L55: 22500 | O55: 16 | R55: =SUM(O55:Q55) -> 16 | S55: 20 | T55: Pedro Paulo Carbone; Sylvio Maestrelli; Anelise Pereira Sihler
A56: 2016-024 | B56: 2016 | C56: Realizado | D56: 28597/2016 | E56: Contratação de TI com base na jurisprudência do TCDF | F56: Jurisdicionados | G56: Treinamento de Jurisdicionados | H56: 24 a 26/10/2016 | I56: 42667 | J56: 42669 | K56: Instrutoria Interna | L56: 4002.88 | P56: 55 | R56: =SUM(O56:Q56) -> 55 | S56: 12 | T56: Marcelo Oliveira Vasconcelos
A57: 2016-025 | B57: 2016 | C57: Realizado | D57: 29925/2016 | E57: Excel Avançado | F57: Servidores do TCDF | G57: Mineração e Análise de Dados | H57: 07 a 11/11/2016 | I57: 42681 | J57: 42685 | K57: Instrutoria Interna | L57: 8088.22 | O57: 14 | R57: =SUM(O57:Q57) -> 14 | S57: 20 | T57: Josdeyvi Magalhães Russi
A58: 2016-026 | B58: 2016 | C58: Realizado | D58: 30869/2016 | E58: Legislação de Pessoal no Setor Público com enfoque na LC 840/2011 | F58: Jurisdicionados | G58: Treinamento de Jurisdicionados | H58: 07 a 11/11/2016 | I58: 42681 | J58: 42685 | K58: Instrutoria Interna | L58: 6671.48 | P58: 47 | R58: =SUM(O58:Q58) -> 47 | S58: 20 | T58: Sebastião Cal de Miranda
A59: 2016-027 | B59: 2016 | C59: Realizado | D59: 30354/2016 | E59: Elaboração de Relatórios e Pareceres com base no Manual de Redação Oficial do TCDF - Turma 2 | F59: Servidores do TCDF | G59: Desenvolvimento Individual e Promoção da Cultura Organizacional | H59: 21, 22, 23, 24 e 28/11/2016 | I59: 42695 | J59: 42702 | K59: Instrutoria Externa | L59: 7880 | O59: 31 | R59: =SUM(O59:Q59) -> 31 | S59: 20 | T59: Paula Cobucci
A60: 2016-028 | B60: 2016 | C60: Realizado | D60: 9272/2016 | E60: Gestão e fiscalização de contratos adm. - M2, Turma 2 | F60: Jurisdicionados | G60: Treinamento de Jurisdicionados | H60: 21 a 25/11/2016 | I60: 42695 | J60: 42699 | K60: Instrutoria Interna | L60: 5612 | P60: 28 | R60: =SUM(O60:Q60) -> 28 | S60: 20 | T60: Roberto Dias Santiago
A61: 2016-029 | B61: 2016 | C61: Realizado | D61: 9272/2016 | E61: Gestão e fiscalização de contratos adm. - M1, Turma 2 | F61: Jurisdicionados | G61: Treinamento de Jurisdicionados | H61: 21 a 25/11/2016 | I61: 42695 | J61: 42699 | K61: Instrutoria Interna | L61: 5612 | P61: 34 | R61: =SUM(O61:Q61) -> 34 | S61: 20 | T61: Roberto Dias Santiago
A62: 2016-030 | B62: 2016 | C62: Realizado | D62: 32080/2016 | E62: Contratação e Fiscalização de Obras Públicas - Aspectos Polêmicos | F62: Jurisdicionados | G62: Treinamento de Jurisdicionados | H62: 05 a 07/12/2016 | I62: 42709 | J62: 42711 | K62: Instrutoria Interna | L62: 8000 | P62: 60 | R62: =SUM(O62:Q62) -> 60 | S62: 20 | T62: ADRIANA CUOCO PORTUGAL; MARCOS GARCIA DA SILVA PINTO
A63: 2017-001 | B63: 2017 | C63: Realizado | D63: 30532/2016 | E63: Instrutoria - Turma 2 | F63: Servidores do TCDF | G63: Administração, Estratégia e Inovação | H63: 06, 07, 08, 20 e 21/02/2017 | I63: 42773 | J63: 42788 | K63: Instrutoria Externa | L63: 27300 | O63: 29 | R63: =SUM(O63:Q63) -> 29 | S63: 26 | T63: Carbone, Sylvio - Inteletto
A64: 2017-002 | B64: 2017 | C64: Realizado | D64: 30532/2016 | E64: Tutoria em EAD | F64: Servidores do TCDF | G64: Administração, Estratégia e Inovação | H64: 06 e 31/03/2017 | I64: 42800 | J64: 42825 | K64: Instrutoria Externa | L64: 54300 | O64: 26 | R64: =SUM(O64:Q64) -> 26 | S64: 30 | T64: Pedro Paulo Carbone; Sylvio Maestrelli; Anelise Pereira Sihler
A65: 2017-003 | B65: 2017 | C65: Realizado | D65: 3164/2017 | E65: Gestão e Fiscalização de Contratos Adm. - M1 | F65: Jurisdicionados | G65: Treinamento de Jurisdicionados | H65: 13 a 17/03/2017 | I65: 42807 | J65: 42811 | K65: Instrutoria Interna | L65: 6962.15 | P65: 47 | R65: =SUM(O65:Q65) -> 47 | S65: 20 | T65: Roberto Dias Santiago
A66: 2017-004 | B66: 2017 | C66: Realizado | D66: 2265/2017 | E66: Excel Avançado - I | F66: Servidores do TCDF | G66: Mineração e Análise de Dados | H66: 20 a 24/03/2017 | I66: 42814 | J66: 42818 | K66: Instrutoria Interna | L66: 7466.41 | O66: 20 | R66: =SUM(O66:Q66) -> 20 | S66: 20 | T66: Josdeyvi Magalhães Russi
A67: 2017-005 | B67: 2017 | C67: Realizado | D67: 4730/2017 | E67: Gestão e Fiscalização de Contratos - Serviços | F67: Jurisdicionados | G67: Treinamento de Jurisdicionados | H67: 27 a 31/03/2017 | I67: 42821 | J67: 42825 | K67: Instrutoria Interna | L67: 6962.15 | P67: 43 | R67: =SUM(O67:Q67) -> 43 | S67: 20 | T67: Leonardo José Alves Leal Neri
A68: 2017-006 | B68: 2017 | C68: Realizado | D68: 3784/2017 | E68: Regime Próprio da Previdência | F68: Servidores do TCDF | G68: Desenvolvimento Individual e Promoção da Cultura Organizacional | H68: 27 a 31/03/2017 | I68: 42821 | J68: 42825 | K68: Instrutoria Interna | L68: 7241.74 | O68: 15 | R68: =SUM(O68:Q68) -> 15 | S68: 20 | T68: Michel Martins de Morais
A69: 2017-007 | B69: 2017 | C69: Realizado | D69: 997/2017 | E69: Formulação e Avaliação de Políticas Públicas com foco no Controle Externo | F69: Servidores do TCDF | G69: Áreas Temáticas de Fiscalização do Setor Público | H69: 03 a 07/04/2017 | I69: 42828 | J69: 42832 | K69: Instrutoria Externa | L69: 7950 | O69: 29 | R69: =SUM(O69:Q69) -> 29 | S69: 20 | T69: Pedro Luiz Costa Cavalcante
A70: 2017-008 | B70: 2017 | C70: Realizado | D70: 3164/2017 | E70: Gestão e Fiscalização de Contratos Adm. - M2 | F70: Jurisdicionados | G70: Treinamento de Jurisdicionados | H70: 24 a 28/04/2017 | I70: 42849 | J70: 42853 | K70: Instrutoria Interna | L70: 6962.15 | P70: 46 | R70: =SUM(O70:Q70) -> 46 | S70: 20 | T70: Roberto Dias Santiago
A71: 2017-009 | B71: 2017 | C71: Realizado | D71: 30532/2017 | E71: Instrutoria - Turma 3 | F71: Servidores do TCDF | G71: N/A | I71: 42860 | J71: 42860 | K71: Instrutoria Externa | L71: 27300 | O71: 14 | R71: =SUM(O71:Q71) -> 14 | S71: 26 | T71: Pedro Paulo Carbone; Sylvio Maestrelli
A72: 2017-010 | B72: 2017 | C72: Realizado | D72: 13946/2017 | E72: Sistema Channel - Turma 2 | F72: Servidores do TCDF | G72: N/A | I72: 42860 | J72: 42860 | K72: Instrutoria Externa | L72: 0 | O72: 12 | R72: =SUM(O72:Q72) -> 12 | S72: 8 | T72: Breno
A73: 2017-011 | B73: 2017 | C73: Realizado | D73: 8964/2017 | E73: Excel Avançado - II | F73: Servidores do TCDF | G73: Mineração e Análise de Dados | H73: 08 a 12/05/2017 | I73: 42863 | J73: 42867 | K73: Instrutoria Interna | L73: 7241.74 | O73: 18 | R73: =SUM(O73:Q73) -> 18 | S73: 20 | T73: Josdeyvi Magalhães Russi
A74: 2017-012 | B74: 2017 | C74: Realizado | D74: 2001/2017 | E74: Processo nos Tribunais de Contas: Acusação, Contraditório, Julgamento e Recursos | F74: Servidores do TCDF | G74: Metodologias de Auditoria e Fiscalização | H74: 15 a 19/05/2017 | I74: 42870 | J74: 42874 | K74: Instrutoria Externa | L74: 33600 | O74: 30 | R74: =SUM(O74:Q74) -> 30 | S74: 20 | T74: Odilon Cavallari de Oliveira
A75: 2017-013 | B75: 2017 | C75: Realizado | D75: 6120/2017 | E75: Capacitação para Conselheiros de Cultura | F75: Sociedade | G75: Treinamento de Jurisdicionados | H75: 22 a 26/05/2017 | I75: 42877 | J75: 42881 | K75: Instrutoria Interna | L75: 0 | Q75: 37 | R75: =SUM(O75:Q75) -> 37 | S75: 20 | T75: Carlos Augusto Pereira da Silva
A76: 2017-014 | B76: 2017 | C76: Realizado | D76: 11354/2017 | E76: Legislação de Pessoal no Setor Público, com enfoque na LC 840/2011 | F76: Jurisdicionados | G76: Treinamento de Jurisdicionados | H76: 22 a 26/05/2017 | I76: 42877 | J76: 42881 | K76: Instrutoria Interna | L76: 6962.15 | P76: 47 | R76: =SUM(O76:Q76) -> 47 | S76: 20 | T76: Sebastião Cal de Miranda
A77: 2017-015 | B77: 2017 | C77: Realizado | D77: 11460/2017 | E77: Tomada de Contas Especial | F77: Servidores do TCDF | G77: Metodologias de Auditoria e Fiscalização | H77: 25 e 26/05/2017 | I77: 42880 | J77: 42881 | K77: Instrutoria Externa | L77: 8000 | O77: 30 | R77: =SUM(O77:Q77) -> 30 | S77: 16 | T77: Guilherme Henrique De La Rocque Almeida
A78: 2017-016 | B78: 2017 | C78: Realizado | D78: 4675/2017 | E78: Oratória - Turma 1 | F78: Servidores do TCDF | G78: Desenvolvimento Individual e Promoção da Cultura Organizacional | H78: 25 a 26/05/2017 | I78: 42880 | J78: 42881 | K78: Instrutoria Externa | L78: 7880 | O78: 19 | R78: =SUM(O78:Q78) -> 19 | S78: 20 | T78: Paula Cobucci
A79: 2017-017 | B79: 2017 | C79: Realizado | D79: 14086/2017 | E79: Contratação de Soluções de Tecnologia da Informação e Comunicação - TIC - T.1 | F79: Jurisdicionados | G79: Treinamento de Jurisdicionados | H79: 26 a 29/05/2017 | I79: 42881 | J79: 42884 | K79: Instrutoria Interna | L79: 5569.72 | P79: 37 | R79: =SUM(O79:Q79) -> 37 | S79: 16 | T79: ADINOR BEDRITICHUK JUNIOR; EVERTON PEIXOTO CORREIA DE ASSUMPCAO; FLAVIO JOSE FONSECA DE SOUZA
A80: 2017-018 | B80: 2017 | C80: Realizado | D80: 4675/2017 | E80: Oratória - Turma 2 | F80: Servidores do TCDF | G80: Desenvolvimento Individual e Promoção da Cultura Organizacional | H80: 05 a 09/06/2017 | I80: 42891 | J80: 42895 | K80: Instrutoria Externa | L80: 7880 | O80: 19 | R80: =SUM(O80:Q80) -> 19 | S80: 20 | T80: Paula Cobucci
A81: 2017-019 | B81: 2017 | C81: Realizado | D81: 7690/2017 | E81: PPP - Análise Econômica e Financeira no Excel | F81: Servidores do TCDF | G81: Mineração e Análise de Dados | H81: 19 a 23/06/2017 | I81: 42905 | J81: 42909 | K81: Instrutoria Interna | L81: 8547.4 | O81: 20 | R81: =SUM(O81:Q81) -> 20 | S81: 20 | T81: Orivam Ibiapina da Silva
A82: 2017-020 | B82: 2017 | C82: Realizado | D82: 13128/2017 | E82: Capacitação Especial para Promoção Funcional | F82: Servidores do TCDF | G82: Ambientação e Desenvolvimento na Carreira | H82: 23/06 a 16/08/2017 | I82: 42909 | J82: 42963 | K82: Instrutoria Interna | L82: 11567.86 | O82: 50 | R82: =SUM(O82:Q82) -> 50 | S82: 20 | T82: Agnaldo Moreira Marques; DELSO FERREIRA DA SILVA JUNIOR; EMILIO VINHADELLI PAPADOPOLIS; Henrique Mattei ;LUCIENE DE FATIMA CARVALHO TEODORO; Paulo Alves Honorato; ROMULO MIRANDA ALVIM; SERGIO ARAUJO DE AMORIM LOPES
A83: 2017-021 | B83: 2017 | C83: Realizado | D83: 4764/2017 | E83: Gestão de Processos | F83: Servidores do TCDF | G83: Administração, Estratégia e Inovação | H83: 26 a 30/06/2017 | I83: 42912 | J83: 42916 | K83: Instrutoria Externa | L83: 9780 | O83: 17 | R83: =SUM(O83:Q83) -> 17 | S83: 20 | T83: Annibal
A84: 2017-022 | B84: 2017 | C84: Realizado | D84: 12741/2017 | E84: Planilha de Terceirização de Mão de Obra - T.1 | F84: Jurisdicionados | G84: Treinamento de Jurisdicionados | H84: 26 a 30/06/2017 | I84: 42912 | J84: 42916 | K84: Instrutoria Interna | L84: 6962.15 | P84: 25 | R84: =SUM(O84:Q84) -> 25 | S84: 20 | T84: Leonardo José Alves Leal Neri
A85: 2017-023 | B85: 2017 | C85: Realizado | D85: 14060/2017 | E85: Capacitação para Conselheiros de Saúde | F85: Sociedade | G85: Treinamento de Jurisdicionados | H85: 03 a 07/07/2017 | I85: 42919 | J85: 42923 | K85: Instrutoria Interna | L85: 7231.26 | Q85: 49 | R85: =SUM(O85:Q85) -> 49 | S85: 20 | T85: Romildo Araújo da Silva; Tarsila Firmino Ely
A86: 2017-024 | B86: 2017 | C86: Realizado | D86: 20884/2017 | E86: Planilha de Terceirização de Mão de Obra - T.2 | F86: Jurisdicionados | G86: Treinamento de Jurisdicionados | H86: 24 a 28/07/2017 | I86: 42940 | J86: 42944 | K86: Instrutoria Interna | L86: 6008.6 | P86: 34 | R86: =SUM(O86:Q86) -> 34 | S86: 20 | T86: Leonardo José Alves Leal Neri
A87: 2017-025 | B87: 2017 | C87: Realizado | D87: 13098/2017 | E87: Excel Avançado - III | F87: Servidores do TCDF | G87: Mineração e Análise de Dados | H87: 21 a 25/08/2017 | I87: 42968 | J87: 42972 | K87: Instrutoria Interna | L87: 7603.8 | O87: 19 | R87: =SUM(O87:Q87) -> 19 | S87: 20 | T87: Josdeyvi Magalhães Russi
A88: 2017-026 | B88: 2017 | C88: Realizado | D88: 3199/2017 | E88: XXIII SEMAT | F88: Jurisdicionados | G88: Treinamento de Jurisdicionados | H88: 29 e 30/08/2017 | I88: 42976 | J88: 42977 | K88: Instrutoria Externa | L88: 40881.51 | O88: 100 | P88: 212 | Q88: 0 | R88: =SUM(O88:Q88) -> 312 | S88: 8 | T88: Roberto Ellery; Marcos Mendes; Maria Lúcia Fattorelli; Fábio Henrique Granja e Barros; Adler Anaximandro de Cruz e Alves; Daniel Soares Godoi Gomes de Oliveira; Samy Dana
A89: 2017-027 | B89: 2017 | C89: Realizado | D89: 24014/2017 | E89: Contratação Direta - Dispensa e Inexigibilidade de Licitação sob o enfoque da Lei n° 8666/1993 | F89: Jurisdicionados | G89: Treinamento de Jurisdicionados | H89: 11 a 15/09/2017 | I89: 42989 | J89: 42993 | K89: Instrutoria Interna | L89: 7452.02 | P89: 57 | R89: =SUM(O89:Q89) -> 57 | S89: 20 | T89: Roberto Dias Santiago
A90: 2017-028 | B90: 2017 | C90: Realizado | D90: 26440/2017 | E90: Lei das Estatais | F90: Jurisdicionados | G90: Treinamento de Jurisdicionados | H90: 25 a 29/09/2017 | I90: 43003 | J90: 43007 | K90: Instrutoria Interna | L90: 7510.44 | P90: 50 | R90: =SUM(O90:Q90) -> 50 | S90: 20 | T90: Roberto Dias Santiago
A91: 2017-029 | B91: 2017 | C91: Realizado | D91: 25185/2017 | E91: Impactos do Novo Sicro no Orçamento de Obras Rodoviárias | F91: Servidores do TCDF | G91: Áreas Temáticas de Fiscalização do Setor Público | H91: 17 a 18/10/2017 | I91: 43025 | J91: 43026 | K91: Instrutoria Externa | L91: 19780 | O91: 18 | R91: =SUM(O91:Q91) -> 18 | S91: 20 | T91: Elci Pessoa Júnior
A92: 2017-030 | B92: 2017 | C92: Realizado | D92: 29563/2017 | E92: Boas Práticas para uma Atuação Eficiente dos Executores de Contratos Administrativos | F92: Servidores do TCDF | G92: Administração, Estratégia e Inovação | H92: 23 a 27/10/2017 | I92: 43031 | J92: 43035 | K92: Instrutoria Interna | L92: 7452.02 | O92: 18 | R92: =SUM(O92:Q92) -> 18 | S92: 20 | T92: CLEUSA MARTINS PITANGA;PAOLA KARINA DE BARRON SALES
A93: 2017-031 | B93: 2017 | C93: Realizado | D93: 17964/2017 | E93: Regularidade nos Processo de Aquisição / Manutenção de Equipamentos médico-hospitalares – Termos de Referência | F93: Jurisdicionados | G93: Treinamento de Jurisdicionados | H93: 23 a 27/10/2017 | I93: 43031 | J93: 43035 | K93: Híbrida | L93: 10272.4 | P93: 40 | R93: =SUM(O93:Q93) -> 40 | S93: 20 | T93: Tarsila Firmino Ely; Luiz Eduardo Costa
A94: 2017-032 | B94: 2017 | C94: Realizado | D94: 31223/2017 | E94: Contratação de Soluções de Tecnologia da Informação e Comunicação - TIC - T.2 | F94: Jurisdicionados | G94: Treinamento de Jurisdicionados | H94: 06 a 09/11/2017 | I94: 43045 | J94: 43048 | K94: Instrutoria Interna | L94: 5961.61 | P94: 37 | R94: =SUM(O94:Q94) -> 37 | S94: 16 | T94: Adinor Bedritichuk Junior; Everton Peixoto Correia de Assumpção; Flávio José Fonseca de Souza
A95: 2018-001 | B95: 2018 | C95: Realizado | D95: 5529/2018 | E95: Capacitação para Conselheiros de Saúde | F95: Sociedade | G95: Treinamento de Jurisdicionados | H95: 20 e 21/03/2018 | I95: 43179 | J95: 43180 | K95: Instrutoria Interna | L95: 5647.92 | Q95: 96 | R95: =SUM(O95:Q95) -> 96 | S95: 20 | T95: Tarsila Firmino Ely
A96: 2018-002 | B96: 2018 | C96: Realizado | D96: 13475/2018 | E96: SAS aplicado ao Controle Externo (Turma 2) | F96: Servidores do TCDF | G96: Mineração e Análise de Dados | H96: 02 a 06/04/2018 | I96: 43192 | J96: 43196 | K96: Instrutoria Interna | L96: 13018.48 | O96: 19 | R96: =SUM(O96:Q96) -> 19 | S96: 20 | T96: Rômulo Miranda Alvim
A97: 2018-003 | B97: 2018 | C97: Realizado | D97: 6835/2018 | E97: Gestão e Fiscalização de Contratos Adm. - M1, Turma 1 | F97: Jurisdicionados | G97: Treinamento de Jurisdicionados | H97: 09 a 13/04/2018 | I97: 43199 | J97: 43203 | K97: Instrutoria Interna | L97: 7310.2 | P97: 65 | R97: =SUM(O97:Q97) -> 65 | S97: 20 | T97: Roberto Dias Santiago
A98: 2018-004 | B98: 2018 | C98: Realizado | D98: 25059/2016 | E98: Oficina de SAS | F98: Servidores do TCDF | G98: N/A | I98: 43225 | J98: 43225 | K98: Instrutoria Externa | L98: 0 | O98: 19 | R98: =SUM(O98:Q98) -> 19 | S98: 8 | T98: Rômulo Miranda Alvim
A99: 2018-005 | B99: 2018 | C99: Realizado | D99: 6797/2018 | E99: Oratória e Técnicas de Apresentação Corporativa (Turma 1) | F99: Servidores do TCDF | G99: Desenvolvimento Individual e Promoção da Cultura Organizacional | H99: 07, 08, 09 e 11/05/2018 | I99: 43227 | J99: 43231 | K99: Instrutoria Externa | L99: 7690 | O99: 19 | R99: =SUM(O99:Q99) -> 19 | S99: 16 | T99: Paula Cobucci
A100: 2018-006 | B100: 2018 | C100: Realizado | D100: 8374/2018 | E100: SAS aplicado ao Controle Externo (Turma 1) | F100: Servidores do TCDF | G100: Mineração e Análise de Dados | H100: 14 a 18/05/2018 | I100: 43234 | J100: 43238 | K100: Instrutoria Interna | L100: 7510.44 | O100: 20 | R100: =SUM(O100:Q100) -> 20 | S100: 20 | T100: Rômulo Miranda Alvim
...

Sheet GECC 2026
A1: Ano | B1: ID Ação | C1: Status | D1: Curso | E1: Carga Horária | F1: Instrutor | G1: Qtd Instrutores | H1: GECC Aula (h) | I1: GECC Material (h) | J1: Total GECC (h) | L1: Ano Filtro: | M1: 2026 | U1: Override Aula (h) | V1: Override Material (h)
A2: {=_xlfn.LET(_xlpm.totalRows,MAX(S4:S200),_xlpm.seq,_xlfn.SEQUENCE(_xlpm.totalRows),_xlpm.srcRow,_xlfn.MAP(_xlpm.seq,_xlfn.LAMBDA(_xlpm.s,MATCH(_xlpm.s-1,T4:T200,1))),_xlpm.instrIdx,_xlfn.MAP(_xlpm.seq,_xlpm.srcRow,_xlfn.LAMBDA(_xlpm.s,_xlpm.sr,_xlpm.s-INDEX(T4:T200,_xlpm.sr))),_xlpm.ano,_xlfn.MAP(_xlpm.srcRow,_xlfn.LAMBDA(_xlpm.sr,INDEX(L4:L200,_xlpm.sr))),_xlpm.id,_xlfn.MAP(_xlpm.srcRow,_xlfn.LAMBDA(_xlpm.sr,INDEX(M4:M200,_xlpm.sr))),_xlpm.status,_xlfn.MAP(_xlpm.srcRow,_xlfn.LAMBDA(_xlpm.sr,INDEX(N4:N200,_xlpm.sr))),_xlpm.curso,_xlfn.MAP(_xlpm.srcRow,_xlfn.LAMBDA(_xlpm.sr,INDEX(O4:O200,_xlpm.sr))),_xlpm.ch,_xlfn.MAP(_xlpm.srcRow,_xlfn.LAMBDA(_xlpm.sr,INDEX(P4:P200,_xlpm.sr)+0)),_xlpm.instrStr,_xlfn.MAP(_xlpm.srcRow,_xlfn.LAMBDA(_xlpm.sr,INDEX(Q4:Q200,_xlpm.sr))),_xlpm.nInstr,_xlfn.MAP(_xlpm.srcRow,_xlfn.LAMBDA(_xlpm.sr,INDEX(R4:R200,_xlpm.sr)+0)),_xlpm.instrName,_xlfn.MAP(_xlpm.instrStr,_xlpm.instrIdx,_xlfn.LAMBDA(_xlpm.s,_xlpm.idx,TRIM(INDEX(_xlfn.TEXTSPLIT(_xlpm.s,"; "),,_xlpm.idx)))),_xlpm.ovAula,_xlfn.MAP(_xlpm.seq,_xlfn.LAMBDA(_xlpm.s,INDEX(U2:U200,_xlpm.s))),_xlpm.ovMat,_xlfn.MAP(_xlpm.seq,_xlfn.LAMBDA(_xlpm.s,INDEX(V2:V200,_xlpm.s))),_xlpm.geccAula,_xlfn.MAP(_xlpm.ovAula,_xlpm.ch,_xlfn.LAMBDA(_xlpm.ov,_xlpm.c,IF(_xlpm.ov<>"",_xlpm.ov+0,_xlpm.c))),_xlpm.geccMat,_xlfn.MAP(_xlpm.ovMat,_xlpm.ch,_xlpm.nInstr,_xlfn.LAMBDA(_xlpm.ov,_xlpm.c,_xlpm.n,IF(_xlpm.ov<>"",_xlpm.ov+0,_xlpm.c*0.3/_xlpm.n))),_xlpm.geccTotal,_xlpm.geccAula+_xlpm.geccMat,_xlfn.HSTACK(_xlpm.ano,_xlpm.id,_xlpm.status,_xlpm.curso,_xlpm.ch,_xlpm.instrName,_xlpm.nInstr,_xlpm.geccAula,_xlpm.geccMat,_xlpm.geccTotal))} -> 2026 | B2: 2026-001 | C2: Realizado | D2: Contratação de TIC | E2: 8 | F2: Flávio José Fonseca de Souza | G2: 1 | H2: 8 | I2: 2.4 | J2: 10.4
A3: 2026 | B3: 2026-002 | C3: Realizado | D3: Tcendo o Futuro - Edição Especial Filhos | E3: 4 | F3: Cinthia Thais de Carvalho Luz Thomazi | G3: 5 | H3: 4 | I3: 0.24 | J3: 4.24 | L3: fAno | M3: fID | N3: fStatus | O3: fCurso | P3: fCH | Q3: fInstr | R3: fNInstr | S3: fCumSum | T3: preCum
A4: 2026 | B4: 2026-002 | C4: Realizado | D4: Tcendo o Futuro - Edição Especial Filhos | E4: 4 | F4: Adriana Cuoco Portugal | G4: 5 | H4: 4 | I4: 0.24 | J4: 4.24 | L4: {=_xlfn.LET(_xlpm.src,'Ações InCompany'!A2:T1000,_xlpm.sAno,INDEX(_xlpm.src,,2),_xlpm.sMod,INDEX(_xlpm.src,,11),_xlfn._xlws.FILTER(_xlfn.HSTACK(INDEX(_xlpm.src,,2),INDEX(_xlpm.src,,1),INDEX(_xlpm.src,,3),INDEX(_xlpm.src,,5),INDEX(_xlpm.src,,19),INDEX(_xlpm.src,,20)),(_xlpm.sAno=M1)*(_xlpm.sMod="Instrutoria Interna"),""))} -> 2026 | M4: 2026-001 | N4: Realizado | O4: Contratação de TIC | P4: 8 | Q4: Flávio José Fonseca de Souza | R4: {=IF(L4:L200="","",IF(ISERROR(FIND("; ",Q4:Q200)),1,(LEN(Q4:Q200)-LEN(SUBSTITUTE(Q4:Q200,"; ","")))/2+1))} -> 1 | S4: {=IF(R4:R200="","",_xlfn.SCAN(0,R4:R200,_xlfn.LAMBDA(_xlpm.a,_xlpm.b,IF(_xlpm.b="","",_xlpm.a+_xlpm.b))))} -> 1 | T4: {=_xlfn.VSTACK(0,_xlfn._xlws.FILTER(S4:S200,S4:S200<>""))} -> 0
A5: 2026 | B5: 2026-002 | C5: Realizado | D5: Tcendo o Futuro - Edição Especial Filhos | E5: 4 | F5: Fernanda Viana de Souza | G5: 5 | H5: 4 | I5: 0.24 | J5: 4.24 | L5: 2026 | M5: 2026-002 | N5: Realizado | O5: Tcendo o Futuro - Edição Especial Filhos | P5: 4 | Q5: Cinthia Thais de Carvalho Luz Thomazi; Adriana Cuoco Portugal; Fernanda Viana de Souza; Denise Duarte Guirra Kuhlmann; Priscila Nolasco | R5: 5 | S5: 6 | T5: 1
A6: 2026 | B6: 2026-002 | C6: Realizado | D6: Tcendo o Futuro - Edição Especial Filhos | E6: 4 | F6: Denise Duarte Guirra Kuhlmann | G6: 5 | H6: 4 | I6: 0.24 | J6: 4.24 | L6: 2026 | M6: 2026-004 | N6: Realizado | O6: Gestão e Fiscalização de Contratos de Equipamentos Médico Hospitalares e Serviços de Manutenção | P6: 12 | Q6: Tarsila Firmino Ely; Luciana Alvim | R6: 2 | S6: 8 | T6: 6
A7: 2026 | B7: 2026-002 | C7: Realizado | D7: Tcendo o Futuro - Edição Especial Filhos | E7: 4 | F7: Priscila Nolasco | G7: 5 | H7: 4 | I7: 0.24 | J7: 4.24 | L7: 2026 | M7: 2026-005 | N7: Realizado | O7: FIT1: Treinamento e Desenvolvimento (T&D) | P7: 16 | Q7: Paulo José Góes Daltro | R7: 1 | S7: 9 | T7: 8
A8: 2026 | B8: 2026-004 | C8: Realizado | D8: Gestão e Fiscalização de Contratos de Equipamentos Médico Hospitalares e Serviços de Manutenção | E8: 12 | F8: Tarsila Firmino Ely | G8: 2 | H8: 12 | I8: 1.8 | J8: 13.8 | L8: 2026 | M8: 2026-006 | N8: Realizado | O8: Curso para gestores e fiscais de contratos de serviços assistenciais complementares – SES/DF | P8: 12 | Q8: Adriana Magalhães; Luciana Alvim | R8: 2 | S8: 11 | T8: 9
A9: 2026 | B9: 2026-004 | C9: Realizado | D9: Gestão e Fiscalização de Contratos de Equipamentos Médico Hospitalares e Serviços de Manutenção | E9: 12 | F9: Luciana Alvim | G9: 2 | H9: 12 | I9: 1.8 | J9: 13.8 | L9: 2026 | M9: 2026-007 | N9: Realizado | O9: Planilhas de Terceirização de Mão de Obra, de acordo com a Lei nº 14.133/2021 - T1 | P9: 20 | Q9: Leonardo José Alves Leal Neri | R9: 1 | S9: 12 | T9: 11
A10: 2026 | B10: 2026-005 | C10: Realizado | D10: FIT1: Treinamento e Desenvolvimento (T&D) | E10: 16 | F10: Paulo José Góes Daltro | G10: 1 | H10: 0 | I10: 0 | J10: 0 | L10: 2026 | M10: 2026-008 | N10: Realizado | O10: Curso de Promoção Funcional 2026/2027 | P10: 20 | Q10: Rômulo Miranda Alvim; Cinthia Thais de Carvalho Luz Thomazi | R10: 2 | S10: 14 | T10: 12 | U10: 0 | V10: 0
A11: 2026 | B11: 2026-006 | C11: Realizado | D11: Curso para gestores e fiscais de contratos de serviços assistenciais complementares – SES/DF | E11: 12 | F11: Adriana Magalhães | G11: 2 | H11: 12 | I11: 1.8 | J11: 13.8 | L11: 2026 | M11: 2026-009 | N11: Realizado | O11: Introdução à Engenharia de Prompt - t1 | P11: 8 | Q11: Arthur Wú; Gustavo Takahashi | R11: 2 | S11: 16 | T11: 14
A12: 2026 | B12: 2026-006 | C12: Realizado | D12: Curso para gestores e fiscais de contratos de serviços assistenciais complementares – SES/DF | E12: 12 | F12: Luciana Alvim | G12: 2 | H12: 12 | I12: 1.8 | J12: 13.8 | L12: 2026 | M12: 2026-010 | N12: Realizado | O12: Planilhas de Terceirização de Mão de Obra, de acordo com a Lei nº 14.133/2021 - T2 | P12: 20 | Q12: Leonardo José Alves Leal Neri | R12: 1 | S12: 17 | T12: 16
A13: 2026 | B13: 2026-007 | C13: Realizado | D13: Planilhas de Terceirização de Mão de Obra, de acordo com a Lei nº 14.133/2021 - T1 | E13: 20 | F13: Leonardo José Alves Leal Neri | G13: 1 | H13: 20 | I13: 6 | J13: 26 | L13: 2026 | M13: 2026-013 | N13: A realizar | O13: Introdução à Engenharia de Prompt - t2 | P13: 8 | Q13: Arthur Wú; Gustavo Takahashi | R13: 2 | S13: 19 | T13: 17
A14: 2026 | B14: 2026-008 | C14: Realizado | D14: Curso de Promoção Funcional 2026/2027 | E14: 20 | F14: Rômulo Miranda Alvim | G14: 2 | H14: 20 | I14: 3 | J14: 23 | L14: 2026 | M14: 2026-014 | N14: A realizar | O14: Mostra Fotográfica “Meu Olhar sobre Brasília” | P14: 0 | Q14: Servidores, colaboradores e estagiários do TCDF | R14: 1 | S14: 20 | T14: 19
A15: 2026 | B15: 2026-008 | C15: Realizado | D15: Curso de Promoção Funcional 2026/2027 | E15: 20 | F15: Cinthia Thais de Carvalho Luz Thomazi | G15: 2 | H15: 20 | I15: 3 | J15: 23 | L15: 2026 | M15: 2026-015 | N15: A realizar | O15: Tcendo o Futuro | P15: 4 | Q15: Cinthia Thais de Carvalho Luz Thomazi; Adriana Cuoco Portugal; Fernanda Viana de Souza; Denise Duarte Guirra Kuhlmann; Priscila Nolasco | R15: 5 | S15: 25 | T15: 20
A16: 2026 | B16: 2026-009 | C16: Realizado | D16: Introdução à Engenharia de Prompt - t1 | E16: 8 | F16: Arthur Wú | G16: 2 | H16: 8 | I16: 1.2 | J16: 9.2 | L16: 2026 | M16: 2026-016 | N16: A realizar | O16: FIT1: Treinamento e Desenvolvimento (T&D) - T2 | P16: 16 | Q16: Paulo José Góes Daltro | R16: 1 | S16: 26 | T16: 25
A17: 2026 | B17: 2026-009 | C17: Realizado | D17: Introdução à Engenharia de Prompt - t1 | E17: 8 | F17: Gustavo Takahashi | G17: 2 | H17: 8 | I17: 1.2 | J17: 9.2 | L17: 2026 | M17: 2026-017 | N17: A realizar | O17: Fiscalizações Baseadas em Risco | P17: 20 | Q17: Larissa Vieira; Reinaldo Alencar; Rogério Ribeiro | R17: 3 | S17: 29 | T17: 26
A18: 2026 | B18: 2026-010 | C18: Realizado | D18: Planilhas de Terceirização de Mão de Obra, de acordo com a Lei nº 14.133/2021 - T2 | E18: 20 | F18: Leonardo José Alves Leal Neri | G18: 1 | H18: 20 | I18: 6 | J18: 26 | L18: 2026 | M18: 2026-018 | N18: A realizar | O18: Tcendo o Futuro | P18: 4 | Q18: Cinthia Thais de Carvalho Luz Thomazi; Adriana Cuoco Portugal; Fernanda Viana de Souza; Denise Duarte Guirra Kuhlmann; Priscila Nolasco | R18: 5 | S18: 34 | T18: 29
A19: 2026 | B19: 2026-013 | C19: A realizar | D19: Introdução à Engenharia de Prompt - t2 | E19: 8 | F19: Arthur Wú | G19: 2 | H19: 8 | I19: 1.2 | J19: 9.2 | L19: 2026 | M19: 2026-019 | N19: A realizar | O19: FIT1: Treinamento e Desenvolvimento (T&D) - T3 | P19: 16 | Q19: Paulo José Góes Daltro | R19: 1 | S19: 35 | T19: 34
A20: 2026 | B20: 2026-013 | C20: A realizar | D20: Introdução à Engenharia de Prompt - t2 | E20: 8 | F20: Gustavo Takahashi | G20: 2 | H20: 8 | I20: 1.2 | J20: 9.2 | T20: 35
A21: 2026 | B21: 2026-014 | C21: A realizar | D21: Mostra Fotográfica “Meu Olhar sobre Brasília” | E21: 0 | F21: Servidores, colaboradores e estagiários do TCDF | G21: 1 | H21: 0 | I21: 0 | J21: 0
A22: 2026 | B22: 2026-015 | C22: A realizar | D22: Tcendo o Futuro | E22: 4 | F22: Cinthia Thais de Carvalho Luz Thomazi | G22: 5 | H22: 4 | I22: 0.24 | J22: 4.24
A23: 2026 | B23: 2026-015 | C23: A realizar | D23: Tcendo o Futuro | E23: 4 | F23: Adriana Cuoco Portugal | G23: 5 | H23: 4 | I23: 0.24 | J23: 4.24
A24: 2026 | B24: 2026-015 | C24: A realizar | D24: Tcendo o Futuro | E24: 4 | F24: Fernanda Viana de Souza | G24: 5 | H24: 4 | I24: 0.24 | J24: 4.24
A25: 2026 | B25: 2026-015 | C25: A realizar | D25: Tcendo o Futuro | E25: 4 | F25: Denise Duarte Guirra Kuhlmann | G25: 5 | H25: 4 | I25: 0.24 | J25: 4.24
A26: 2026 | B26: 2026-015 | C26: A realizar | D26: Tcendo o Futuro | E26: 4 | F26: Priscila Nolasco | G26: 5 | H26: 4 | I26: 0.24 | J26: 4.24
A27: 2026 | B27: 2026-016 | C27: A realizar | D27: FIT1: Treinamento e Desenvolvimento (T&D) - T2 | E27: 16 | F27: Paulo José Góes Daltro | G27: 1 | H27: 0 | I27: 0 | J27: 0 | U27: 0 | V27: 0
A28: 2026 | B28: 2026-017 | C28: A realizar | D28: Fiscalizações Baseadas em Risco | E28: 20 | F28: Larissa Vieira | G28: 3 | H28: 20 | I28: 2 | J28: 22
A29: 2026 | B29: 2026-017 | C29: A realizar | D29: Fiscalizações Baseadas em Risco | E29: 20 | F29: Reinaldo Alencar | G29: 3 | H29: 20 | I29: 2 | J29: 22
A30: 2026 | B30: 2026-017 | C30: A realizar | D30: Fiscalizações Baseadas em Risco | E30: 20 | F30: Rogério Ribeiro | G30: 3 | H30: 20 | I30: 2 | J30: 22
A31: 2026 | B31: 2026-018 | C31: A realizar | D31: Tcendo o Futuro | E31: 4 | F31: Cinthia Thais de Carvalho Luz Thomazi | G31: 5 | H31: 4 | I31: 0.24 | J31: 4.24
A32: 2026 | B32: 2026-018 | C32: A realizar | D32: Tcendo o Futuro | E32: 4 | F32: Adriana Cuoco Portugal | G32: 5 | H32: 4 | I32: 0.24 | J32: 4.24
A33: 2026 | B33: 2026-018 | C33: A realizar | D33: Tcendo o Futuro | E33: 4 | F33: Fernanda Viana de Souza | G33: 5 | H33: 4 | I33: 0.24 | J33: 4.24
A34: 2026 | B34: 2026-018 | C34: A realizar | D34: Tcendo o Futuro | E34: 4 | F34: Denise Duarte Guirra Kuhlmann | G34: 5 | H34: 4 | I34: 0.24 | J34: 4.24
A35: 2026 | B35: 2026-018 | C35: A realizar | D35: Tcendo o Futuro | E35: 4 | F35: Priscila Nolasco | G35: 5 | H35: 4 | I35: 0.24 | J35: 4.24
A36: 2026 | B36: 2026-019 | C36: A realizar | D36: FIT1: Treinamento e Desenvolvimento (T&D) - T3 | E36: 16 | F36: Paulo José Góes Daltro | G36: 1 | H36: 0 | I36: 0 | J36: 0 | U36: 0 | V36: 0

Sheet Ações 2026
H4: AÇÕES EDUCACIONAIS 2026 CEDUC
B7: Trimestre | C7: Processo | D7: Supervisão | E7: Nome da Ação Educacional | F7: Status | G7: Qual fase? | H7: Data do Curso | I7: C.H. | J7: Modalidade Instrutoria | K7: Instrutores | L7: Vagas | M7: Inscritos | N7: Responsável
B8: 1º | C8: 14319/25 | D8: SAED | E8: Contratação de TIC | F8: Realizado | G8: Finalizado | H8: 20 e 21 de janeiro | I8: 8 | J8: Instrutoria Interna | K8: Flávio José Fonseca | L8: 50 | M8: 55 | N8: Stéphanie
B9: 1º | C9: 16298/25 | D9: SIPEC | E9: TCendo o Futuro - Edição Filhos | F9: Realizado | G9: Finalizado | H9: 23 de janeiro | I9: 4 | J9: Instrutoria Interna | K9: Diversos | L9: 30 | M9: 25 | N9: Raphael
B10: 1º | C10: 4926/25 | D10: SAED | E10: Estruturação de Inovações Disruptivas no TCDF | F10: Realizado | G10: Finalizado | H10: 26 a 30 de janeiro, 2,3, 4 de fevereiro; 9 e 10 fevereiro | I10: 42 | J10: Instrutoria Externa | K10: Caio Castelliano | L10: 30 | M10: 23 | N10: Paula
B11: 1º | C11: 15827/25 | D11: SAED | E11: Gestão e Fiscalização de Contratos de Equipamentos Médico Hospitalares e Serviços de Manutenção | F11: Realizado | G11: Finalizado | H11: 25 a 27 de fevereiro | I11: 12 | J11: Instrutoria Interna | K11: Tarsila Firmino; Luciana Alvim | L11: 20 | M11: 44 | N11: Taissa
B12: 1º | C12: 529/26 | D12: SAED | E12: FIT1: Treinamento e Desenvolvimento (T&D) | F12: Realizado | G12: Finalizado | H12: 25 a 27 de fevereiro; 2 de março | I12: 16 | J12: Instrutoria Interna | K12: Paulo José Góes Daltro | L12: 20 | M12: 18 | N12: Paula
B13: 1º | C13: 15352/25 | D13: SAED | E13: Curso para gestores e fiscais de contratos de serviços assistenciais complementares – SES/DF - T1 | F13: Realizado | G13: Finalizado | H13: 4 a 6 de março | I13: 12 | J13: Instrutoria Interna | K13: Adriana Magalhães; Luciana Rocha de Melo | L13: 20 | M13: 20 | N13: Taissa
B14: 1º | C14: 10/26 | D14: SAED | E14: Planilhas de Terceirização de Mão de Obra, de acordo com a Lei nº 14.133/2021 - T1 | F14: Realizado | G14: Aguardando finalizar doc T2 | H14: 9 a 13 de março | I14: 20 | J14: Instrutoria Interna | K14: Leonardo Leal Neri | L14: 20 | M14: 19 | N14: Paula
B15: 1º | C15: 354/26 | D15: SAED | E15: Promoção Funcional | F15: Realizado | G15: Relatório GECC pgmto encaminhado | H15: 16, 17, 19, 20 de março | I15: 20 | J15: Instrutoria Interna | K15: Rômulo Miranda Alvim; Cinthia Thais de Carvalho Luz Thomazi | L15: 33 | M15: 33 | N15: Stéphanie
B16: 1º | C16: 15249/2025 | D16: SAED | E16: Engenharia de Prompt - T1 | F16: Realizado | G16: Relatório GECC pgmto encaminhado | H16: 17 a 19 de março | I16: 8 | J16: Instrutoria Interna | K16: Arthur WÚ | L16: 20 | M16: 20 | N16: Stéphanie
B17: 1º | C17: 10/26 | D17: SAED | E17: Planilhas de Terceirização de Mão de Obra, de acordo com a Lei nº 14.133/2021 - T2 | F17: Realizado | G17: Aguardando AR e Lista Presença | H17: 23 a 27 de março | I17: 20 | J17: Instrutoria Interna | K17: Leonardo Leal Neri | L17: 20 | M17: 19 | N17: Paula
B18: 1º | C18: 2111/26 | D18: SAED | E18: Dia da Ouvidoria | F18: Realizado | G18: Autorizado | H18: 24 de março | I18: 4 | J18: Instrutoria Externa | K18: Diversos | L18: 170 | M18: 140 | N18: Gilson
B19: 1º | C19: 49/26 | D19: SAED | E19: Maratona de Transparência Pública | F19: Em andamento | G19: Aguardando AR e Lista Presença | H19: 30 e 31 de março | I19: 14 | J19: Instrutoria Externa | K19: Diversos | M19: 180 | N19: Sibele
B20: 2º | C20: 1984/26 | D20: SAED | E20: Curso para gestores e fiscais de contratos de serviços assistenciais complementares – SES/DF - Turma 2 | F20: A realizar | G20: Autorizado pela Presidência | H20: 8 a 10 de abril | I20: 12 | J20: Instrutoria Interna | K20: Adriana Magalhães; Luciana Rocha de Melo | L20: 20 | N20: Taissa
B21: 2º | D21: SIPEC | E21: Café e Tartúlia | F21: A realizar | H21: 10 de abril | I21: 4 | J21: Instrutoria Interna | K21: Diversos | N21: Raphael
B22: 2º | C22: 3976/25 | D22: SAED | E22: Curso de Formação para Conselheiros de Cultura | F22: A realizar | G22: Em processo de contratação | H22: 13 a 16 de abril | I22: 16 | J22: Instrutoria Externa | K22: Christiane Montes Ramírez | L22: 50 | N22: Taissa
B23: 2º | C23: 15249/2025 | D23: SAED | E23: Engenharia de Prompt - T2 | F23: A realizar | G23: Autorizado pela Presidência | H23: 15 e 17 de abril | I23: 8 | J23: Instrutoria Interna | K23: Arthur WÚ; Gustavo Takahashi | L23: 20 | N23: Stéphanie
B24: 2º | C24: 2511/26 | D24: SIPEC | E24: Mostra Fotográfica “Meu Olhar sobre Brasília” | F24: A realizar | H24: 20 a 30 de abril | I24: - | K24: - | N24: Raphael
B25: 2º | C25: 1900/26 | D25: SIPEC | E25: TCendo o Futuro | F25: A realizar | H25: 23 e 24 de abril | I25: 4 | K25: Diversos | L25: 80 | N25: Raphael
B26: 2º | C26: 3103/26 | D26: SAED | E26: FIT1: Treinamento e Desenvolvimento (T&D) - T2 | F26: A realizar | G26: Em processo de autorização | H26: 27 a 30 de abril | J26: Instrutoria Interna | K26: Paulo José Góes Daltro | L26: 15 | N26: Paula
B27: 2º | C27: 3103/26 | D27: SAED | E27: FIT1: Treinamento e Desenvolvimento (T&D) - T3 | F27: A realizar | G27: Em processo de autorização | H27: 27 a 30 de abril | I27: 16 | J27: Instrutoria Interna | K27: Paulo José Góes Daltro | L27: 15 | N27: Paula
B28: 2º | D28: SAED | E28: Fiscalizações Baseadas em Risco | F28: A realizar | G28: Aguardando Solicitação | H28: 4, 5, 6, 11 e 12 de maio | I28: 20 | J28: Instrutoria Interna | K28: Rogério Ribeiro; Reinaldo Alencar; Larissa Vieira | L28: 20 | N28: Stéphanie
B29: 2º | C29: 1900/26 | D29: SIPEC | E29: TCendo o Futuro | F29: A realizar | H29: 8 de maio | I29: 4 | J29: Instrutoria Interna | K29: Diversos | L29: 80 | N29: Raphael
B30: 2º | C30: 2647/26 | D30: SAED | E30: Fórum Longevidade - Palestra Alexandre Kalache | F30: A realizar | H30: 21 e 22 de maio | I30: 1 | J30: Instrutoria Externa | K30: Alexandre Kalache | N30: Sibele
B31: 2º | C31: 2960/26 | D31: SAED | E31: Fórum Longevidade - Palestra Juliana | F31: A realizar | H31: 21 e 22 de maio | I31: 1 | J31: Instrutoria Externa | K31: Juliana Seild | N31: Stéphanie
B32: 2º | C32: 2820/26 | D32: SAED | E32: Fórum Longevidade - Escape Game | F32: A realizar | H32: 21 e 22 de maio | I32: 1 | J32: Instrutoria Externa | K32: Empresa Escape Game | N32: Paula
B33: 2º | C33: 3105/26 | D33: SAED | E33: Fórum Longevidade - Palestra Raquel | F33: A realizar | H33: 21 e 22 de maio | I33: 1 | J33: Instrutoria Externa | K33: Raquel Arigony | N33: Stéphanie
B34: 2º | C34: - | D34: SAED | E34: Políticas Públicas | F34: A realizar | G34: Elaborando Plano de Ensino | H34: 25 a 27 de maio; 1 a 3 de junho | I34: 20 | J34: Instrutoria Interna | K34: Rogério Ribeiro; Reinaldo Alencar | L34: 24 | N34: Stéphanie

Sheet Controle Arq.
G2: 11565/2024
G3: 13950/2023
G4: 784/2024
G5: 12891/2023
G6: 613/2024
G7: 6589/2024
G8: 6295/2024
G9: 920/2024
G10: 8683/2024
G11: 10049/2024
G12: 10118/2024
G13: 11946/2024 | I13: Paula
G14: 6564/2024
G15: 6321/2024
G16: 2928/2024
G17: 9914/2024
G18: 12138/2024
G19: 2524/2024 | M19: 00600-00006259/2022-18
G20: 5803/2024 | M20: 00600-00004891/2022-19
G21: 7023/2024 | M21: 3643/22
G22: 11896/2024 | M22: 3052/22
G23: 5036/2024 | M23: 3028/22
G24: 4375/2024 | M24: 2911/22
G25: 9044/2024 | M25: 2829/22
G26: 9074/2024 | M26: 2221/22
G27: 397/2024 | M27: 937/22
G28: 4734/2024 | M28: 12718/22
G29: 419/2024 | M29: 9809/21
G30: 1347/2024 | M30: 9715/21
... G41: 11097/2024 | M41: 3904/23
G42: 10889/2024 | I42: Pimenta | M42: 2178/23
G43: 10895/2024 | M43: 535/23
G44: 10896/2024 | M44: 402/23
G45: 10897/2024 | M45: 381/23
G46: 10898/2024 | M46: 14663/22
G47: 10901/2024 | M47: 13772/22
G48: 13257/2024 | M48: 13693/22
G49: 1125/2024 | M49: 11400/22
G50: 1401/2024 | M50: 11363/22
G51: 3829/2024 | M51: 9843/22
G52: 10477/2024 | M52: 9187/22
G53: 7736/2024 | M53: 8684/22
G54: 3810/2024 | M54: 8046/22
G55: 11954/2024 | M55: 13921/22
G56: 1461/2024
G57: 3839/2024
G58: 5757/2024
G59: 4979/2024
G60: 11703/2024
G61: 9305/2024
G62: 6654/2024
G65: 5386/2024 | H65: ste
G66: 394/2024 | H66: ste
G68: 1895/2024 | H68: RP
G70: 3873/2024 | H70: RP
G71: 2598/2024 | H71: ste
G72: 6994/2024 | H72: RP
G73: 6546/2024 | H73: RP
G74: 10410/2024 | H74: ste
G75: 10686/2024 | H75: ste
G76: 11840/2024 | H76: ste
G77: 10547/2024 | H77: ste
G78: 10874/2024 | H78: ste
... G89: 15811/2023 | H89: ste

Sheet PlanoCap2627
A1: ANO - VIGÊNCIA | B1: EIXO TEMÁTICO | C1: Programa | D1: Público-Alvo Preferencial | E1: Descrição
A2: 2026/2027 | B2: Controle Externo | C2: Metodologias de Auditoria e Fiscalização | D2: Membros e servidores que atuam no Controle Externo | E2: Destina-se a oferecer ações de aprendizagem de metodologias necessárias à realização de fiscalizações governamentais, alinhadas às Normas Brasileiras de Auditoria do Setor Público
A3: 2026/2027 | B3: Controle Externo | C3: Áreas Temáticas de Fiscalização do Setor Público | D3: Membros e servidores que atuam no Controle Externo | E3: Destina-se a oferecer ações de aprendizagem voltadas às áreas temáticas fiscalizadas, como saúde, pessoal, previdência, assistência social, obras e serviços de engenharia, tecnologia da informação e comunicação, licitações e contratos, parcerias público-privadas, concessões e desestatização, entre outras
A4: 2026/2027 | B4: Controle Externo | C4: Treinamento de Jurisdicionados | D4: Servidores Públicos dos órgãos jurisdicionados ao TCDF | E4: Destina-se a oferecer ações de aprendiza_x0002_gem para os gestores e servidores públicos dos órgãos jurisdicionados ao TCDF, a fim de promover a correta e eficiente aplicação dos recursos públicos
A5: 2026/2027 | B5: Controle Externo | C5: Treinamento em Saúde Pública | D5: Membros e servidores do TCDF, servidores públicos dos órgãos jurisdicionados ao TCDF da área da saúde e cidadãos interessados na temática de saúde pública | E5: Destina-se a oferecer ações de aprendiza_x0002_gem para os atores responsáveis pela saúde pública distrital e interessados na temática, com vistas à correta e eficiente aplicação dos recursos públicos e à melhoria dos resultados do setor
A6: 2026/2027 | B6: Controle Externo | C6: Formação de Controladores sociais e cidadãos | D6: Representantes de entidades de Controle social e Cidadãos | E6: Destina-se a oferecer ações de aprendizagem para os cidadãos, para fomentar o exercício do controle social.
A7: 2026/2027 | B7: Organizacional | C7: Inteligência Artificial e Análise de Dados | D7: Membros e servidores do TCDF | E7: Destina-se a oferecer ações de aprendizagem voltadas ao uso da inteligência artificial e à análise e mineração de dados, a fim de iden_x0002_tificar informações úteis à tomada de decisão em meio a grandes quantidades de dados.
A8: 2026/2027 | B8: Organizacional | C8: Administração, Estratégia e Inovação | D8: Membros e Servidores do TCDF | E8: Destina-se a oferecer ações de aprendizagem para auxiliar na gestão e apoio estratégico do TCDF, assim como promover a inovação na Casa. As ações buscam aprimorar processos como os de planejamento, gestão de pessoas, gestão da informação, gestão de projetos, gestão de processos, gestão administrativa, gestão contratual, relacionamento com o cliente, operacionalização de sistemas, entre outros
A9: 2026/2027 | B9: Organizacional | C9: Escola de Instrutores | D9: Corpo técnico e docente da Escola de Contas Públicas do TCDF | E9: Destina-se a oferecer ações de aprendizagem para o corpo técnico e docente da Escola de Contas Públicas do TCDF, a fim de aprimorar a qualidade instrucional e os resultados das ações de treinamento oferecidas internamente.
A10: 2026/2027 | B10: Transversal | C10: Desenvolvimento de Líderes | D10: Servidores que ocu_x0002_pam função gerencial e potenciais líderes a desenvolver | E10: Destina-se a oferecer ações de aprendizagem para os atuais dirigentes do TCDF, consideran_x0002_do as necessidades de cada nível gerencial (estratégico, tático e operacional), àqueles que assumem funções gerenciais e aos servido_x0002_res com potencial de atuação gerencial no Tribunal. As ações devem auxiliar os gestores no exercício da função gerencial, aprimoran_x0002_do competências relacionadas à gestão de desempenho, ao desenvolvimento da equipe, à gestão de equipes remotas e/ou híbridas, à orientação estratégica, ao feedback, entre outras
A11: 2026/2027 | B11: Transversal | C11: Desenvolvimento Individual e Promoção da Cultura Organizacional | D11: Servidores do TCDF | E11: Destina-se a oferecer ações de aprendizagem para auxiliar no desenvolvimento de competências funcionais dos servidores, tais quais orientação para resultado, ética e relacionamento interpessoal.
A12: 2026/2027 | B12: Transversal | C12: Ambientação e Desenvolvimento na Carreira | D12: Servidores do TCDF | E12: Destina-se a oferecer ações de aprendizagem para auxiliar na ambientação e promoção de servidores, promovendo a visão sistêmica da sua atuação no âmbito do TCDF

Sheet Dashboard GECC 2026
A1: Dashboard GECC 2026 - Horas por Instrutor
A2: Consulta de horas GECC por instrutor em 2026
A4: Instrutor | B4: GECC Aula (h) | C4: GECC Material (h) | D4: Total GECC (h) | E4: Qtd Ações
A5: Leonardo José Alves Leal Neri | B5: =SUMIFS('GECC 2026'!H$2:H$200,'GECC 2026'!F$2:F$200,$A5) -> 40 | C5: =SUMIFS('GECC 2026'!I$2:I$200,'GECC 2026'!F$2:F$200,$A5) -> 12 | D5: =SUMIFS('GECC 2026'!J$2:J$200,'GECC 2026'!F$2:F$200,$A5) -> 52 | E5: =COUNTIFS('GECC 2026'!F$2:F$200,$A5) -> 2
A6: Luciana Alvim | B6: =SUMIFS('GECC 2026'!H$2:H$200,'GECC 2026'!F$2:F$200,$A6) -> 24 | C6: =SUMIFS('GECC 2026'!I$2:I$200,'GECC 2026'!F$2:F$200,$A6) -> 3.6 | D6: =SUMIFS('GECC 2026'!J$2:J$200,'GECC 2026'!F$2:F$200,$A6) -> 27.6 | E6: =COUNTIFS('GECC 2026'!F$2:F$200,$A6) -> 2
A7: Cinthia Thais de Carvalho Luz Thomazi | B7: =SUMIFS('GECC 2026'!H$2:H$200,'GECC 2026'!F$2:F$200,$A7) -> 32 | C7: =SUMIFS('GECC 2026'!I$2:I$200,'GECC 2026'!F$2:F$200,$A7) -> 3.72 | D7: =SUMIFS('GECC 2026'!J$2:J$200,'GECC 2026'!F$2:F$200,$A7) -> 35.72 | E7: =COUNTIFS('GECC 2026'!F$2:F$200,$A7) -> 4
A8: Rômulo Miranda Alvim | B8: =SUMIFS('GECC 2026'!H$2:H$200,'GECC 2026'!F$2:F$200,$A8) -> 20 | C8: =SUMIFS('GECC 2026'!I$2:I$200,'GECC 2026'!F$2:F$200,$A8) -> 3 | D8: =SUMIFS('GECC 2026'!J$2:J$200,'GECC 2026'!F$2:F$200,$A8) -> 23 | E8: =COUNTIFS('GECC 2026'!F$2:F$200,$A8) -> 1
A9: Larissa Vieira | B9: =SUMIFS('GECC 2026'!H$2:H$200,'GECC 2026'!F$2:F$200,$A9) -> 20 | C9: =SUMIFS('GECC 2026'!I$2:I$200,'GECC 2026'!F$2:F$200,$A9) -> 2 | D9: =SUMIFS('GECC 2026'!J$2:J$200,'GECC 2026'!F$2:F$200,$A9) -> 22 | E9: =COUNTIFS('GECC 2026'!F$2:F$200,$A9) -> 1
A10: Reinaldo Alencar | B10: =SUMIFS('GECC 2026'!H$2:H$200,'GECC 2026'!F$2:F$200,$A10) -> 20 | C10: =SUMIFS('GECC 2026'!I$2:I$200,'GECC 2026'!F$2:F$200,$A10) -> 2 | D10: =SUMIFS('GECC 2026'!J$2:J$200,'GECC 2026'!F$2:F$200,$A10) -> 22 | E10: =COUNTIFS('GECC 2026'!F$2:F$200,$A10) -> 1
A11: Rogério Ribeiro | B11: =SUMIFS('GECC 2026'!H$2:H$200,'GECC 2026'!F$2:F$200,$A11) -> 20 | C11: =SUMIFS('GECC 2026'!I$2:I$200,'GECC 2026'!F$2:F$200,$A11) -> 2 | D11: =SUMIFS('GECC 2026'!J$2:J$200,'GECC 2026'!F$2:F$200,$A11) -> 22 | E11: =COUNTIFS('GECC 2026'!F$2:F$200,$A11) -> 1
A12: Paulo José Góes Daltro | B12: =SUMIFS('GECC 2026'!H$2:H$200,'GECC 2026'!F$2:F$200,$A12) -> 0 | C12: =SUMIFS('GECC 2026'!I$2:I$200,'GECC 2026'!F$2:F$200,$A12) -> 0 | D12: =SUMIFS('GECC 2026'!J$2:J$200,'GECC 2026'!F$2:F$200,$A12) -> 0 | E12: =COUNTIFS('GECC 2026'!F$2:F$200,$A12) -> 3
A13: Arthur Wú | B13: =SUMIFS('GECC 2026'!H$2:H$200,'GECC 2026'!F$2:F$200,$A13) -> 16 | C13: =SUMIFS('GECC 2026'!I$2:I$200,'GECC 2026'!F$2:F$200,$A13) -> 2.4 | D13: =SUMIFS('GECC 2026'!J$2:J$200,'GECC 2026'!F$2:F$200,$A13) -> 18.4 | E13: =COUNTIFS('GECC 2026'!F$2:F$200,$A13) -> 2
A14: Gustavo Takahashi | B14: =SUMIFS('GECC 2026'!H$2:H$200,'GECC 2026'!F$2:F$200,$A14) -> 16 | C14: =SUMIFS('GECC 2026'!I$2:I$200,'GECC 2026'!F$2:F$200,$A14) -> 2.4 | D14: =SUMIFS('GECC 2026'!J$2:J$200,'GECC 2026'!F$2:F$200,$A14) -> 18.4 | E14: =COUNTIFS('GECC 2026'!F$2:F$200,$A14) -> 2
A15: Adriana Magalhães | B15: =SUMIFS('GECC 2026'!H$2:H$200,'GECC 2026'!F$2:F$200,$A15) -> 12 | C15: =SUMIFS('GECC 2026'!I$2:I$200,'GECC 2026'!F$2:F$200,$A15) -> 1.8 | D15: =SUMIFS('GECC 2026'!J$2:J$200,'GECC 2026'!F$2:F$200,$A15) -> 13.8 | E15: =COUNTIFS('GECC 2026'!F$2:F$200,$A15) -> 1
A16: Tarsila Firmino Ely | B16: =SUMIFS('GECC 2026'!H$2:H$200,'GECC 2026'!F$2:F$200,$A16) -> 12 | C16: =SUMIFS('GECC 2026'!I$2:I$200,'GECC 2026'!F$2:F$200,$A16) -> 1.8 | D16: =SUMIFS('GECC 2026'!J$2:J$200,'GECC 2026'!F$2:F$200,$A16) -> 13.8 | E16: =COUNTIFS('GECC 2026'!F$2:F$200,$A16) -> 1
... A22: Servidores, colaboradores e estagiários do TCDF | B22: =SUMIFS('GECC 2026'!H$2:H$200,'GECC 2026'!F$2:F$200,$A22) -> 0 | C22: =SUMIFS('GECC 2026'!I$2:I$200,'GECC 2026'!F$2:F$200,$A22) -> 0 | D22: =SUMIFS('GECC 2026'!J$2:J$200,'GECC 2026'!F$2:F$200,$A22) -> 0 | E22: =COUNTIFS('GECC 2026'!F$2:F$200,$A22) -> 1
A24: TOTAL GERAL | B24: =SUM(B5:B22) -> 288 | C24: =SUM(C5:C22) -> 42 | D24: =SUM(D5:D22) -> 330 | E24: =SUM(E5:E22) -> 35

Sheet legado
A1: ID_TIPO | B1: Exerc. | C1: Previsão | D1: Status Evento | E1: Processo | F1: Temática | G1: DESTAQUE | H1: Descrição Dest. | I1: Público-Alvo | J1: Programa | K1: TIPO ESCON | L1: Data TXT | M1: Início | N1: Término | O1: Modalidade | P1: Valor Insc. | Q1: V. Coffee Break | R1: Nota Av. Reação | S1: %Av. Reação | T1: Qtd Vagas | U1: P. Servidores | V1: P. Jurisdicionados | W1: P. Sociedade | X1: Total Part. | Y1: C.H. | Z1: Mikhail | AA1: Instrutor | AB1: Objetivo Geral | AC1: Coluna1 | AD1: Coluna2
A2: InCompany | B2: 2014 | D2: Realizado | F2: CURSO DE ELABORAÇÃO DE PARECERES E RELATÓRIOS | I2: Controle Externo | J2: C.E - Programa de Auditoria e Fiscalização do Setor Público | L2: 17 a 21/03/2014 | M2: 41715 | N2: 41719 | O2: Instrutoria Externa | P2: 19500 | U2: 20 | X2: =SUM(U2:W2) -> 20 | Y2: 20
A3: InCompany | B3: 2014 | D3: Realizado | F3: ELABORAÇÃO DE PLANO DE AUDITORIA E MATRIZ DE PLANEJAMENTO | I3: Controle Externo | J3: C.E - Programa de Auditoria e Fiscalização do Setor Público | L3: 14 e 14/04/2014 | M3: 41743 | N3: 41744 | O3: Instrutoria Externa | P3: 28000 | U3: 16 | X3: =SUM(U3:W3) -> 16 | Y3: 16
A4: InCompany | B4: 2014 | D4: Realizado | F4: CURSO DE EXCEL AVANÇADO | I4: Áreas Administrativas | J4: A.C.E - Programa de Análise de Dados | L4: 02 a 09/06/2014 | M4: 41792 | N4: 41799 | O4: Instrutoria Interna | P4: 2991 | U4: 24 | X4: =SUM(U4:W4) -> 24 | Y4: 24
A5: InCompany | B5: 2014 | D5: Realizado | F5: REGIME DIFERENCIADO DE CONTRATAÇÕES PÚBLICAS - RDC | I5: Controle Externo | J5: C.E - Programa de Orçamento e Finanças Públicas | L5: 24 e 25/06/2014 | M5: 41814 | N5: 41815 | O5: Instrutoria Externa | P5: 41341.16 | U5: 16 | X5: =SUM(U5:W5) -> 16 | Y5: 16
A6: InCompany | B6: 2014 | D6: Realizado | F6: ENGENHARIA ECONÔMICA I E II - CAPACITAÇÃO EM PARCERIAS PÚBLICO PRIVADAS E CONCESSÕES DE | I6: Controle Externo | J6: C.E - Programa de Auditoria e Fiscalização do Setor Público | L6: 04 a 08/08/2014 | M6: 41855 | N6: 41859 | O6: Instrutoria Externa | P6: 54900 | U6: 40 | X6: =SUM(U6:W6) -> 40 | Y6: 40
A7: InCompany | B7: 2014 | D7: Realizado | F7: CURSO TÉCNICAS DE AUDITORIA OPERACIONAL | I7: Controle Externo | J7: C.E - Programa de Auditoria e Fiscalização do Setor Público | L7: 10/09/2014 | M7: 41892 | N7: 41892 | O7: Instrutoria Externa | P7: 15000 | U7: 30 | X7: =SUM(U7:W7) -> 30 | Y7: 30
A8: InCompany | B8: 2014 | D8: Realizado | F8: 05, 12, 19 e 26 de abril de 2024, de 14h às 18h. | I8: Controle Externo | J8: C.E - Programa de Auditoria e Fiscalização do Setor Público | L8: 31/10/2014 | M8: 41943 | N8: 41943 | O8: Instrutoria Externa | P8: 33260 | U8: 24 | X8: =SUM(U8:W8) -> 24 | Y8: 24
A9: InCompany | B9: 2014 | D9: Realizado | F9: PROCESSO DE CONTRATAÇÃO PÚBLICA | I9: Controle Externo | J9: C.E - Programa de Orçamento e Finanças Públicas | L9: 10 a 14/11/2014 | M9: 41953 | N9: 41957 | O9: Instrutoria Interna | P9: 4353.54 | V9: 37 | X9: =SUM(U9:W9) -> 37 | Y9: 8
A10: InCompany | B10: 2014 | D10: Realizado | F10: TERMO DE REFERÊNCIA DE SERVIÇOS CONTINUADOS COM DEDICAÇÃO EXCLUSIVA DE MÃO DE OBRA | I10: Controle Externo | J10: C.E - Programa de Auditoria e Fiscalização do Setor Público | L10: 24 a 28/11/2014 | M10: 41967 | N10: 41971 | O10: Instrutoria Interna | P10: 4353.54 | V10: 58 | X10: =SUM(U10:W10) -> 58 | Y10: 20
A11: InCompany | B11: 2015 | D11: Realizado | E11: 1683/2015 | F11: ELABORAÇÃO DE PARECERES E RELATÓRIOS | I11: Controle Externo | J11: C.E - Programa de Auditoria e Fiscalização do Setor Público | L11: 23 a 27/03/2015 | M11: 42086 | N11: 42090 | O11: Instrutoria Externa | P11: 23500 | U11: 25 | X11: =SUM(U11:W11) -> 25 | Y11: 20 | AA11: José Paulo Moreira de Oliveira
A12: InCompany | B12: 2015 | D12: Realizado | E12: 3716/2015 | F12: O PROCESSO DE CONTRATAÇÃO PÚBLICA | I12: Jurisdicionados | J12: C.E - Programa de Orçamento e Finanças Públicas | L12: 06 a 10/04/2015 | M12: 42100 | N12: 42104 | O12: Instrutoria Interna | P12: 4992.74 | V12: 85 | X12: =SUM(U12:W12) -> 85 | Y12: 20 | AA12: Amauri Alves Nery
A13: InCompany | B13: 2015 | D13: Realizado | E13: 2515/2015 | F13: TERMO DE REFERÊNCIA DE SERVIÇOS CONTINUADOS COM DEDICAÇÃO EXCLUSIVA DE MÃO DE OBRA | I13: Jurisdicionados | J13: C.E - Programa de Capacitação para Jurisdicionados Controladores sociais e Cidadãos | L13: 13 a 17/04/2015 | M13: 42107 | N13: 42111 | O13: Instrutoria Interna | P13: 4447.52 | V13: 89 | X13: =SUM(U13:W13) -> 89 | Y13: 20 | AA13: LEONARDO JOSE ALVES LEAL NERI
A14: InCompany | B14: 2015 | D14: Realizado | E14: 7690/2015 | F14: FISCALIZAÇÃO DE CONTRATOS ADMINISTRATIVOS | I14: Áreas Administrativas | J14: A.C.E - Programa de Gestão e Estratégia | L14: 16, 17, 22, 23 e 24/04/2020 | M14: 42110 | N14: 42118 | O14: Instrutoria Interna | P14: 4447.52 | U14: 37 | X14: =SUM(U14:W14) -> 37 | Y14: 30 | AA14: LEONARDO JOSE ALVES LEAL NERI
A15: InCompany | B15: 2015 | D15: Realizado | F15: PALESTRA CONSELHOS REGIONAIS DE SAÚDE | I15: Sociedade | J15: N/A | M15: 42122 | N15: 42122 | O15: Instrutoria Interna | P15: 0 | X15: =SUM(U15:W15) -> 0 | Y15: 5
A16: InCompany | B16: 2015 | D16: Realizado | E16: 3481/2015 | F16: PROCESSO NOS TRIBUNAIS DE CONTAS | I16: Controle Externo | J16: C.E - Programa de Auditoria e Fiscalização do Setor Público | L16: 26 a 29/05/2015 | M16: 42129 | N16: 42132 | O16: Instrutoria Externa | P16: 35500 | U16: 30 | X16: =SUM(U16:W16) -> 30 | Y16: 16 | AA16: Odilon Cavallari de Oliveira
A17: InCompany | B17: 2015 | D17: Realizado | E17: 5654/2015 | F17: A NOVA CONTABILIDADE APLICADA AO SETOR PÚBLICO | I17: Áreas Administrativas | J17: A.C.E - Programa de Gestão e Estratégia | L17: 11 a 15/05/2015 | M17: 42135 | N17: 42139 | O17: Instrutoria Interna | P17: 4992.74 | U17: 30 | X17: =SUM(U17:W17) -> 30 | Y17: 20 | AA17: ROMILDO ARAUJO DA SILVA
A18: InCompany | B18: 2015 | D18: Realizado | E18: 14060/2015 | F18: TREINAMENTO DO SISTEMA TERRAGEO | I18: Áreas Administrativas | J18: A.C.E - Programa de Gestão e Estratégia | L18: 22/05/2015 | M18: 42146 | N18: 42146 | O18: Instrutoria Externa | P18: 0 | U18: 15 | X18: =SUM(U18:W18) -> 15 | Y18: 8 | AA18: INSTRUTOR EXTERNO TERRACAP
A19: InCompany | B19: 2015 | D19: Realizado | E19: 1098/2015 | F19: EXCEL AVANÇADO | I19: Áreas Administrativas | J19: A.C.E - Programa de Análise de Dados | L19: 25/05/2015 01/06/2015 | M19: 42149 | N19: 42156 | O19: Instrutoria Externa | P19: 2630 | U19: 14 | X19: =SUM(U19:W19) -> 14 | Y19: 24 | AA19: Logus TI
A20: InCompany | B20: 2015 | D20: Realizado | E20: 12742/2015 | F20: TREINAMENTO SIGGO (Sistema Integrado de Contabilidade Governamental) | I20: Áreas Administrativas | J20: C.E - Programa de Orçamento e Finanças Públicas | L20: 08 a 12/06/2015 | M20: 42163 | N20: 42167 | O20: Instrutoria Interna | P20: 0 | U20: 14 | X20: =SUM(U20:W20) -> 14 | Y20: 20 | AA20: ROMULO MIRANDA ALVIM
A21: InCompany | B21: 2015 | D21: Realizado | E21: 13480/2015 | F21: GESTÃO E FISCALIZAÇÃO DE CONTRATOS ADMINISTRATIVOS - MÓDULO I | I21: Jurisdicionados | J21: C.E - Programa de Capacitação para Jurisdicionados Controladores sociais e Cidadãos | L21: 15 a 19/06/2015 | M21: 42170 | N21: 42174 | O21: Instrutoria Interna | P21: 4447.52 | V21: 49 | X21: =SUM(U21:W21) -> 49 | Y21: 20 | AA21: Roberto Dias Santiago
A22: InCompany | B22: 2015 | D22: Realizado | E22: 19283/2015 | F22: SEMINÁRIO ATUALIZAÇÃO EM LEGISLAÇÃO DE PESSOAL | I22: Áreas Administrativas | J22: A.C.E - Programa de Gestão e Estratégia | L22: 05 e 07/08/2015 | M22: 42221 | N22: 42223 | O22: Instrutoria Interna | P22: 0 | U22: 43 | X22: =SUM(U22:W22) -> 43 | Y22: 8 | AA22: INACIO MAGALHAES FILHO
A23: InCompany | B23: 2015 | D23: Realizado | E23: 22314/2015 | F23: METODOLOGIA DE CONSTRUÇÃO E ATUALIZAÇÃO DO TESAURO DE CONTAS DO DF | I23: Áreas Administrativas | J23: A.C.E - Programa de Análise de Dados | L23: 24 a 28/08/2015 | M23: 42240 | N23: 42244 | O23: Instrutoria Interna | P23: 2702.38 | U23: 25 | X23: =SUM(U23:W23) -> 25 | Y23: 20 | AA23: ANDREA FORTALEZA BRANDES DE SOUZA
A24: InCompany | B24: 2015 | D24: Realizado | E24: 17949/2015 | F24: RESPONSABILIDADE DE AGENTES PÚBLICOS E PRIVADOS PERANTE OS TRIBUNAIS DE CONTAS | I24: Áreas Administrativas | J24: C.E - Programa de Capacitação para Jurisdicionados Controladores sociais e Cidadãos | L24: 31/08/2015 a 04/09/2015 | M24: 42247 | N24: 42251 | O24: Instrutoria Externa | P24: 33600 | U24: 35 | X24: =SUM(U24:W24) -> 35 | Y24: 20 | AA24: Aprimora Treinamentos
A25: InCompany | B25: 2015 | D25: Realizado | E25: 23973/2015 | F25: TÉCNICAS DE AUDITORIA OPERACIONAL | I25: Controle Externo | J25: C.E - Programa de Auditoria e Fiscalização do Setor Público | L25: 14 a 18/09/2015 | M25: 42261 | N25: 42265 | O25: Instrutoria Externa | P25: 15000 | U25: 35 | X25: =SUM(U25:W25) -> 35 | Y25: 25 | AA25: Dagomar Henrique Limas
A26: InCompany | B26: 2015 | D26: Realizado | F26: LEGISLAÇÃO DE PESSOAL NO SETOR PÚBLICO COM ENFOQUE NA LC nº 840/2011 | I26: Jurisdicionados | J26: N/A | M26: 42268 | N26: 42272 | O26: Instrutoria Interna | P26: 4447.52 | U26: 87 | X26: =SUM(U26:W26) -> 87
A27: InCompany | B27: 2015 | D27: Realizado | E27: 29327/2015 | F27: CAPACITAÇÃO PARA CONSELHEIROS DE SAÚDE - Turma I | I27: Sociedade | J27: C.E - Programa de Capacitação para Jurisdicionados Controladores sociais e Cidadãos | L27: 29/09/2015 a 02/10/2015 | M27: 42276 | N27: 42279 | O27: Instrutoria Interna | P27: 4076.52 | W27: 46 | X27: =SUM(U27:W27) -> 46 | Y27: 20 | AA27: ROMILDO ARAUJO DA SILVA; TARSILA FIRMINO ELY
A28: InCompany | B28: 2015 | D28: Realizado | E28: 30040/2015 | F28: OFICINA DE ACCESS AVANÇADO | I28: Áreas Administrativas | J28: A.C.E - Programa de Análise de Dados | L28: 05 a 09/10/2015 | M28: 42282 | N28: 42286 | O28: Instrutoria Interna | P28: 4447.52 | U28: 15 | X28: =SUM(U28:W28) -> 15 | Y28: 20 | AA28: JOSDEYVI MAGALHAES RUSSI
A29: InCompany | B29: 2015 | D29: Realizado | E29: 13480/2015 | F29: GESTÃO E FISCALIZAÇÃO DE CONTRATOS ADMINISTRATIVOS - MÓDULO II | I29: Jurisdicionados | J29: C.E - Programa de Capacitação para Jurisdicionados Controladores sociais e Cidadãos | L29: 19 a 23/10/2015 | M29: 42296 | N29: 42300 | O29: Instrutoria Interna | P29: 4447.52 | V29: 54 | X29: =SUM(U29:W29) -> 54 | Y29: 20 | AA29: Roberto Dias Santiago
A30: InCompany | B30: 2015 | D30: Realizado | F30: CONTRATAÇÃO DE SOLUÇÕES DE TECNOLOGIA DA INFORMAÇÃO E COMUNICAÇÃO - IN nº 04/2014 | I30: Jurisdicionados | J30: N/A | M30: 42303 | N30: 42305 | O30: Instrutoria Interna | P30: 4447.52 | U30: 52 | X30: =SUM(U30:W30) -> 52 | Y30: 0
A31: InCompany | B31: 2015 | D31: Realizado | E31: 29327/2015 | F31: CAPACITAÇÃO PARA CONSELHEIROS DE SAÚDE - Turma II | I31: Sociedade | J31: C.E - Programa de Capacitação para Jurisdicionados Controladores sociais e Cidadãos | L31: 17 a 20/11/2015 | M31: 42325 | N31: 42328 | O31: Instrutoria Interna | P31: 4076.52 | W31: 46 | X31: =SUM(U31:W31) -> 46 | Y31: 20 | AA31: ROMILDO ARAUJO DA SILVA; TARSILA FIRMINO ELY
A32: InCompany | B32: 2015 | D32: Realizado | E32: 5891/2015 | F32: AUDITORIA EM OBRAS RODOVIÁRIAS | I32: Controle Externo | J32: C.E - Programa de Áreas Temáticas do Controle Externo | L32: 06 a 10/04/2015 | M32: 42466 | N32: 42104 | O32: Instrutoria Externa | P32: 29000 | U32: 19 | X32: =SUM(U32:W32) -> 19 | Y32: 40 | AA32: Elci Pessoa Júnior
A33: InCompany | B33: 2016 | D33: Realizado | E33: 13946/2016 | F33: Sistema Channel - Turma 1 | I33: Servidores do TCDF | J33: N/A | M33: 42495 | O33: Instrutoria Externa | P33: 0 | U33: 14 | X33: =SUM(U33:W33) -> 14 | Y33: 8 | AA33: Profº Breno (TCE-PE)
A34: InCompany | B34: 2016 | D34: Realizado | F34: Instrutoria | I34: Servidores do TCDF | J34: N/A | M34: 42495 | O34: Instrutoria Externa | P34: 22500 | U34: 25 | X34: =SUM(U34:W34) -> 25 | Y34: 20
A35: InCompany | B35: 2016 | D35: Realizado | E35: 30532/2016 . 28880/2016 (Pag) | F35: Trilhas de Aprendizagem | I35: Servidores do TCDF | J35: N/A | M35: 42495 | O35: Instrutoria Externa | P35: 25200 | U35: 17 | X35: =SUM(U35:W35) -> 17 | Y35: 20 | AA35: Pedro Paulo Carbone, Sylvio Maestrelli e Anelise Pereira Sihler
A36: InCompany | B36: 2016 | D36: Realizado | E36: 8721/2016 | F36: Termo de Referência de Serviços Continuados com dedicação exclusiva de mão de obra | I36: Jurisdicionados | J36: C.E - Programa de Capacitação para Jurisdicionados Controladores sociais e Cidadãos | L36: 16 a 20/05/2016 | M36: 42506 | N36: 42510 | O36: Instrutoria Interna | P36: 6671.48 | V36: 75 | X36: =SUM(U36:W36) -> 75 | Y36: 20 | AA36: LEONARDO JOSE ALVES LEAL NERI
A37: InCompany | B37: 2016 | D37: Realizado | E37: 16866/2016 | F37: Workshop para prefeitos comunitários | I37: Sociedade | J37: C.E - Programa de Capacitação para Jurisdicionados Controladores sociais e Cidadãos | L37: 13/06/2016 | M37: 42534 | N37: 42534 | O37: Instrutoria Interna | P37: 2668.6 | V37: 18 | X37: =SUM(U37:W37) -> 18 | Y37: 3 | AA37: LUIZ GENEDIO MENDES JORGE
A38: InCompany | B38: 2016 | D38: Realizado | E38: 8195/2016 | F38: Workshop sobre Parcerias Público-Privadas | I38: Sociedade | J38: C.E - Programa de Capacitação para Jurisdicionados Controladores sociais e Cidadãos | L38: 13 e 14/06/2016 | M38: 42534 | N38: 42535 | O38: Instrutoria Externa | P38: 0 | U38: 33 | X38: =SUM(U38:W38) -> 33 | Y38: 10 | AA38: Maria Aparecida Aiko Ikemura (TCE-MG)
A39: InCompany | B39: 2016 | D39: Realizado | E39: 12356/2016 | F39: Contratação Direta - Dispensa e Inexigibilidade de Licitação | I39: Jurisdicionados | J39: C.E - Programa de Capacitação para Jurisdicionados Controladores sociais e Cidadãos | L39: 13 a 17/06/2016 | M39: 42534 | N39: 42538 | O39: Instrutoria Interna | P39: 6671.48 | V39: 55 | X39: =SUM(U39:W39) -> 55 | Y39: 20 | AA39: Roberto Dias Santiago
A40: InCompany | B40: 2016 | D40: Realizado | E40: 16351/2016 | F40: Capacitação para Conselheiros de Saúde | I40: Sociedade | J40: C.E - Programa de Auditoria e Fiscalização do Setor Público | L40: 27/06/2016 a 01/07/2016 | M40: 42548 | N40: 42552 | O40: Instrutoria Interna | P40: 7080.23 | W40: 45 | X40: =SUM(U40:W40) -> 45 | Y40: 20 | AA40: ROMILDO ARAUJO DA SILVA; TARSILA FIRMINO ELY
A41: InCompany | B41: 2016 | D41: Realizado | E41: 13816/2016 | F41: Access básico aplicado ao SIGGO | I41: Áreas Administrativas | J41: A.C.E - Programa de Análise de Dados | L41: 27/06/2016 a 01/07/2016 | M41: 42548 | N41: 42552 | O41: Instrutoria Interna | P41: 6671.48 | U41: 15 | X41: =SUM(U41:W41) -> 15 | Y41: 20 | AA41: ROMULO MIRANDA ALVIM
A42: InCompany | B42: 2016 | D42: Realizado | E42: 15487/2016 | F42: Acompanhamento do Orçamento Público – Jornalistas | I42: Sociedade | J42: C.E - Programa de Capacitação para Jurisdicionados Controladores sociais e Cidadãos | L42: 28/06/2016 a 30/06/2016 | M42: 42549 | N42: 42551 | O42: Instrutoria Interna | P42: 1334.3 | W42: 21 | X42: =SUM(U42:W42) -> 21 | Y42: 8 | AA42: LUIZ GENEDIO MENDES JORGE
A43: InCompany | B43: 2016 | D43: Realizado | E43: 14910/2016 | F43: Curso de Educação Financeira | I43: Servidores do TCDF | J43: PTs - Programa de Desenvolvimento Individual | L43: 20 e 21/07/2016 | M43: 42571 | N43: 42572 | O43: Instrutoria Externa | P43: 0 | U43: 40 | X43: =SUM(U43:W43) -> 40 | Y43: 9 | AA43: BRB
A44: InCompany | B44: 2016 | D44: Realizado | E44: 20995/2016 | F44: Governança e gestão de TIC - Melhores práticas de mercado | I44: Jurisdicionados | J44: C.E - Programa de Capacitação para Jurisdicionados Controladores sociais e Cidadãos | L44: 01 e 02/08/2016 | M44: 42583 | N44: 42584 | O44: Instrutoria Interna | P44: 2668.6 | V44: 45 | X44: =SUM(U44:W44) -> 45 | Y44: 8 | AA44: EVERTON PEIXOTO CORREIA DE ASSUMPCAO
A45: InCompany | B45: 2016 | D45: Realizado | E45: 13794/2016 | F45: Oficina de Access Intermediário | I45: Servidores do TCDF | J45: A.C.E - Programa de Análise de Dados | L45: 08 a 12/08/2016 | M45: 42590 | N45: 42594 | O45: Instrutoria Interna | P45: 7488.98 | U45: 13 | X45: =SUM(U45:W45) -> 13 | Y45: 20 | AA45: JOSDEYVI MAGALHAES RUSSI
A46: InCompany | B46: 2016 | D46: Realizado | E46: 13832/2016 | F46: Elaboração de Relatórios e Pareceres com base no manual de redação do Tribunal de Contas do Distrito Federal - Turma 1 | I46: Servidores do TCDF | J46: PTs - Programa de Desenvolvimento Individual | L46: 15 a 19/08/2016 | M46: 42597 | N46: 42601 | O46: Instrutoria Externa | P46: 7880 | U46: 35 | X46: =SUM(U46:W46) -> 35 | Y46: 20 | AA46: Profª Paula Cobucci
A47: InCompany | B47: 2016 | D47: Realizado | E47: 23447/2016 | F47: Processo de Contratação Pública na área de Saúde – Termos de Referência | I47: Jurisdicionados | J47: C.E - Programa de Capacitação para Jurisdicionados Controladores sociais e Cidadãos | L47: 15 a 19/08/2016 | M47: 42597 | N47: 42601 | O47: Híbrida | P47: 9556.7 | U47: 8 | V47: 63 | X47: =SUM(U47:W47) -> 71 | Y47: 20 | AA47: Tarsila Firmino Ely;ROMILDO ARAUJO DA SILVA;Luiz Eduardo Costa
A48: InCompany | B48: 2016 | D48: Realizado | E48: 2251/2016 | F48: XXII SEMAT | I48: Híbrido | J48: C.E - Programa de Capacitação para Jurisdicionados Controladores sociais e Cidadãos | L48: 31/08 e 01/09/2016 | M48: 42613 | N48: 42614 | O48: Instrutoria Externa | P48: 44423.6 | U48: 87 | V48: 242 | W48: 0 | X48: =SUM(U48:W48) -> 329 | Y48: 8 | AA48: Ives Gandra da Silva Martins Filho, Pedro Jorge Simon, Renato Rainha, Luiz Genédio Mendes Jorge, Henrique Moraes Ziller, Maria Rosynete de Oliveira e Eliana Calmon
A49: InCompany | B49: 2016 | D49: Realizado | E49: 24427/2016 | F49: Gestão de Processos | I49: Servidores do TCDF | J49: A.C.E - Programa de Gestão e Estratégia | L49: 12 a 16/09/2016 | M49: 42625 | N49: 42629 | O49: Instrutoria Externa | P49: 9200 | U49: 26 | X49: =SUM(U49:W49) -> 26 | Y49: 20 | AA49: Profº Annibal
A50: InCompany | B50: 2016 | D50: Realizado | E50: 26365/2016 | F50: Orçamento Público | I50: Servidores do TCDF | J50: C.E - Programa de Orçamento e Finanças Públicas | L50: 19 a 23/09/2016 | M50: 42632 | N50: 42636 | O50: Instrutoria Externa | P50: 5900 | U50: 35 | X50: =SUM(U50:W50) -> 35 | Y50: 20 | AA50: Profº Rita (SENADO)
A51: InCompany | B51: 2016 | D51: Realizado | E51: 3169/2016 | F51: Gestão e fiscalização de contratos adm. - M1, Turma 1 | I51: Jurisdicionados | J51: C.E - Programa de Capacitação para Jurisdicionados Controladores sociais e Cidadãos | L51: 19 a 23/09/2016 | M51: 42632 | N51: 42636 | O51: Instrutoria Interna | P51: 6671.48 | V51: 46 | X51: =SUM(U51:W51) -> 46 | Y51: 20 | AA51: Roberto Dias Santiago
A52: InCompany | B52: 2016 | D52: Realizado | E52: 3169/2016 | F52: Gestão e fiscalização de contratos adm. - M2, Turma 1 | I52: Jurisdicionados | J52: C.E - Programa de Capacitação para Jurisdicionados Controladores sociais e Cidadãos | L52: 19 a 23/09/2016 | M52: 42632 | N52: 42636 | O52: Instrutoria Interna | P52: 6671.48 | V52: 52 | X52: =SUM(U52:W52) -> 52 | Y52: 20 | AA52: Roberto Dias Santiago
A53: InCompany | B53: 2016 | D53: Realizado | E53: 26373/2016 | F53: Regime Próprio de Previdência Social | I53: Servidores do TCDF | J53: PTs - Programa de Desenvolvimento Individual | L53: 03 a 07/10/2016 | M53: 42646 | N53: 42650 | O53: Instrutoria Interna | P53: 8088.22 | U53: 34 | X53: =SUM(U53:W53) -> 34 | Y53: 20 | AA53: Michel Martins de Morais
A54: InCompany | B54: 2016 | D54: Realizado | E54: 18508/2016 | F54: Como elaborar a planilha de formação de preços da IN nº 02/08 e como julgar a licitação para a contratação dos serviços contínuos | I54: Controle Externo | J54: C.E - Programa de Auditoria e Fiscalização do Setor Público | L54: 17 a 19/10/2016 | M54: 42660 | N54: 42662 | O54: Instrutoria Externa | P54: 54183.63 | U54: 27 | X54: =SUM(U54:W54) -> 27 | Y54: 15 | AA54: Zênite Informação e Consultoria
A55: InCompany | B55: 2016 | D55: Realizado | E55: 30532/2016 | F55: Aprendizagem Organizacional | I55: Áreas Administrativas | J55: A.C.E - Programa de Gestão e Estratégia | L55: 20, 21, 24, 27 e 28/10/2016 | M55: 42663 | N55: 42671 | O55: Instrutoria Externa | P55: 22500 | U55: 16 | X55: =SUM(U55:W55) -> 16 | Y55: 20 | AA55: Pedro Paulo Carbone e Sylvio Maestrelliv- Inteletto
A56: InCompany | B56: 2016 | D56: Realizado | E56: 28597/2016 | F56: Contratação de TI com base na jurisprudência do TCDF | I56: Jurisdicionados | J56: C.E - Programa de Capacitação para Jurisdicionados Controladores sociais e Cidadãos | L56: 24 a 26/10/2016 | M56: 42667 | N56: 42669 | O56: Instrutoria Interna | P56: 4002.88 | V56: 55 | X56: =SUM(U56:W56) -> 55 | Y56: 12 | AA56: Marcelo Oliveira Vasconcelos
A57: InCompany | B57: 2016 | D57: Realizado | E57: 29925/2016 | F57: Excel Avançado | I57: Servidores do TCDF | J57: A.C.E - Programa de Análise de Dados | L57: 07 a 11/11/2016 | M57: 42681 | N57: 42685 | O57: Instrutoria Interna | P57: 8088.22 | U57: 14 | X57: =SUM(U57:W57) -> 14 | Y57: 20 | AA57: JOSDEYVI MAGALHAES RUSSI
A58: InCompany | B58: 2016 | D58: Realizado | E58: 30869/2016 | F58: Legislação de Pessoal no Setor Público com enfoque na LC 840/2011 | I58: Jurisdicionados | J58: C.E - Programa de Capacitação para Jurisdicionados Controladores sociais e Cidadãos | L58: 07 a 11/11/2016 | M58: 42681 | N58: 42685 | O58: Instrutoria Interna | P58: 6671.48 | V58: 47 | X58: =SUM(U58:W58) -> 47 | Y58: 20 | AA58: SEBASTIAO CAL DE MIRANDA
A59: InCompany | B59: 2016 | D59: Realizado | E59: 30354/2016 | F59: Elaboração de Relatórios e Pareceres com base no Manual de Redação Oficial do TCDF - Turma 2 | I59: Servidores do TCDF | J59: PTs - Programa de Desenvolvimento Individual | L59: 21, 22, 23, 24 e 28/11/2016 | M59: 42695 | N59: 42702 | O59: Instrutoria Externa | P59: 7880 | U59: 31 | X59: =SUM(U59:W59) -> 31 | Y59: 20 | AA59: Profª Paula Cobucci
A60: InCompany | B60: 2016 | D60: Realizado | E60: 9272/2016 | F60: Gestão e fiscalização de contratos adm. - M2, Turma 2 | I60: Jurisdicionados | J60: C.E - Programa de Capacitação para Jurisdicionados Controladores sociais e Cidadãos | L60: 21 a 25/11/2016 | M60: 42695 | N60: 42699 | O60: Instrutoria Interna | P60: 5612 | V60: 28 | X60: =SUM(U60:W60) -> 28 | Y60: 20 | AA60: Roberto Dias Santiago
A61: InCompany | B61: 2016 | D61: Realizado | E61: 9272/2016 | F61: Gestão e fiscalização de contratos adm. - M1, Turma 2 | I61: Jurisdicionados | J61: C.E - Programa de Capacitação para Jurisdicionados Controladores sociais e Cidadãos | L61: 21 a 25/11/2016 | M61: 42695 | N61: 42699 | O61: Instrutoria Interna | P61: 5612 | V61: 34 | X61: =SUM(U61:W61) -> 34 | Y61: 20 | AA61: Roberto Dias Santiago
A62: InCompany | B62: 2016 | D62: Realizado | E62: 32080/16 | F62: Contratação e Fiscalização de Obras Públicas - Aspectos Polêmicos | I62: Jurisdicionados | J62: C.E - Programa de Capacitação para Jurisdicionados Controladores sociais e Cidadãos | L62: 05 a 07/12/2016 | M62: 42709 | N62: 42711 | O62: Instrutoria Interna | P62: 8000 | V62: 60 | X62: =SUM(U62:W62) -> 60 | Y62: 20 | AA62: ADRIANA CUOCO PORTUGAL; MARCOS GARCIA DA SILVA PINTO
A63: InCompany | B63: 2017 | D63: Realizado | E63: 30532/2016 | F63: Instrutoria - Turma 2 | I63: Áreas Administrativas | J63: A.C.E - Programa de Gestão e Estratégia | L63: 06, 07, 08, 20, 21/02/2018 | M63: 42773 | N63: 42788 | O63: Instrutoria Externa | P63: 27300 | U63: 29 | X63: =SUM(U63:W63) -> 29 | Y63: 26 | AA63: Carbone, Sylvio - Inteletto
A64: InCompany | B64: 2017 | D64: Realizado | E64: 30532/2016 | F64: Tutoria em EAD | I64: Áreas Administrativas | J64: A.C.E - Programa de Gestão e Estratégia | L64: 06 e 31/03/2017 | M64: 42800 | N64: 42825 | O64: Instrutoria Externa | P64: 54300 | U64: 26 | X64: =SUM(U64:W64) -> 26 | Y64: 30 | AA64: Pedro Paulo Carbone, Sylvio Maestrelli e Anelise Pereira Sihler
A65: InCompany | B65: 2017 | D65: Realizado | E65: 3164/2017 | F65: Gestão e Fiscalização de Contratos Adm. - M1 | I65: Jurisdicionados | J65: C.E - Programa de Capacitação para Jurisdicionados Controladores sociais e Cidadãos | L65: 13 a 17/03/2017 | M65: 42807 | N65: 42811 | O65: Instrutoria Interna | P65: 6962.15 | V65: 47 | X65: =SUM(U65:W65) -> 47 | Y65: 20 | AA65: Roberto Dias Santiago
A66: InCompany | B66: 2017 | D66: Realizado | E66: 2265/2017 | F66: Excel Avançado - I | I66: Servidores do TCDF | J66: A.C.E - Programa de Análise de Dados | L66: 20 a 24/03/2017 | M66: 42814 | N66: 42818 | O66: Instrutoria Interna | P66: 7466.41 | U66: 20 | X66: =SUM(U66:W66) -> 20 | Y66: 20 | AA66: JOSDEYVI MAGALHAES RUSSI
A67: InCompany | B67: 2017 | D67: Realizado | E67: 4730/2017 | F67: Gestão e Fiscalização de Contratos - Serviços | I67: Jurisdicionados | J67: C.E - Programa de Capacitação para Jurisdicionados Controladores sociais e Cidadãos | L67: 27 a 31/03/2017 | M67: 42821 | N67: 42825 | O67: Instrutoria Interna | P67: 6962.15 | V67: 43 | X67: =SUM(U67:W67) -> 43 | Y67: 20 | AA67: LEONARDO JOSE ALVES LEAL NERI
A68: InCompany | B68: 2017 | D68: Realizado | E68: 3784/2017 | F68: Regime Próprio da Previdência | I68: Servidores do TCDF | J68: PTs - Programa de Desenvolvimento Individual | L68: 27 a 31/03/2017 | M68: 42821 | N68: 42825 | O68: Instrutoria Interna | P68: 7241.74 | U68: 15 | X68: =SUM(U68:W68) -> 15 | Y68: 20 | AA68: Michel Martins de Morais
A69: InCompany | B69: 2017 | D69: Realizado | E69: 997/2017 | F69: Formulação e Avaliação de Políticas Públicas com foco no Controle Externo | I69: Controle Externo | J69: C.E - Programa de Áreas Temáticas do Controle Externo | L69: 03 a 07/04/2017 | M69: 42828 | N69: 42832 | O69: Instrutoria Externa | P69: 7950 | U69: 29 | X69: =SUM(U69:W69) -> 29 | Y69: 20 | AA69: Pedro Luiz Costa Cavalcante
A70: InCompany | B70: 2017 | D70: Realizado | E70: 3164/2017 | F70: Gestão e Fiscalização de Contratos Adm. - M2 | I70: Jurisdicionados | J70: C.E - Programa de Capacitação para Jurisdicionados Controladores sociais e Cidadãos | L70: 24 a 28/04/2017 | M70: 42849 | N70: 42853 | O70: Instrutoria Interna | P70: 6962.15 | V70: 46 | X70: =SUM(U70:W70) -> 46 | Y70: 20 | AA70: Roberto Dias Santiago
A71: InCompany | B71: 2017 | D71: Realizado | E71: 30532/2017 | F71: Instrutoria - Turma 3 | I71: Servidores do TCDF | J71: N/A | M71: 42860 | N71: 42860 | O71: Instrutoria Externa | P71: 27300 | U71: 14 | X71: =SUM(U71:W71) -> 14 | Y71: 26 | AA71: Carbone, Sylvio - Inteletto
A72: InCompany | B72: 2017 | D72: Realizado | E72: 13946/2017 | F72: Sistema Channel - Turma 2 | I72: Servidores do TCDF | J72: N/A | M72: 42860 | N72: 42860 | O72: Instrutoria Externa | P72: 0 | U72: 12 | X72: =SUM(U72:W72) -> 12 | Y72: 8 | AA72: Profº Breno (TCE-PE)
A73: InCompany | B73: 2017 | D73: Realizado | E73: 8964/2017 | F73: Excel Avançado - II | I73: Servidores do TCDF | J73: A.C.E - Programa de Análise de Dados | L73: 08 a 12/05/2017 | M73: 42863 | N73: 42136 | O73: Instrutoria Interna | P73: 7241.74 | U73: 18 | X73: =SUM(U73:W73) -> 18 | Y73: 20 | AA73: JOSDEYVI MAGALHAES RUSSI
A74: InCompany | B74: 2017 | D74: Realizado | E74: 2001/2017 | F74: Processo nos Tribunais de Contas: Acusação, Contraditório, Julgamento e Recursos | I74: Servidores do TCDF | J74: C.E - Programa de Auditoria e Fiscalização do Setor Público | L74: 15 a 19/05/2017 | M74: 42870 | N74: 42874 | O74: Instrutoria Externa | P74: 33600 | U74: 30 | X74: =SUM(U74:W74) -> 30 | Y74: 20 | AA74: Odilon Cavallari de Oliveira
A75: InCompany | B75: 2017 | D75: Realizado | E75: 6120/2017 | F75: Capacitação para Conselheiros de Cultura | I75: Sociedade | J75: C.E - Programa de Capacitação para Jurisdicionados Controladores sociais e Cidadãos | L75: 22 a 26/05/2017 | M75: 42877 | N75: 42881 | O75: Instrutoria Interna | P75: 0 | W75: 37 | X75: =SUM(U75:W75) -> 37 | Y75: 20 | AA75: Carlos Augusto Pereira da Silva
A76: InCompany | B76: 2017 | D76: Realizado | E76: 11354/2017 | F76: Legislação de Pessoal no Setor Público, com enfoque na LC 840/2011 | I76: Jurisdicionados | J76: C.E - Programa de Capacitação para Jurisdicionados Controladores sociais e Cidadãos | L76: 22 a 26/05/2017 | M76: 42877 | N76: 42881 | O76: Instrutoria Interna | P76: 6962.15 | V76: 47 | X76: =SUM(U76:W76) -> 47 | Y76: 20 | AA76: SEBASTIAO CAL DE MIRANDA
A77: InCompany | B77: 2017 | D77: Realizado | E77: 11460/2017 | F77: Tomada de Contas Especial | I77: Controle Externo | J77: C.E - Programa de Auditoria e Fiscalização do Setor Público | L77: 25 e 26/05/2017 | M77: 42880 | N77: 42881 | O77: Instrutoria Externa | P77: 8000 | U77: 30 | X77: =SUM(U77:W77) -> 30 | Y77: 16 | AA77: Guilherme Henrique De La Rocque Almeida
A78: InCompany | B78: 2017 | D78: Realizado | E78: 4675/2017 | F78: Oratória - Turma 1 | I78: Servidores do TCDF | J78: PTs - Programa de Desenvolvimento Individual | L78: 25 a 26/05/2017 | M78: 42880 | N78: 42881 | O78: Instrutoria Externa | P78: 7880 | U78: 19 | X78: =SUM(U78:W78) -> 19 | Y78: 20 | AA78: Paula Cobucci
A79: InCompany | B79: 2017 | D79: Realizado | E79: 14086/2017 | F79: Contratação de Soluções de Tecnologia da Informação e Comunicação - TIC - T.1 | I79: Jurisdicionados | J79: C.E - Programa de Capacitação para Jurisdicionados Controladores sociais e Cidadãos | L79: 26 a 29/05/2017 | M79: 42881 | N79: 42884 | O79: Instrutoria Interna | P79: 5569.72 | V79: 37 | X79: =SUM(U79:W79) -> 37 | Y79: 16 | AA79: ADINOR BEDRITICHUK JUNIOR; EVERTON PEIXOTO CORREIA DE ASSUMPCAO; FLAVIO JOSE FONSECA DE SOUZA
A80: InCompany | B80: 2017 | D80: Realizado | E80: 4675/2017 | F80: Oratória - Turma 2 | I80: Servidores do TCDF | J80: PTs - Programa de Desenvolvimento Individual | L80: 05 a 09/06/2017 | M80: 42891 | N80: 42895 | O80: Instrutoria Externa | P80: 7880 | U80: 19 | X80: =SUM(U80:W80) -> 19 | Y80: 20 | AA80: Paula Cobucci
A81: InCompany | B81: 2017 | D81: Realizado | E81: 7690/2017 | F81: PPP - Análise Econômica e Financeira no Excel | I81: Servidores do TCDF | J81: A.C.E - Programa de Análise de Dados | L81: 19 a 23/06/2017 | M81: 42905 | N81: 42909 | O81: Instrutoria Interna | P81: 8547.4 | U81: 20 | X81: =SUM(U81:W81) -> 20 | Y81: 20 | AA81: Orivam Ibiapina da Silva
A82: InCompany | B82: 2017 | D82: Realizado | E82: 13128/2017 | F82: Capacitação Especial para Promoção Funcional | I82: Servidores do TCDF | J82: PTs - Programa de Ambientação e Desenvolvimento na Carreira | L82: 23 e 28/06/2017, 8 a 11/08/2017 e 16/08/2017 | M82: 42909 | N82: 42963 | O82: Instrutoria Interna | P82: 11567.86 | U82: 50 | X82: =SUM(U82:W82) -> 50 | Y82: 20 | AA82: Agnaldo Moreira Marques;DELSO FERREIRA DA SILVA JUNIOR;EMILIO VINHADELLI PAPADOPOLIS; Henrique Mattei;LUCIENE DE FATIMA CARVALHO TEODORO;Paulo Alves Honorato;ROMULO MIRANDA ALVIM;SERGIO ARAUJO DE AMORIM LOPES
A83: InCompany | B83: 2017 | D83: Realizado | E83: 4764/2017 | F83: Gestão de Processos | I83: Servidores do TCDF | J83: A.C.E - Programa de Gestão e Estratégia | L83: 26 a 30/06/2017 | M83: 42912 | N83: 42916 | O83: Instrutoria Externa | P83: 9780 | U83: 17 | X83: =SUM(U83:W83) -> 17 | Y83: 20 | AA83: Annibal
A84: InCompany | B84: 2017 | D84: Realizado | E84: 14060/2017 | F84: Capacitação para Conselheiros de Saúde | I84: Sociedade | J84: C.E - Programa de Capacitação para Jurisdicionados Controladores sociais e Cidadãos | L84: 03 a 07/072017 | M84: 42919 | N84: 42923 | O84: Instrutoria Interna | P84: 7231.26 | W84: 49 | X84: =SUM(U84:W84) -> 49 | Y84: 20 | AA84: ROMILDO ARAUJO DA SILVA; TARSILA FIRMINO ELY
A85: InCompany | B85: 2017 | D85: Realizado | E85: 20884/17 | F85: Planilha de Terceirização de Mão de Obra - T.2 | I85: Jurisdicionados | J85: C.E - Programa de Capacitação para Jurisdicionados Controladores sociais e Cidadãos | L85: 24 a 28/07/2017 | M85: 42940 | N85: 42944 | O85: Instrutoria Interna | P85: 6008.6 | V85: 34 | X85: =SUM(U85:W85) -> 34 | Y85: 20 | AA85: LEONARDO JOSE ALVES LEAL NERI
A86: InCompany | B86: 2017 | D86: Realizado | E86: 12741/2017 | F86: Planilha de Terceirização de Mão de Obra - T.1 | I86: Jurisdicionados | J86: C.E - Programa de Capacitação para Jurisdicionados Controladores sociais e Cidadãos | L86: 26 a 30/06/2017 | M86: 42942 | N86: 42916 | O86: Instrutoria Interna | P86: 6962.15 | V86: 25 | X86: =SUM(U86:W86) -> 25 | Y86: 20 | AA86: LEONARDO JOSE ALVES LEAL NERI
A87: InCompany | B87: 2017 | D87: Realizado | E87: 13098/2017 | F87: Excel Avançado - III | I87: Servidores do TCDF | J87: A.C.E - Programa de Análise de Dados | L87: 21 a 25/08/2017 | M87: 42968 | N87: 42972 | O87: Instrutoria Interna | P87: 7603.8 | U87: 19 | X87: =SUM(U87:W87) -> 19 | Y87: 20 | AA87: JOSDEYVI MAGALHAES RUSSI
A88: InCompany | B88: 2017 | D88: Realizado | E88: 3199/2017 | F88: XXIII SEMAT | I88: Jurisdicionados | J88: C.E - Programa de Capacitação para Jurisdicionados Controladores sociais e Cidadãos | L88: 29 e 30/08/17 | M88: 42976 | N88: 42977 | O88: Instrutoria Externa | P88: 40881.51 | U88: 100 | V88: 212 | W88: 0 | X88: =SUM(U88:W88) -> 312 | Y88: 8 | AA88: Roberto Ellery, Marcos Mendes, Maria Lúcia Fattorelli , Fábio Henrique Granja e Barros, Adler Anaximandro de Cruz e Alves, Daniel Soares Godoi Gomes de Oliveira, Samy Dana
A89: InCompany | B89: 2017 | D89: Realizado | E89: 24014/2017 | F89: Contratação Direta - Dispensa e Inexigibilidade de Licitação sob o enfoque da Lei n° 8666/1993 | I89: Jurisdicionados | J89: C.E - Programa de Capacitação para Jurisdicionados Controladores sociais e Cidadãos | L89: 11 a 15/09/2017 | M89: 42989 | N89: 42993 | O89: Instrutoria Interna | P89: 7452.02 | V89: 57 | X89: =SUM(U89:W89) -> 57 | Y89: 20 | AA89: Roberto Dias Santiago
A90: InCompany | B90: 2017 | D90: Realizado | E90: 26440/2017 | F90: Lei das Estatais | I90: Jurisdicionados | J90: C.E - Programa de Capacitação para Jurisdicionados Controladores sociais e Cidadãos | L90: 25 a 29/09/2017 | M90: 43003 | N90: 43007 | O90: Instrutoria Interna | P90: 7510.44 | V90: 50 | X90: =SUM(U90:W90) -> 50 | Y90: 20 | AA90: Roberto Dias Santiago
A91: InCompany | B91: 2017 | D91: Realizado | E91: 25185/2017 | F91: Impactos do Novo Sicro no Orçamento de Obras Rodoviárias | I91: Controle Externo | J91: C.E - Programa de Áreas Temáticas do Controle Externo | L91: 17 a 18/10/2017 | M91: 43025 | N91: 43026 | O91: Instrutoria Externa | P91: 19780 | U91: 18 | X91: =SUM(U91:W91) -> 18 | Y91: 20 | AA91: New Roads - Elci Júnior
A92: InCompany | B92: 2017 | D92: Realizado | E92: 29563/2017 | F92: Boas Práticas para uma Atuação Eficiente dos Executores de Contratos Administrativos | I92: Áreas Administrativas | J92: A.C.E - Programa de Gestão e Estratégia | L92: 23 a 27/10/2017 | M92: 43031 | N92: 43035 | O92: Instrutoria Interna | P92: 7452.02 | U92: 18 | X92: =SUM(U92:W92) -> 18 | Y92: 20 | AA92: CLEUSA MARTINS PITANGA;PAOLA KARINA DE BARRON SALES
A93: InCompany | B93: 2017 | D93: Realizado | E93: 17964/2017 | F93: Regularidade nos Processo de Aquisição / Manutenção de Equipamentos médico-hospitalares – Termos de Referência | I93: Jurisdicionados | J93: C.E - Programa de Capacitação para Jurisdicionados Controladores sociais e Cidadãos | L93: 23 a 27/10/2017 | M93: 43031 | N93: 43035 | O93: Híbrida | P93: 10272.4 | V93: 40 | X93: =SUM(U93:W93) -> 40 | Y93: 20 | AA93: TARSILA FIRMINO ELY;Luiz Eduardo Costa*
A94: InCompany | B94: 2017 | D94: Realizado | E94: 31223/2017 | F94: Contratação de Soluções de Tecnologia da Informação e Comunicação - TIC - T.2 | I94: Jurisdicionados | J94: C.E - Programa de Capacitação para Jurisdicionados Controladores sociais e Cidadãos | L94: 06 a 09/11/2017 | M94: 43045 | N94: 43048 | O94: Instrutoria Interna | P94: 5961.61 | V94: 37 | X94: =SUM(U94:W94) -> 37 | Y94: 16 | AA94: ADINOR BEDRITICHUK JUNIOR; EVERTON PEIXOTO CORREIA DE ASSUMPCAO; FLAVIO JOSE FONSECA DE SOUZA
A95: InCompany | B95: 2018 | D95: Realizado | E95: 5529/18 | F95: Capacitação para Conselheiros de Saúde | I95: Sociedade | J95: C.E - Programa de Capacitação para Jurisdicionados Controladores sociais e Cidadãos | L95: 20 e 21/03/2018 | M95: 43179 | N95: 43180 | O95: Instrutoria Interna | P95: 5647.92 | W95: 96 | X95: =SUM(U95:W95) -> 96 | Y95: 20 | AA95: Tarsila Firmino Ely
A96: InCompany | B96: 2018 | D96: Realizado | E96: 13475/2018 | F96: SAS aplicado ao Controle Externo (Turma 2) | I96: Servidores do TCDF | J96: A.C.E - Programa de Análise de Dados | L96: 02 a 06/04/2018 | M96: 43192 | N96: 43196 | O96: Instrutoria Interna | P96: 13018.48 | U96: 19 | X96: =SUM(U96:W96) -> 19 | Y96: 20 | AA96: ROMULO MIRANDA ALVIM
A97: InCompany | B97: 2018 | D97: Realizado | E97: 6835/18 | F97: Gestão e Fiscalização de Contratos Adm. - M1, Turma 1 | I97: Jurisdicionados | J97: C.E - Programa de Capacitação para Jurisdicionados Controladores sociais e Cidadãos | L97: 09 a 13/04/2018 | M97: 43199 | N97: 43203 | O97: Instrutoria Interna | P97: 7310.2 | V97: 65 | X97: =SUM(U97:W97) -> 65 | Y97: 20 | AA97: Roberto Dias Santiago
A98: InCompany | B98: 2018 | D98: Realizado | E98: 25059/2016 | F98: Oficina de SAS | I98: Servidores do TCDF | J98: N/A | K98: Interno | M98: 43225 | N98: 43225 | O98: Instrutoria Externa | P98: 0 | U98: 19 | X98: =SUM(U98:W98) -> 19 | Y98: 8 | AA98: ROMULO MIRANDA ALVIM
A99: InCompany | B99: 2018 | D99: Realizado | E99: 6797/2018 | F99: Oratória e Técnicas de Apresentação Corporativa (Turma 1) | I99: Servidores do TCDF | J99: PTs - Programa de Desenvolvimento Individual | L99: 07, 08, 09 e 11/05/2018 | M99: 43227 | N99: 43231 | O99: Instrutoria Externa | P99: 7690 | U99: 19 | X99: =SUM(U99:W99) -> 19 | Y99: 16 | AA99: Paula Cobucci
A100: InCompany | B100: 2018 | D100: Realizado | E100: 8374/2018 | F100: SAS aplicado ao Controle Externo (Turma 1) | I100: Servidores do TCDF | J100: A.C.E - Programa de Análise de Dados | L100: 14 a 18/05/2018 | M100: 43234 | N100: 43238 | O100: Instrutoria Interna | P100: 7510.44 | U100: 20 | X100: =SUM(U100:W100) -> 20 | Y100: 20 | AA100: ROMULO MIRANDA ALVIM
...
